Workbook

Sheet 1-BRL PP Chart
A1: Data | C1: Mês | D1: Real (jul/94 a ago/26) | E1: Real (jul/94 a mar/25) | F1: Taxa de Inflação Mensal | G1: Taxa de Inflação Mensal | H1: Var. Anual | I1: Var. Anual
A2: 15615 | C2: 34486 | D2: =+'BRL e USD Chart'!$D2 -> 100 | E2: =+'BRL e USD Chart'!$D2 -> 100
A3: 15646 | C3: 34516 | D3: =+'BRL e USD Chart'!$D3 -> 93.597903 | E3: =+'BRL e USD Chart'!$D3 -> 93.597903 | F3: =+E3/E2-1 -> -0.064020966 | G3: =+F3 -> -0.064020966
A4: 15676 | C4: 34547 | D4: =+'BRL e USD Chart'!$D4 -> 91.888772 | E4: =+'BRL e USD Chart'!$D4 -> 91.888772 | F4: =+E4/E3-1 -> -0.018260357 | G4: =+F4 -> -0.018260357
A5: 15707 | C5: 34578 | D5: =+'BRL e USD Chart'!$D5 -> 90.50406 | E5: =+'BRL e USD Chart'!$D5 -> 90.50406 | F5: =+E5/E4-1 -> -0.015069438 | G5: =+F5 -> -0.015069438
A6: 15738 | C6: 34608 | D6: =+'BRL e USD Chart'!$D6 -> 88.193393 | E6: =+'BRL e USD Chart'!$D6 -> 88.193393 | F6: =+E6/E5-1 -> -0.025531086 | G6: =+F6 -> -0.025531086
A7: 15766 | C7: 34639 | D7: =+'BRL e USD Chart'!$D7 -> 85.782894 | E7: =+'BRL e USD Chart'!$D7 -> 85.782894 | F7: =+E7/E6-1 -> -0.027331972 | G7: =+F7 -> -0.027331972
A8: 15797 | C8: 34669 | D8: =+'BRL e USD Chart'!$D8 -> 84.340668 | E8: =+'BRL e USD Chart'!$D8 -> 84.340668 | F8: =+E8/E7-1 -> -0.016812506 | G8: =+F8 -> -0.016812506
A9: 15827 | C9: 34700 | D9: =+'BRL e USD Chart'!$D9 -> 82.930844 | E9: =+'BRL e USD Chart'!$D9 -> 82.930844 | F9: =+E9/E8-1 -> -0.016715831 | G9: =+F9 -> -0.016715831
A10: 15858 | C10: 34731 | D10: =+'BRL e USD Chart'!$D10 -> 82.093491 | E10: =+'BRL e USD Chart'!$D10 -> 82.093491 | F10: =+E10/E9-1 -> -0.01009701 | G10: =+F10 -> -0.01009701
A11: 15888 | C11: 34759 | D11: =+'BRL e USD Chart'!$D11 -> 80.840463 | E11: =+'BRL e USD Chart'!$D11 -> 80.840463 | F11: =+E11/E10-1 -> -0.015263417 | G11: =+F11 -> -0.015263417
A12: 15919 | C12: 34790 | D12: =+'BRL e USD Chart'!$D12 -> 78.922643 | E12: =+'BRL e USD Chart'!$D12 -> 78.922643 | F12: =+E12/E11-1 -> -0.023723519 | G12: =+F12 -> -0.023723519
A13: 15950 | C13: 34820 | D13: =+'BRL e USD Chart'!$D13 -> 76.870209 | E13: =+'BRL e USD Chart'!$D13 -> 76.870209 | F13: =+E13/E12-1 -> -0.026005649 | G13: =+F13 -> -0.026005649
A14: 15980 | C14: 34851 | D14: =+'BRL e USD Chart'!$D14 -> 75.171336 | E14: =+'BRL e USD Chart'!$D14 -> 75.171336 | F14: =+E14/E13-1 -> -0.022100528 | G14: =+F14 -> -0.022100528 | H14: =+E14/E2-1 -> -0.24828664 | I14: =+H14 -> -0.24828664
A15: 16011 | C15: 34881 | D15: =+'BRL e USD Chart'!$D15 -> 73.438195 | E15: =+'BRL e USD Chart'!$D15 -> 73.438195 | F15: =+E15/E14-1 -> -0.023055881 | G15: =+F15 -> -0.023055881 | H15: =+E15/E3-1 -> -0.21538633 | I15: =+H15 -> -0.21538633
A16: 16041 | C16: 34912 | D16: =+'BRL e USD Chart'!$D16 -> 72.718284 | E16: =+'BRL e USD Chart'!$D16 -> 72.718284 | F16: =+E16/E15-1 -> -0.0098029508 | G16: =+F16 -> -0.0098029508 | H16: =+E16/E4-1 -> -0.2086271 | I16: =+H16 -> -0.2086271
A17: 16072 | C17: 34943 | D17: =+'BRL e USD Chart'!$D17 -> 72.00543 | E17: =+'BRL e USD Chart'!$D17 -> 72.00543 | F17: =+E17/E16-1 -> -0.0098029508 | G17: =+F17 -> -0.0098029508 | H17: =+E17/E5-1 -> -0.20439558 | I17: =+H17 -> -0.20439558
A18: 16103 | C18: 34973 | D18: =+'BRL e USD Chart'!$D18 -> 71.00427 | E18: =+'BRL e USD Chart'!$D18 -> 71.00427 | F18: =+E18/E17-1 -> -0.013903954 | G18: =+F18 -> -0.013903954 | H18: =+E18/E6-1 -> -0.19490262 | I18: =+H18 -> -0.19490262
A19: 16132 | C19: 35004 | D19: =+'BRL e USD Chart'!$D19 -> 69.975628 | E19: =+'BRL e USD Chart'!$D19 -> 69.975628 | F19: =+E19/E18-1 -> -0.014487041 | G19: =+F19 -> -0.014487041 | H19: =+E19/E7-1 -> -0.1842706 | I19: =+H19 -> -0.1842706
A20: 16163 | C20: 35034 | D20: =+'BRL e USD Chart'!$D20 -> 68.900776 | E20: =+'BRL e USD Chart'!$D20 -> 68.900776 | F20: =+E20/E19-1 -> -0.015360378 | G20: =+F20 -> -0.015360378 | H20: =+E20/E8-1 -> -0.1830658 | I20: =+H20 -> -0.1830658
A21: 16193 | C21: 35065 | D21: =+'BRL e USD Chart'!$D21 -> 67.989714 | E21: =+'BRL e USD Chart'!$D21 -> 67.989714 | F21: =+E21/E20-1 -> -0.013222814 | G21: =+F21 -> -0.013222814 | H21: =+E21/E9-1 -> -0.18016373 | I21: =+H21 -> -0.18016373
A22: 16224 | C22: 35096 | D22: =+'BRL e USD Chart'!$D22 -> 67.296559 | E22: =+'BRL e USD Chart'!$D22 -> 67.296559 | F22: =+E22/E21-1 -> -0.010194992 | G22: =+F22 -> -0.010194992 | H22: =+E22/E10-1 -> -0.18024488 | I22: =+H22 -> -0.18024488
A23: 16254 | C23: 35125 | D23: =+'BRL e USD Chart'!$D23 -> 67.061843 | E23: =+'BRL e USD Chart'!$D23 -> 67.061843 | F23: =+E23/E22-1 -> -0.0034877927 | G23: =+F23 -> -0.0034877927 | H23: =+E23/E11-1 -> -0.17044213 | I23: =+H23 -> -0.17044213
A24: 16285 | C24: 35156 | D24: =+'BRL e USD Chart'!$D24 -> 66.227378 | E24: =+'BRL e USD Chart'!$D24 -> 66.227378 | F24: =+E24/E23-1 -> -0.012443215 | G24: =+F24 -> -0.012443215 | H24: =+E24/E12-1 -> -0.16085707 | I24: =+H24 -> -0.16085707
A25: 16316 | C25: 35186 | D25: =+'BRL e USD Chart'!$D25 -> 65.429142 | E25: =+'BRL e USD Chart'!$D25 -> 65.429142 | F25: =+E25/E24-1 -> -0.012052954 | G25: =+F25 -> -0.012052954 | H25: =+E25/E13-1 -> -0.14883615 | I25: =+H25 -> -0.14883615
... A376: 26999 | C376: 45870 | D376: =+'BRL e USD Chart'!$D376 -> 11.705162 | E376: =+'BRL e USD Chart'!$D376 -> 11.705162 | F376: =+E376/E375-1 -> 0.0011012113 | G376: =+F376 -> 0.0011012113 | H376: =+E376/E364-1 -> -0.048801259 | I376: =+H376 -> -0.048801259
A377: 27030 | C377: 45901 | D377: =+'BRL e USD Chart'!$D377 -> 11.649245 | E377: =+'BRL e USD Chart'!$D377 -> 11.649245
A378: 27061 | C378: 45931 | D378: =+'BRL e USD Chart'!$D378 -> 11.638771 | E378: =+'BRL e USD Chart'!$D378 -> 11.638771
A379: 27089 | C379: 45962 | D379: =+'BRL e USD Chart'!$D379 -> 11.617858 | E379: =+'BRL e USD Chart'!$D379 -> 11.617858
A380: 27120 | C380: 45992 | D380: =+'BRL e USD Chart'!$D380 -> 11.579646 | E380: =+'BRL e USD Chart'!$D380 -> 11.579646
A381: 27150 | C381: 46023 | D381: =+'BRL e USD Chart'!$D381 -> 11.541558 | E381: =+'BRL e USD Chart'!$D381 -> 11.541558
A382: 27181 | C382: 46054 | D382: =+'BRL e USD Chart'!$D382 -> 11.461329 | E382: =+'BRL e USD Chart'!$D382 -> 11.461329
A383: 27211 | C383: 46082 | D383: =+'BRL e USD Chart'!$D383 -> 11.361349 | E383: =+'BRL e USD Chart'!$D383 -> 11.361349
A384: 27242 | C384: 46113 | D384: =+'BRL e USD Chart'!$D384 -> 11.285735 | E384: =+'BRL e USD Chart'!$D384 -> 11.285735
A385: 27273 | C385: 46143 | D385: =+'BRL e USD Chart'!$D385 -> 11.220655 | E385: =+'BRL e USD Chart'!$D385 -> 11.220655
A386: 27303 | C386: 46174 | D386: =+'BRL e USD Chart'!$D386 -> 11.202731 | E386: =+'BRL e USD Chart'!$D386 -> 11.202731
A387: 27334 | C387: 46204 | D387: =+'BRL e USD Chart'!$D387 -> 11.194894 | E387: =+'BRL e USD Chart'!$D387 -> 11.194894
A388: 27364 | C388: 46235 | D388: =+'BRL e USD Chart'!$D388 -> 11.230833 | E388: =+'BRL e USD Chart'!$D388 -> 11.230833
A389: 27395
A390: 27426
A391: 27454
A392: 27485
A393: 27515
A394: 27546
A395: 27576
A396: 27607
A397: 27638
A398: 27668
A399: 27699
A400: 27729
... A405: 27881
A406: 27912 | I406: -0.1 | J406: =((1+J407)^(12))-1 -> -0.058377193 | K406: =+D359/D239-1 -> -0.43247903 | L406: meses | M406: =+'USD PP Chart'!B1347/'USD PP Chart'!B1227-1 -> -0.24349882
A407: 27942 | I407: =((1+I406)^(0.0833333333333333))-1 -> -0.008741611 | J407: -0.005 | K407: =((1+K406)^(1/L407))-1 -> -0.0047095217 | L407: 120 | M407: =((1+M406)^(1/L407))-1 -> -0.0023227248
A408: 27973
A409: 28004
A410: 28034 | L410: =10*12 -> 120
A411: 28065
A412: 28095
A413: 28126
A414: 28157
A415: 28185
A416: 28216
A417: 28246
A418: 28277
A419: 28307
A420: 28338
A421: 28369
A422: 28399
... A946: 44348

Sheet 2-Chart Câmbio Justo
A1: Data | C1: Mês | D1: USDBRL | E1: USDBRL | F1: Câmbio pela PPC | G1: Cruzado (fev-86 a jan-89) | H1: Cruzado Novo (jan-89 a mar-90) | I1: Cruzeiro (mar-90 a ago/93) | J1: Cruzeiro real (ago/93 a jun-94) | K1: Real (jul/94 a jun-21)
A2: 15615 | C2: 34486 | D2: =+USDBRL!D499 -> 2292.9624 | E2: =+'USD PP 1994'!C989 -> 100 | F2: =+'BRL e USD Chart 99'!F2 -> 1 | G2: 100 | H2: 100 | I2: 100 | J2: 100 | K2: 100
A3: 15646 | C3: 34516 | D3: =+USDBRL!D500 -> 0.92905 | E3: =+'USD PP 1994'!C990 -> 99.704142 | F3: =+'BRL e USD Chart 99'!F3 -> 1.0652391 | G3: 98.202887 | H3: 87.711604 | I3: 83.201597 | J3: 74.560095 | K3: 93.501636 | P3: =5.2/4.9-1 -> 0.06122449
A4: 15676 | C4: 34547 | D4: =+USDBRL!D501 -> 0.8976 | E4: =+'USD PP 1994'!C991 -> 99.260355 | F4: =+'BRL e USD Chart 99'!F4 -> 1.0802229 | G4: 95.985619 | H4: 82.389258 | I4: 76.662303 | J4: 55.135765 | K4: 91.713228
A5: 15707 | C5: 34578 | D5: =+USDBRL!D502 -> 0.8642 | E5: =+'USD PP 1994'!C992 -> 98.964497 | F5: =+'BRL e USD Chart 99'!F5 -> 1.0934813 | G5: 94.177413 | H5: 74.88571 | I5: 68.632321 | J5: 40.588755 | K5: 90.967296
A6: 15738 | C6: 34608 | D6: =+USDBRL!D503 -> 0.845 | E6: =+'USD PP 1994'!C993 -> 98.964497 | F6: =+'BRL e USD Chart 99'!F6 -> 1.1221305 | G6: 93.281907 | H6: 64.22996 | I6: 61.65872 | J6: 29.301729 | K6: 88.172237
A7: 15766 | C7: 34639 | D7: =+USDBRL!D504 -> 0.8408 | E7: =+'USD PP 1994'!C994 -> 98.816568 | F7: =+'BRL e USD Chart 99'!F7 -> 1.1519379 | G7: 92.294357 | H7: 51.265033 | I7: 55.136117 | J7: 20.885053 | K7: 85.587494
A8: 15797 | C8: 34669 | D8: =+USDBRL!D505 -> 0.8491 | E8: =+'USD PP 1994'!C995 -> 98.816568 | F8: =+'BRL e USD Chart 99'!F8 -> 1.1716361 | G8: 90.591242 | H8: 40.032042 | I8: 48.736955 | J8: 15.113288 | K8: 84.530859
A9: 15827 | C9: 34700 | D9: =+USDBRL!D506 -> 0.8461 | E9: =+'USD PP 1994'!C996 -> 98.372781 | F9: =+'BRL e USD Chart 99'!F9 -> 1.1862026 | G9: 89.314051 | H9: 30.570479 | I9: 42.07628 | J9: 10.64766 | K9: 83.859979
A10: 15858 | C10: 34731 | D10: =+USDBRL!D507 -> 0.8398 | E10: =+'USD PP 1994'!C997 -> 98.076923 | F10: =+'BRL e USD Chart 99'!F10 -> 1.1946979 | G10: 86.645373 | H10: 22.506426 | I10: 35.48944 | J10: 7.2819448 | K10: 82.767448
A11: 15888 | C11: 34759 | D11: =+USDBRL!D508 -> 0.8884 | E11: =+'USD PP 1994'!C998 -> 97.633136 | F11: =+'BRL e USD Chart 99'!F11 -> 1.2077261 | G11: 82.969811 | H11: 16.393347 | I11: 30.586435 | J11: 5.0185698 | K11: 81.20825
A12: 15919 | C12: 34790 | D12: =+USDBRL!D509 -> 0.9065 | E12: =+'USD PP 1994'!C999 -> 97.337278 | F12: =+'BRL e USD Chart 99'!F12 -> 1.2333251 | G12: 75.22195 | H12: 11.467087 | I12: 25.273868 | J12: 3.3290679 | K12: 79.119495
A13: 15950 | C13: 34820 | D13: =+USDBRL!D510 -> 0.8964 | E13: =+'USD PP 1994'!C1000 -> 97.189349 | F13: =+'BRL e USD Chart 99'!F13 -> 1.2643305 | G13: 66.129187 | H13: 7.5530804 | I13: 20.967204 | K13: 77.590954
A14: 15980 | C14: 34851 | D14: =+USDBRL!D511 -> 0.913 | E14: =+'USD PP 1994'!C1001 -> 97.04142 | F14: =+'BRL e USD Chart 99'!F14 -> 1.2909365 | G14: 59.425941 | H14: 4.3276688 | I14: 19.508005 | K14: 75.580512
A15: 16011 | C15: 34881 | D15: =+USDBRL!D512 -> 0.9278 | E15: =+'USD PP 1994'!C1002 -> 97.04142 | F15: =+'BRL e USD Chart 99'!F15 -> 1.3214026 | G15: 53.073092 | H15: 2.5432939 | I15: 18.199464 | K15: 72.869757
A16: 16041 | C16: 34912 | D16: =+USDBRL!D513 -> 0.941 | E16: =+'USD PP 1994'!C1003 -> 96.745562 | F16: =+'BRL e USD Chart 99'!F16 -> 1.3304159 | G16: 45.536758 | H16: 1.419962 | I16: 17.208267 | K16: 71.84241
A17: 16072 | C17: 34943 | D17: =+USDBRL!D514 -> 0.9518 | E17: =+'USD PP 1994'!C1004 -> 96.597633 | F17: =+'BRL e USD Chart 99'!F17 -> 1.3415326 | G17: 36.000283 | I17: 15.67523 | K17: 71.314682
A18: 16103 | C18: 34973 | D18: =+USDBRL!D515 -> 0.9592 | E18: =+'USD PP 1994'!C1005 -> 96.301775 | F18: =+'BRL e USD Chart 99'!F18 -> 1.3562815 | G18: 28.40035 | I18: 14.083765 | K18: 70.274617
A19: 16132 | C19: 35004 | D19: =+USDBRL!D516 -> 0.9629 | E19: =+'USD PP 1994'!C1006 -> 96.301775 | F19: =+'BRL e USD Chart 99'!F19 -> 1.3762188 | G19: 25.998123 | I19: 12.308831 | K19: 69.461913
A20: 16163 | C20: 35034 | D20: =+USDBRL!D517 -> 0.9678 | E20: =+'USD PP 1994'!C1007 -> 96.301775 | F20: =+'BRL e USD Chart 99'!F20 -> 1.3976878 | G20: 24.890496 | I20: 10.591886 | K20: 68.631472
A21: 16193 | C21: 35065 | D21: =+USDBRL!D518 -> 0.974 | E21: =+'USD PP 1994'!C1008 -> 95.857988 | F21: =+'BRL e USD Chart 99'!F21 -> 1.4098896 | G21: 23.320993 | I21: 8.4620008 | K21: 67.404707
A22: 16224 | C22: 35096 | D22: =+USDBRL!D519 -> 0.9806 | E22: =+'USD PP 1994'!C1009 -> 95.414201 | F22: =+'BRL e USD Chart 99'!F22 -> 1.4178169 | G22: 21.168188 | I22: 6.7485452 | K22: 67.136162
A23: 16254 | C23: 35125 | D23: =+USDBRL!D520 -> 0.9857 | E23: =+'USD PP 1994'!C1010 -> 94.970414 | F23: =+'BRL e USD Chart 99'!F23 -> 1.4161617 | G23: 18.666833 | I23: 5.475493 | K23: 66.982103
A24: 16285 | C24: 35156 | D24: =+USDBRL!D521 -> 0.9898 | E24: =+'USD PP 1994'!C1011 -> 94.674556 | F24: =+'BRL e USD Chart 99'!F24 -> 1.429538 | G24: 16.103203 | I24: 4.3494265 | K24: 65.914292
A25: 16316 | C25: 35186 | D25: =+USDBRL!D522 -> 0.9949 | E25: =+'USD PP 1994'!C1012 -> 94.526627 | F25: =+'BRL e USD Chart 99'!F25 -> 1.4447175 | G25: 14.03941 | I25: 3.5777137 | K25: 65.042719
A26: 16346 | C26: 35217 | D26: =+USDBRL!D523 -> 1.0009 | E26: =+'USD PP 1994'!C1013 -> 94.378698 | F26: =+'BRL e USD Chart 99'!F26 -> 1.4596218 | G26: 12.382616 | I26: 2.9388152 | K26: 64.138368
A27: 16377 | C27: 35247 | D27: =+USDBRL!D524 -> 1.0065 | E27: =+'USD PP 1994'!C1014 -> 94.230769 | F27: =+'BRL e USD Chart 99'!F27 -> 1.4735104 | G27: 10.436254 | I27: 2.394537 | K27: 63.30902
A28: 16407 | C28: 35278 | D28: =+USDBRL!D525 -> 1.013 | E28: =+'USD PP 1994'!C1015 -> 94.08284 | F28: =+'BRL e USD Chart 99'!F28 -> 1.4776705 | G28: 8.6129027 | I28: 1.9542455 | K28: 63.094499
... A36: 16650 | C36: 35521 | D36: =+USDBRL!D533 -> 1.0605 | E36: =+'USD PP 1994'!C1023 -> 92.307692 | F36: =+'BRL e USD Chart 99'!F36 -> 1.5134078 | G36: 1.6238485 | I36: 0.34952315 | K36: 61.084333
A37: 16681 | C37: 35551 | D37: =+USDBRL!D534 -> 1.0679 | E37: =+'USD PP 1994'!C1024 -> 92.455621 | F37: =+'BRL e USD Chart 99'!F37 -> 1.5220481 | G37: =+USDBRL!D534/'2-Chart Câmbio Justo'!F37*100 -> 70.162042 | I37: 0.27939501 | K37: 60.750207
A38: 16711 | C38: 35582 | D38: =+USDBRL!D535 -> 1.0742 | E38: =+'USD PP 1994'!C1025 -> 92.307692 | F38: =+'BRL e USD Chart 99'!F38 -> 1.5278187 | G38: =+USDBRL!D535/'2-Chart Câmbio Justo'!F38*100 -> 70.30939 | I38: 0.22323027 | K38: 59.899632
A39: 16742 | C39: 35612 | D39: =+USDBRL!D536 -> 1.0803 | E39: =+'USD PP 1994'!C1026 -> 92.159763 | F39: =+'BRL e USD Chart 99'!F39 -> 1.5287261 | G39: =+USDBRL!D536/'2-Chart Câmbio Justo'!F39*100 -> 70.666682 | I39: 0.1733962 | K39: 59.833815
A40: 16772 | C40: 35643 | D40: =+USDBRL!D537 -> 1.0875 | E40: =+'USD PP 1994'!C1027 -> 92.011834 | F40: =+'BRL e USD Chart 99'!F40 -> 1.525967 | G40: =+USDBRL!D537/'2-Chart Câmbio Justo'!F40*100 -> 71.266285 | I40: 0.13426994 | K40: 60.292035
A41: 16803 | C41: 35674 | D41: =+USDBRL!D538 -> 1.0932 | E41: =+'USD PP 1994'!C1028 -> 91.715976 | F41: =+'BRL e USD Chart 99'!F41 -> 1.521973 | G41: =+USDBRL!D538/'2-Chart Câmbio Justo'!F41*100 -> 71.827818 | I41: 0.1028652 | K41: 60.286006
A42: 16834 | C42: 35704 | D42: =+USDBRL!D539 -> 1.0997 | E42: =+'USD PP 1994'!C1029 -> 91.568047 | F42: =+'BRL e USD Chart 99'!F42 -> 1.5230131 | G42: =+USDBRL!D539/'2-Chart Câmbio Justo'!F42*100 -> 72.205551 | I42: 0.078589041 | K42: 60.153668
A43: 16862 | C43: 35735 | D43: =+USDBRL!D540 -> 1.1069 | E43: =+'USD PP 1994'!C1030 -> 91.568047 | F43: =+'BRL e USD Chart 99'!F43 -> 1.5256022 | G43: =+USDBRL!D540/'2-Chart Câmbio Justo'!F43*100 -> 72.554955 | I43: 0.058661671 | K43: 59.836534
A44: 16893 | C44: 35765 | D44: =+USDBRL!D541 -> 1.1132 | E44: =+'USD PP 1994'!C1031 -> 91.715976 | F44: =+'BRL e USD Chart 99'!F44 -> 1.5346375 | G44: =+USDBRL!D541/'2-Chart Câmbio Justo'!F44*100 -> 72.538301 | K44: 59.497399
A45: 16923 | C45: 35796 | D45: =+USDBRL!D542 -> 1.1195 | E45: =+'USD PP 1994'!C1032 -> 91.568047 | F45: =+'BRL e USD Chart 99'!F45 -> 1.5430407 | G45: =+USDBRL!D542/'2-Chart Câmbio Justo'!F45*100 -> 72.551555 | K45: 59.354947
A46: 16954 | C46: 35827 | D46: =+USDBRL!D543 -> 1.1267 | E46: =+'USD PP 1994'!C1033 -> 91.420118 | F46: =+'BRL e USD Chart 99'!F46 -> 1.5476344 | G46: =+USDBRL!D543/'2-Chart Câmbio Justo'!F46*100 -> 72.801432 | K46: 59.450067
A47: 16984 | C47: 35855 | D47: =+USDBRL!D544 -> 1.1333 | E47: =+'USD PP 1994'!C1034 -> 91.272189 | F47: =+'BRL e USD Chart 99'!F47 -> 1.5503836 | G47: =+USDBRL!D544/'2-Chart Câmbio Justo'!F47*100 -> 73.09804 | K47: 59.587118
A48: 17015 | C48: 35886 | D48: =+USDBRL!D545 -> 1.1408 | E48: =+'USD PP 1994'!C1035 -> 90.976331 | F48: =+'BRL e USD Chart 99'!F48 -> 1.5490669 | G48: =+USDBRL!D545/'2-Chart Câmbio Justo'!F48*100 -> 73.644335 | K48: 59.219954
A49: 17046 | C49: 35916 | D49: =+USDBRL!D546 -> 1.1477 | E49: =+'USD PP 1994'!C1036 -> 90.828402 | F49: =+'BRL e USD Chart 99'!F49 -> 1.5542808 | G49: =+USDBRL!D546/'2-Chart Câmbio Justo'!F49*100 -> 73.841226 | K49: 58.913603
A50: 17076 | C50: 35947 | D50: =+USDBRL!D547 -> 1.1542 | E50: =+'USD PP 1994'!C1037 -> 90.828402 | F50: =+'BRL e USD Chart 99'!F50 -> 1.5545917 | G50: =+USDBRL!D547/'2-Chart Câmbio Justo'!F50*100 -> 74.244577 | K50: 58.80188
A51: 17107 | C51: 35977 | D51: =+USDBRL!D548 -> 1.1611 | E51: =+'USD PP 1994'!C1038 -> 90.680473 | F51: =+'BRL e USD Chart 99'!F51 -> 1.5501973 | G51: =+USDBRL!D548/'2-Chart Câmbio Justo'!F51*100 -> 74.900144 | K51: 59.258168
A52: 17137 | C52: 36008 | D52: =+USDBRL!D549 -> 1.1713 | E52: =+'USD PP 1994'!C1039 -> 90.532544 | F52: =+'BRL e USD Chart 99'!F52 -> 1.5397753 | G52: =+USDBRL!D549/'2-Chart Câmbio Justo'!F52*100 -> 76.069541 | K52: 59.856735
A53: 17168 | C53: 36039 | D53: =+USDBRL!D550 -> 1.1805 | E53: =+'USD PP 1994'!C1040 -> 90.384615 | F53: =+'BRL e USD Chart 99'!F53 -> 1.5338774 | G53: =+USDBRL!D550/'2-Chart Câmbio Justo'!F53*100 -> 76.961824 | K53: 60.254414
A54: 17199 | C54: 36069 | D54: =+USDBRL!D551 -> 1.188 | E54: =+'USD PP 1994'!C1041 -> 90.236686 | F54: =+'BRL e USD Chart 99'!F54 -> 1.5316732 | G54: =+USDBRL!D551/'2-Chart Câmbio Justo'!F54*100 -> 77.562237 | K54: 60.242366
A55: 17227 | C55: 36100 | D55: =+USDBRL!D552 -> 1.1933 | E55: =+'USD PP 1994'!C1042 -> 90.236686 | F55: =+'BRL e USD Chart 99'!F55 -> 1.5298352 | G55: =+USDBRL!D552/'2-Chart Câmbio Justo'!F55*100 -> 78.001866 | K55: 60.508604
... A57: 17288 | C57: 36161 | D57: =+USDBRL!D554 -> 1.5015 | E57: =+'USD PP 1994'!C1044 -> 89.940828 | F57: =+'BRL e USD Chart 99'!F57 -> 1.5405602 | G57: =+USDBRL!D554/'2-Chart Câmbio Justo'!F57*100 -> 97.464546 | K57: 60.279902
A58: 17319 | C58: 36192 | D58: =+USDBRL!D555 -> 1.9133 | E58: =+'USD PP 1999'!C1045 -> 89.940828 | F58: =+'BRL e USD Chart 99'!F58 -> 1.5567361 | G58: =+USDBRL!D555/'2-Chart Câmbio Justo'!F58*100 -> 122.90458 | K58: 59.441773
A59: 17349 | C59: 36220 | D59: =+USDBRL!D556 -> 1.8964 | E59: =+'USD PP 1999'!C1046 -> 100 | F59: =+'BRL e USD Chart 99'!F59 -> 1.8957534 | G59: =+USDBRL!D556/'2-Chart Câmbio Justo'!F59*100 -> 100.03411 | K59: 59.110752
A60: 17380 | C60: 36251 | D60: =+USDBRL!D557 -> 1.6937 | E60: =+'USD PP 1999'!C1047 -> 99.339934 | F60: =+'BRL e USD Chart 99'!F60 -> 1.8937863 | G60: =+USDBRL!D557/'2-Chart Câmbio Justo'!F60*100 -> 89.434588 | K60: 58.834232
A61: 17411 | C61: 36281 | D61: =+USDBRL!D558 -> 1.6831 | E61: =+'USD PP 1999'!C1048 -> 99.339934 | F61: =+'BRL e USD Chart 99'!F61 -> 1.8994677 | G61: =+USDBRL!D558/'2-Chart Câmbio Justo'!F61*100 -> 88.609036 | K61: 59.052727
A62: 17441 | C62: 36312 | D62: =+USDBRL!D559 -> 1.765 | E62: =+'USD PP 1999'!C1049 -> 99.339934 | F62: =+'BRL e USD Chart 99'!F62 -> 1.9030767 | G62: =+USDBRL!D559/'2-Chart Câmbio Justo'!F62*100 -> 92.744555 | K62: 59.100007
A63: 17472 | C63: 36342 | D63: =+USDBRL!D560 -> 1.7999 | E63: =+'USD PP 1999'!C1050 -> 99.009901 | F63: =+'BRL e USD Chart 99'!F63 -> 1.9174288 | G63: =+USDBRL!D560/'2-Chart Câmbio Justo'!F63*100 -> 93.870501 | K63: 58.462762
A64: 17502 | C64: 36373 | D64: =+USDBRL!D561 -> 1.88035 | E64: =+'USD PP 1999'!C1051 -> 98.679868 | F64: =+'BRL e USD Chart 99'!F64 -> 1.9217392 | G64: =+USDBRL!D561/'2-Chart Câmbio Justo'!F64*100 -> 97.846265 | K64: 58.033316
A65: 17533 | C65: 36404 | D65: =+USDBRL!D562 -> 1.8977 | E65: =+'USD PP 1999'!C1052 -> 98.349835 | F65: =+'BRL e USD Chart 99'!F65 -> 1.9212494 | G65: =+USDBRL!D562/'2-Chart Câmbio Justo'!F65*100 -> 98.774266 | K65: 57.509975
A66: 17564 | C66: 36434 | D66: =+USDBRL!D563 -> 1.9691 | E66: =+'USD PP 1999'!C1053 -> 98.019802 | F66: =+'BRL e USD Chart 99'!F66 -> 1.9375884 | G66: =+USDBRL!D563/'2-Chart Câmbio Justo'!F66*100 -> 101.62633 | K66: 56.867374
A67: 17593 | C67: 36465 | D67: =+USDBRL!D564 -> 1.9295 | E67: =+'USD PP 1999'!C1054 -> 98.019802 | F67: =+'BRL e USD Chart 99'!F67 -> 1.9559955 | G67: =+USDBRL!D564/'2-Chart Câmbio Justo'!F67*100 -> 98.645421 | K67: 56.038011
A68: 17624 | C68: 36495 | D68: =+USDBRL!D565 -> 1.8424 | E68: =+'USD PP 1999'!C1055 -> 98.019802 | F68: =+'BRL e USD Chart 99'!F68 -> 1.9677315 | G68: =+USDBRL!D565/'2-Chart Câmbio Justo'!F68*100 -> 93.630662 | K68: 55.764764
A69: 17654 | C69: 36526 | D69: =+USDBRL!D566 -> 1.8033 | E69: =+'USD PP 1999'!C1056 -> 97.689769 | F69: =+'BRL e USD Chart 99'!F69 -> 1.973265 | G69: =+USDBRL!D566/'2-Chart Câmbio Justo'!F69*100 -> 91.386612 | K69: 55.448706
... A326: 25477 | C326: 44348 | D326: =+USDBRL!D823 -> 5.0316 | E326: =+'USD PP 1999'!C1313 -> 60.726073 | F326: =+'BRL e USD Chart 99'!F326 -> 4.427947 | G326: =+USDBRL!D823/'2-Chart Câmbio Justo'!F326*100 -> 113.6328 | K326: 17.370595
A327: 25508 | C327: 44378 | D327: =+USDBRL!D824 -> 5.15635 | E327: =+'USD PP 1999'!C1314 -> 60.39604 | F327: =+'BRL e USD Chart 99'!F327 -> 4.4461594 | G327: =+USDBRL!D824/'2-Chart Câmbio Justo'!F327*100 -> 115.97313
A328: 25538 | C328: 44409 | D328: =+USDBRL!D825 -> 5.2514 | E328: =+'USD PP 1999'!C1315 -> 60.39604 | F328: =+'BRL e USD Chart 99'!F328 -> 4.484841 | G328: =+USDBRL!D825/'2-Chart Câmbio Justo'!F328*100 -> 117.09222 | I328: 37530 | J328: 40695 | S328: 4.93
A329: 25569 | C329: 44440 | D329: =+USDBRL!D826 -> 5.2794 | E329: =+'USD PP 1999'!C1316 -> 60.231023 | F329: =+'BRL e USD Chart 99'!F329 -> 4.5244693 | G329: =+USDBRL!D826/'2-Chart Câmbio Justo'!F329*100 -> 116.68551 | I329: =+G102 -> 170.47564 | J329: =+G207 -> 50.902808 | S329: =+F334/S328-1 -> -0.074590472
A330: 25600 | C330: 44470 | D330: =+USDBRL!D827 -> 5.5397 | E330: =+'USD PP 1999'!C1317 -> 59.735974 | F330: =+'BRL e USD Chart 99'!F330 -> 4.5433729 | G330: =+USDBRL!D827/'2-Chart Câmbio Justo'!F330*100 -> 121.92924 | H330: USDBRL | I330: =+F368*I329/100 -> 8.0018481 | J330: =+F368*J329/100 -> 2.3892946
A331: 25628 | C331: 44501 | D331: =+USDBRL!D828 -> 5.5566 | E331: =+'USD PP 1999'!C1318 -> 59.405941 | F331: =+'BRL e USD Chart 99'!F331 -> 4.561195 | G331: =+USDBRL!D828/'2-Chart Câmbio Justo'!F331*100 -> 121.82334 | N331: 5.15
A332: 25659 | C332: 44531 | D332: =+USDBRL!D829 -> 5.651 | E332: =+'USD PP 1999'!C1319 -> 59.240924 | F332: =+'BRL e USD Chart 99'!F332 -> 4.5817292 | G332: =+USDBRL!D829/'2-Chart Câmbio Justo'!F332*100 -> 123.33771 | N332: =+F334/N331-1 -> -0.11412253
A333: 25689 | C333: 44562 | D333: =+USDBRL!D830 -> 5.5338 | E333: =+'USD PP 1999'!C1320 -> 58.745875 | F333: =+'BRL e USD Chart 99'!F333 -> 4.5679764 | G333: =+USDBRL!D830/'2-Chart Câmbio Justo'!F333*100 -> 121.14336
A334: 25720 | C334: 44593 | D334: =+USDBRL!D831 -> 5.1963 | E334: =+'USD PP 1999'!C1321 -> 58.085809 | F334: =+'BRL e USD Chart 99'!F334 -> 4.562269 | G334: =+USDBRL!D831/'2-Chart Câmbio Justo'!F334*100 -> 113.89727 | H334: 11
A335: 25750 | C335: 44621 | D335: =+USDBRL!D832 -> 4.9681 | E335: =+'USD PP 1999'!C1322 -> 57.425743 | F335: =+'BRL e USD Chart 99'!F335 -> 4.5834939 | G335: =+USDBRL!D832/'2-Chart Câmbio Justo'!F335*100 -> 108.39111
A336: 25781 | C336: 44652 | D336: =+USDBRL!D833 -> 4.7577 | E336: =+'USD PP 1999'!C1323 -> 57.09571 | F336: =+'BRL e USD Chart 99'!F336 -> 4.6054578 | G336: =+USDBRL!D833/'2-Chart Câmbio Justo'!F336*100 -> 103.30569
A337: 25812 | C337: 44682 | D337: =+USDBRL!D834 -> 4.9548 | E337: =+'USD PP 1999'!C1324 -> 56.435644 | F337: =+'BRL e USD Chart 99'!F337 -> 4.5736109 | G337: =+USDBRL!D834/'2-Chart Câmbio Justo'!F337*100 -> 108.33453
A338: 25842 | C338: 44713 | D338: =+USDBRL!D835 -> 5.0489 | E338: =+'USD PP 1999'!C1325 -> 55.610561 | F338: =+'BRL e USD Chart 99'!F338 -> 4.5369404 | G338: =+USDBRL!D835/'2-Chart Câmbio Justo'!F338*100 -> 111.28425
A339: 25873 | C339: 44743 | D339: =+USDBRL!D836 -> 5.3678 | E339: =+'USD PP 1999'!C1326 -> 55.775578 | F339: =+'BRL e USD Chart 99'!F339 -> 4.5194604 | G339: =+USDBRL!D836/'2-Chart Câmbio Justo'!F339*100 -> 118.77082
A340: 25903 | C340: 44774 | D340: =+USDBRL!D837 -> 5.143 | E340: =+'USD PP 1999'!C1327 -> 55.775578 | F340: =+'BRL e USD Chart 99'!F340 -> 4.5031904 | G340: =+USDBRL!D837/'2-Chart Câmbio Justo'!F340*100 -> 114.20792
A341: 25934 | C341: 44805 | D341: =+USDBRL!D838 -> 5.2367 | E341: =+'USD PP 1999'!C1328 -> 55.610561 | F341: =+'BRL e USD Chart 99'!F341 -> 4.4768467 | G341: =+USDBRL!D838/'2-Chart Câmbio Justo'!F341*100 -> 116.97296
A342: 25965 | C342: 44835 | D342: =+USDBRL!D839 -> 5.25 | E342: =+'USD PP 1999'!C1329 -> 55.445545 | F342: =+'BRL e USD Chart 99'!F342 -> 4.4898973 | G342: =+USDBRL!D839/'2-Chart Câmbio Justo'!F342*100 -> 116.92918
A343: 25993 | C343: 44866 | D343: =+USDBRL!D840 -> 5.2744 | E343: =+'USD PP 1999'!C1330 -> 55.445545 | F343: =+'BRL e USD Chart 99'!F343 -> 4.5083059 | G343: =+USDBRL!D840/'2-Chart Câmbio Justo'!F343*100 -> 116.99295
A344: 26024 | C344: 44896 | D344: =+USDBRL!D841 -> 5.2421 | E344: =+'USD PP 1999'!C1331 -> 55.610561 | F344: =+'BRL e USD Chart 99'!F344 -> 4.5497582 | G344: =+USDBRL!D841/'2-Chart Câmbio Justo'!F344*100 -> 115.21711
A345: 26054 | C345: 44927 | D345: =+USDBRL!D842 -> 5.2004 | E345: =+'USD PP 1999'!C1332 -> 55.115512 | F345: =+'BRL e USD Chart 99'!F345 -> 4.5331549 | G345: =+USDBRL!D842/'2-Chart Câmbio Justo'!F345*100 -> 114.71922
A346: 26085 | C346: 44958 | D346: =+USDBRL!D843 -> 5.1714 | E346: =+'USD PP 1999'!C1333 -> 54.785479 | F346: =+'BRL e USD Chart 99'!F346 -> 4.5438608 | G346: =+USDBRL!D843/'2-Chart Câmbio Justo'!F346*100 -> 113.81071
... A359: 26481 | C359: 45352 | D359: =+USDBRL!D856 -> 4.9798 | E359: =+'USD PP 1999'!C1346 -> 52.805281 | F359: =+'BRL e USD Chart 99'!F359 -> 4.5838672 | G359: =+USDBRL!D856/'2-Chart Câmbio Justo'!F359*100 -> 108.63753
A360: 26512 | C360: 45383 | D360: =+USDBRL!D857 -> 5.1288 | E360: =+'USD PP 1999'!C1347 -> 52.640264 | F360: =+'BRL e USD Chart 99'!F360 -> 4.5869069
A361: 26543 | C361: 45413 | D361: =+USDBRL!D858 -> 5.1327 | E361: =+'USD PP 1999'!C1348 -> 52.475248 | F361: =+'BRL e USD Chart 99'!F361 -> 4.5935615
A362: 26573 | C362: 45444 | D362: =+USDBRL!D859 -> 5.3887 | E362: =+'USD PP 1999'!C1349 -> 52.475248 | F362: =+'BRL e USD Chart 99'!F362 -> 4.603208
A363: 26604 | C363: 45474 | D363: =+USDBRL!D860 -> 5.5417 | E363: =+'USD PP 1999'!C1350 -> 52.475248 | F363: =+'BRL e USD Chart 99'!F363 -> 4.6207002
A364: 26634 | C364: 45505 | D364: =+USDBRL!D861 -> 5.5523 | E364: =+'USD PP 1999'!C1351 -> 52.475248 | F364: =+'BRL e USD Chart 99'!F364 -> 4.619776 | J364: =+D102/F102 -> 1.7047564 | K364: =+D207/F207 -> 0.50902808
A365: 26665 | C365: 45536 | D365: =+USDBRL!D862 -> 5.5413 | E365: =+'USD PP 1999'!C1352 -> 52.310231 | F365: =+'BRL e USD Chart 99'!F365 -> 4.6255115 | J365: =+J364*F368 -> 8.0018481 | K365: =+K364*F368 -> 2.3892946
A366: 26696 | C366: 45566 | D366: =+USDBRL!D863 -> 5.6238 | E366: =+'USD PP 1999'!C1353 -> 52.310231 | F366: =+'BRL e USD Chart 99'!F366 -> 4.6514144
A367: 26724 | C367: 45597 | D367: =+USDBRL!D864 -> 5.8068 | E367: =+'USD PP 1999'!C1354 -> 52.310231 | F367: =+'BRL e USD Chart 99'!F367 -> 4.6695549
A368: 26755 | C368: 45627 | D368: =+USDBRL!D865 -> 6.0967 | E368: =+'USD PP 1999'!C1355 -> 52.310231 | F368: =+'BRL e USD Chart 99'!F368 -> 4.6938366
A369: 26785 | C369: 45658 | D369: =+USDBRL!D866 -> 6.0215 | E369: =+'USD PP 1999'!C1356 -> 51.980198 | F369: =+'BRL e USD Chart 99'!F369 -> 4.6716853
A370: 26816 | C370: 45689 | D370: =+USDBRL!D867 -> 5.7653 | E370: =+'USD PP 1999'!C1357 -> 51.650165 | F370: =+'BRL e USD Chart 99'!F370 -> 4.7028343
A371: 26846 | C371: 45717 | D371: =+USDBRL!D868 -> 5.7465 | E371: =+'USD PP 1999'!C1358 -> 51.650165 | F371: =+'BRL e USD Chart 99'!F371 -> 4.7291701
A372: 26877 | C372: 45748 | D372: =+USDBRL!D869 -> 5.7834 | E372: =+'USD PP 1999'!C1359 -> 51.485149 | F372: =+'BRL e USD Chart 99'!F372 -> 4.7343314
A373: 26908 | C373: 45778 | D373: =+USDBRL!D870 -> 5.6671 | E373: =+'USD PP 1999'!C1360 -> 51.320132 | F373: =+'BRL e USD Chart 99'!F373 -> 4.7314271
A374: 26938 | C374: 45809 | D374: =+USDBRL!D871 -> 5.5468 | E374: =+'USD PP 1999'!C1361 -> 51.155116 | F374: =+'BRL e USD Chart 99'!F374 -> 4.7275324
A375: 26969 | C375: 45839 | D375: =+USDBRL!D872 -> 5.5282 | E375: =+'USD PP 1999'!C1362 -> 51.155116 | F375: =+'BRL e USD Chart 99'!F375 -> 4.739824
A376: 26999 | C376: 45870 | D376: =+USDBRL!D873 -> 5.4466 | E376: =+'USD PP 1999'!C1363 -> 50.990099 | F376: =+'BRL e USD Chart 99'!F376 -> 4.7193373
...

Sheet 3-BRL USD 99 Depr %
A1: Data | B1: Sobre/(Sub)Valorização do BRL | C1: Sobre/(Sub)Valorização do BRL | D1: BTC | E1: Média Histórica | F1: Média Móvel 5 anos
A2: 34516
A3: 34547
A4: 34578
A5: 34608
A6: 34639
A7: 34669
A8: 34700
A9: 34731
A10: 34759
A11: 34790
A12: 34820
A13: 34851
... A57: 36192
A58: 36220 | B58: =+'BRL e USD Chart 99'!F59/USDBRL!D556-1 -> -0.00034095668 | C58: =+B58 -> -0.00034095668 | E58: =AVERAGE($C$58:$C$381) -> 0.16263388
A59: 36251 | B59: =+'BRL e USD Chart 99'!F60/USDBRL!D557-1 -> 0.11813564 | C59: =+B59 -> 0.11813564 | E59: =AVERAGE($C$58:$C$381) -> 0.16263388
A60: 36281 | B60: =+'BRL e USD Chart 99'!F61/USDBRL!D558-1 -> 0.12855308 | C60: =+B60 -> 0.12855308 | E60: =AVERAGE($C$58:$C$381) -> 0.16263388
A61: 36312 | B61: =+'BRL e USD Chart 99'!F62/USDBRL!D559-1 -> 0.078230413 | C61: =+B61 -> 0.078230413 | E61: =AVERAGE($C$58:$C$381) -> 0.16263388
A62: 36342 | B62: =+'BRL e USD Chart 99'!F63/USDBRL!D560-1 -> 0.065297397 | C62: =+B62 -> 0.065297397 | E62: =AVERAGE($C$58:$C$381) -> 0.16263388
A63: 36373 | B63: =+'BRL e USD Chart 99'!F64/USDBRL!D561-1 -> 0.022011415 | C63: =+B63 -> 0.022011415 | E63: =AVERAGE($C$58:$C$381) -> 0.16263388
A64: 36404 | B64: =+'BRL e USD Chart 99'!F65/USDBRL!D562-1 -> 0.012409449 | C64: =+B64 -> 0.012409449 | E64: =AVERAGE($C$58:$C$381) -> 0.16263388
A65: 36434 | B65: =+'BRL e USD Chart 99'!F66/USDBRL!D563-1 -> -0.016003041 | C65: =+B65 -> -0.016003041 | E65: =AVERAGE($C$58:$C$381) -> 0.16263388
A66: 36465 | B66: =+'BRL e USD Chart 99'!F67/USDBRL!D564-1 -> 0.013731797 | C66: =+B66 -> 0.013731797 | E66: =AVERAGE($C$58:$C$381) -> 0.16263388
A67: 36495 | B67: =+'BRL e USD Chart 99'!F68/USDBRL!D565-1 -> 0.068026202 | C67: =+B67 -> 0.068026202 | E67: =AVERAGE($C$58:$C$381) -> 0.16263388
A68: 36526 | B68: =+'BRL e USD Chart 99'!F69/USDBRL!D566-1 -> 0.09425219 | C68: =+B68 -> 0.09425219 | E68: =AVERAGE($C$58:$C$381) -> 0.16263388
A69: 36557 | B69: =+'BRL e USD Chart 99'!F70/USDBRL!D567-1 -> 0.10756525 | C69: =+B69 -> 0.10756525 | E69: =AVERAGE($C$58:$C$381) -> 0.16263388
... A105: 37653 | B105: =+'BRL e USD Chart 99'!F106/USDBRL!D603-1 -> -0.32820591 | C105: =+B105 -> -0.32820591 | E105: =AVERAGE($C$58:$C$381) -> 0.16263388
A106: 37681 | B106: =+'BRL e USD Chart 99'!F107/USDBRL!D604-1 -> -0.29544135 | C106: =+B106 -> -0.29544135 | E106: =AVERAGE($C$58:$C$381) -> 0.16263388 | F106: =AVERAGE(B58:B106) -> -0.072144009
A107: 37712 | B107: =+'BRL e USD Chart 99'!F108/USDBRL!D605-1 -> -0.21228527 | C107: =+B107 -> -0.21228527 | E107: =AVERAGE($C$58:$C$381) -> 0.16263388 | F107: =AVERAGE(B59:B107) -> -0.076469404
A108: 37742 | B108: =+'BRL e USD Chart 99'!F109/USDBRL!D606-1 -> -0.16223148 | C108: =+B108 -> -0.16223148 | E108: =AVERAGE($C$58:$C$381) -> 0.16263388 | F108: =AVERAGE(B60:B108) -> -0.082191181
A109: 37773 | B109: =+'BRL e USD Chart 99'!F110/USDBRL!D607-1 -> -0.14402404 | C109: =+B109 -> -0.14402404 | E109: =AVERAGE($C$58:$C$381) -> 0.16263388 | F109: =AVERAGE(B61:B109) -> -0.08775398
A110: 37803 | B110: =+'BRL e USD Chart 99'!F111/USDBRL!D608-1 -> -0.14129933 | C110: =+B110 -> -0.14129933 | E110: =AVERAGE($C$58:$C$381) -> 0.16263388 | F110: =AVERAGE(B62:B110) -> -0.092234179
A111: 37834 | B111: =+'BRL e USD Chart 99'!F112/USDBRL!D609-1 -> -0.17663362 | C111: =+B111 -> -0.17663362 | E111: =AVERAGE($C$58:$C$381) -> 0.16263388 | F111: =AVERAGE(B63:B111) -> -0.097171546
A112: 37865 | B112: =+'BRL e USD Chart 99'!F113/USDBRL!D610-1 -> -0.15072673 | C112: =+B112 -> -0.15072673 | E112: =AVERAGE($C$58:$C$381) -> 0.16263388 | F112: =AVERAGE(B64:B112) -> -0.10069681
A113: 37895 | B113: =+'BRL e USD Chart 99'!F114/USDBRL!D611-1 -> -0.13001512 | C113: =+B113 -> -0.13001512 | E113: =AVERAGE($C$58:$C$381) -> 0.16263388 | F113: =AVERAGE(B65:B113) -> -0.10360344
A114: 37926 | B114: =+'BRL e USD Chart 99'!F115/USDBRL!D612-1 -> -0.13955275 | C114: =+B114 -> -0.13955275 | E114: =AVERAGE($C$58:$C$381) -> 0.16263388 | F114: =AVERAGE(B66:B114) -> -0.10612486
A115: 37956 | B115: =+'BRL e USD Chart 99'!F116/USDBRL!D613-1 -> -0.13688956 | C115: =+B115 -> -0.13688956 | E115: =AVERAGE($C$58:$C$381) -> 0.16263388 | F115: =AVERAGE(B67:B115) -> -0.10919877
A116: 37987 | B116: =+'BRL e USD Chart 99'!F117/USDBRL!D614-1 -> -0.11284126 | C116: =+B116 -> -0.11284126 | E116: =AVERAGE($C$58:$C$381) -> 0.16263388 | F116: =AVERAGE(B68:B116) -> -0.11288994
A117: 38018 | B117: =+'BRL e USD Chart 99'!F118/USDBRL!D615-1 -> -0.13616985 | C117: =+B117 -> -0.13616985 | E117: =AVERAGE($C$58:$C$381) -> 0.16263388 | F117: =AVERAGE(B69:B117) -> -0.11759243
... A376: 45901 | B376: =+'BRL e USD Chart 99'!F377/USDBRL!D874-1 -> -0.11933002 | C376: =+B376 -> -0.11933002 | E376: =AVERAGE($C$58:$C$381) -> 0.16263388 | F376: =AVERAGE(B328:B376) -> -0.12876646
A377: 45931 | E377: =AVERAGE($C$58:$C$381) -> 0.16263388 | F377: =AVERAGE(B329:B377) -> -0.12847002
A378: 45962 | B378: =+'BRL e USD Chart 99'!F379/USDBRL!D876-1 -> -0.10968784 | C378: =+B378 -> -0.10968784 | E378: =AVERAGE($C$58:$C$381) -> 0.16263388 | F378: =AVERAGE(B330:B378) -> -0.12700827
A379: 45992 | B379: =+'BRL e USD Chart 99'!F380/USDBRL!D877-1 -> -0.12512984 | C379: =+B379 -> -0.12512984 | E379: =AVERAGE($C$58:$C$381) -> 0.16263388 | F379: =AVERAGE(B331:B379) -> -0.12588307
A380: 46023 | B380: =+'BRL e USD Chart 99'!F381/USDBRL!D878-1 -> -0.10911896 | C380: =+B380 -> -0.10911896 | E380: =AVERAGE($C$58:$C$381) -> 0.16263388 | F380: =AVERAGE(B332:B380) -> -0.12421434
A381: 46054 | B381: =+'BRL e USD Chart 99'!F382/USDBRL!D879-1 -> -0.082178975 | C381: =+B381 -> -0.082178975 | E381: =AVERAGE($C$58:$C$381) -> 0.16263388 | F381: =AVERAGE(B333:B381) -> -0.12229033
A382: 46082 | B382: =+'BRL e USD Chart 99'!F383/USDBRL!D880-1 -> -0.088612538 | C382: =+B382 -> -0.088612538 | E382: =AVERAGE($C$58:$C$381) -> 0.16263388 | F382: =AVERAGE(B334:B382) -> -0.12159442
A383: 46113 | B383: =+'BRL e USD Chart 99'!F384/USDBRL!D881-1 -> -0.053791808 | C383: =+B383 -> -0.053791808 | E383: =AVERAGE($C$58:$C$381) -> 0.16263388 | F383: =AVERAGE(B335:B383) -> -0.12110227
A384: 46143 | B384: =+'BRL e USD Chart 99'!F385/USDBRL!D882-1 -> -0.042429604 | C384: =+B384 -> -0.042429604 | E384: =AVERAGE($C$58:$C$381) -> 0.16263388 | F384: =AVERAGE(B336:B384) -> -0.12131957
A385: 46174 | B385: =+'BRL e USD Chart 99'!F386/USDBRL!D883-1 -> -0.057963505 | C385: =+B385 -> -0.057963505 | E385: =AVERAGE($C$58:$C$381) -> 0.16263388 | F385: =AVERAGE(B337:B385) -> -0.12092437
A386: 46204 | B386: =+'BRL e USD Chart 99'!F387/USDBRL!D884-1 -> -0.047127536 | C386: =+B386 -> -0.047127536 | E386: =AVERAGE($C$58:$C$381) -> 0.16263388 | F386: =AVERAGE(B338:B386) -> -0.11979369
A387: 46235 | B387: =+'BRL e USD Chart 99'!F388/USDBRL!D885-1 -> -0.046073553 | C387: =+B387 -> -0.046073553 | E387: =AVERAGE($C$58:$C$381) -> 0.16263388 | F387: =AVERAGE(B339:B387) -> -0.11746101
E978: 1

Sheet USDBRL
A1: Data | B1: 3697 - Taxa de câmbio - Livre - Dólar americano (compra) - Média de período - mensal - u.m.c./US$ | C1: 3698 - Taxa de câmbio - Livre - Dólar americano (venda) - Média de período - mensal - u.m.c./US$ | D1: USDBRL
A2: 19360 | B2: 18.38 | C2: 18.72 | D2: =(B2+C2)/2 -> 18.55
A3: 19391 | B3: 36.5 | C3: 38 | D3: =(B3+C3)/2 -> 37.25
A4: 19419 | B4: 36.7903 | C4: 38.2581 | D4: =(B4+C4)/2 -> 37.5242
A5: 19450 | B5: 40.93 | C5: 41.9333 | D5: =(B5+C5)/2 -> 41.43165
A6: 19480 | B6: 39.2581 | C6: 40.2581 | D6: =(B6+C6)/2 -> 39.7581
A7: 19511 | B7: 43.0933 | C7: 44.07 | D7: =(B7+C7)/2 -> 43.58165
A8: 19541 | B8: 43.5774 | C8: 44.38 | D8: =(B8+C8)/2 -> 43.9787
A9: 19572 | B9: 39.6677 | C9: 40.6677 | D9: =(B9+C9)/2 -> 40.1677
A10: 19603 | B10: 37.4867 | C10: 38.4867 | D10: =(B10+C10)/2 -> 37.9867
A11: 19633 | B11: 37.1 | C11: 38.1 | D11: =(B11+C11)/2 -> 37.6
A12: 19664 | B12: 37.5633 | C12: 38.5967 | D12: =(B12+C12)/2 -> 38.08
A13: 19694 | B13: 51.1129 | C13: 53.0968 | D13: =(B13+C13)/2 -> 52.10485
... A887: 46309 | B887: 4.9859 | C887: 4.9853 | D887: =(B887+C887)/2 -> 4.9856

Sheet BRL IPCA
A1: Data | B1: 193 - Índice de preços ao consumidor-São Paulo (IPC-Fipe) - Var. % mensal | C1: Cruzeiro (nov/42 a jan/67 | D1: Cruzeiro Novo (fev-67 a mai-70) | E1: Cruzeiro (jun-70 a fev-86) | F1: Cruzado (mar-86 a dez-88) | G1: Cruzado Novo (jan-89 a fev-90) | H1: Cruzeiro (mar-90 a jul/93) | I1: Cruzeiro Real (ago/93 a jun-94) | J1: Real (jul/94 a jun-21) | K1: Cruzeiro (nov/42 a jan/67 | L1: Cruzeiro Novo (fev-67 a mai-70) | M1: Cruzeiro (jun-70 a fev-86) | N1: Cruzado (mar-86 a dez-88) | O1: Cruzado Novo (jan-89 a fev-90) | P1: Cruzeiro (mar-90 a jul/93) | Q1: Cruzeiro Real (ago/93 a jun-94) | R1: Real (jul/94 a jun-21) | S1: Cruzeiro (nov/42 a jan/67 | T1: Cruzeiro Novo (fev-67 a mai-70) | U1: Cruzeiro (jun-70 a fev-86) | V1: Cruzado (mar-86 a dez-88) | W1: Cruzado Novo (jan-89 a fev-90) | X1: Cruzeiro (mar-90 a jul/93) | Y1: Cruzeiro Real (ago/93 a jun-94) | Z1: Real (jul/94 a jun-21) | AA1: 433 - Índice nacional de preços ao consumidor-amplo (IPCA) - Var. % mensal | AB1: 1788 - BM - Base monetária restrita (saldo em final de período) - u.m.c. (mil) | AC1: 1827 - Meios de pagamento - M1 (saldo em final de período) - u.m.c. (mil) | AD1: 1837 - Meios de pagamento amplos - M2 (saldo em final de período) - u.m.c. (mil)
A2: 14277 | B2: -0.0152 | AA2: - | AB2: - | AC2: - | AD2: -
A3: 14305 | B3: 0.0248 | AA3: - | AB3: - | AC3: - | AD3: -
A4: 14336 | B4: 0.0181 | AA4: - | AB4: - | AC4: - | AD4: -
A5: 14366 | B5: 0 | AA5: - | AB5: - | AC5: - | AD5: -
A6: 14397 | B6: -0.003 | AA6: - | AB6: - | AC6: - | AD6: -
A7: 14427 | B7: -0.0089 | AA7: - | AB7: - | AC7: - | AD7: -
A8: 14458 | B8: 0.007 | AA8: - | AB8: - | AC8: - | AD8: -
A9: 14489 | B9: -0.0099 | AA9: - | AB9: - | AC9: - | AD9: -
A10: 14519 | B10: 0.0131 | AA10: - | AB10: - | AC10: - | AD10: -
A11: 14550 | B11: 0.003 | AA11: - | AB11: - | AC11: - | AD11: -
A12: 14580 | B12: -0.0138 | AA12: - | AB12: - | AC12: - | AD12: -
A13: 14611 | B13: 0.0481 | AA13: - | AB13: - | AC13: - | AD13: -
... A45: 15585 | B45: 0.0208 | AA45: - | AB45: - | AC45: - | AD45: -
A46: 15615 | B46: -0.012 | C46: 100 | K46: 100 | AA46: - | AB46: - | AC46: - | AD46: -
A47: 15646 | B47: 0.0028 | C47: =+$C$46/(1+((K47/100)-1)) -> 99.720782 | K47: =+K46*(1+S47) -> 100.28 | S47: 0.0028 | AA47: - | AB47: - | AC47: - | AD47: -
A48: 15676 | B48: -0.0021 | C48: =+$C$46/(1+((K48/100)-1)) -> 99.930636 | K48: =+K47*(1+S48) -> 100.06941 | S48: -0.0021 | AA48: - | AB48: - | AC48: - | AD48: -
A49: 15707 | B49: 0.0185 | C49: =+$C$46/(1+((K49/100)-1)) -> 98.115499 | K49: =+K48*(1+S49) -> 101.9207 | S49: 0.0185 | AA49: - | AB49: - | AC49: - | AD49: -
A50: 15738 | B50: 0.014 | C50: =+$C$46/(1+((K50/100)-1)) -> 96.760848 | K50: =+K49*(1+S50) -> 103.34759 | S50: 0.014 | AA50: - | AB50: - | AC50: - | AD50: -
A51: 15766 | B51: -0.0014 | C51: =+$C$46/(1+((K51/100)-1)) -> 96.896503 | K51: =+K50*(1+S51) -> 103.2029 | S51: -0.0014 | AA51: - | AB51: - | AC51: - | AD51: -
A52: 15797 | B52: 0.0311 | C52: =+$C$46/(1+((K52/100)-1)) -> 93.973914 | K52: =+K51*(1+S52) -> 106.41251 | S52: 0.0311 | AA52: - | AB52: - | AC52: - | AD52: -
A53: 15827 | B53: 0.004 | C53: =+$C$46/(1+((K53/100)-1)) -> 93.599516 | K53: =+K52*(1+S53) -> 106.83816 | S53: 0.004 | AA53: - | AB53: - | AC53: - | AD53: -
A54: 15858 | B54: -0.0047 | C54: =+$C$46/(1+((K54/100)-1)) -> 94.041511 | K54: =+K53*(1+S54) -> 106.33602 | S54: -0.0047 | AA54: - | AB54: - | AC54: - | AD54: -
A55: 15888 | B55: 0.0308 | C55: =+$C$46/(1+((K55/100)-1)) -> 91.231578 | K55: =+K54*(1+S55) -> 109.61117 | S55: 0.0308 | AA55: - | AB55: - | AC55: - | AD55: -
A56: 15919 | B56: 0.0019 | C56: =+$C$46/(1+((K56/100)-1)) -> 91.058567 | K56: =+K55*(1+S56) -> 109.81943 | S56: 0.0019 | AA56: - | AB56: - | AC56: - | AD56: -
A57: 15950 | B57: 0.0208 | C57: =+$C$46/(1+((K57/100)-1)) -> 89.203142 | K57: =+K56*(1+S57) -> 112.10367 | S57: 0.0208 | AA57: - | AB57: - | AC57: - | AD57: -
A58: 15980 | B58: 0.0419 | C58: =+$C$46/(1+((K58/100)-1)) -> 85.615838 | K58: =+K57*(1+S58) -> 116.80082 | S58: 0.0419 | AA58: - | AB58: - | AC58: - | AD58: -
... A84: 16772 | B84: -0.0008 | C84: =+$C$46/(1+((K84/100)-1)) -> 53.143297 | K84: =+K83*(1+S84) -> 188.17049 | S84: -0.0008 | AA84: - | AB84: - | AC84: - | AD84: -
A85: 16803 | B85: -0.0314 | C85: =+$C$46/(1+((K85/100)-1)) -> 54.866092 | K85: =+K84*(1+S85) -> 182.26193 | S85: -0.0314 | AA85: - | AB85: 22900000 | AC85: 39600000 | AD85: -
A86: 16834 | B86: 0.0211 | C86: =+$C$46/(1+((K86/100)-1)) -> 53.73234 | K86: =+K85*(1+S86) -> 186.10766 | S86: 0.0211 | AA86: - | AB86: 23600000 | AC86: 39300000 | AD86: -
A87: 16862 | B87: 0.0829 | C87: =+$C$46/(1+((K87/100)-1)) -> 49.61893 | K87: =+K86*(1+S87) -> 201.53598 | S87: 0.0829 | AA87: - | AB87: 23900000 | AC87: 38600000 | AD87: -
A88: 16893 | B88: 0.0134 | C88: =+$C$46/(1+((K88/100)-1)) -> 48.962829 | K88: =+K87*(1+S88) -> 204.23657 | S88: 0.0134 | AA88: - | AB88: 23700000 | AC88: 42000000 | AD88: -
A89: 16923 | B89: 0.016 | C89: =+$C$46/(1+((K89/100)-1)) -> 48.19176 | K89: =+K88*(1+S89) -> 207.50435 | S89: 0.016 | AA89: - | AB89: 24200000 | AC89: 42700000 | AD89: -
A90: 16954 | B90: 0.0199 | C90: =+$C$46/(1+((K90/100)-1)) -> 47.251456 | K90: =+K89*(1+S90) -> 211.63369 | S90: 0.0199 | AA90: - | AB90: 24900000 | AC90: 43400000 | AD90: -
A91: 16984 | B91: 0.0336 | C91: =+$C$46/(1+((K91/100)-1)) -> 45.715418 | K91: =+K90*(1+S91) -> 218.74458 | S91: 0.0336 | AA91: - | AB91: 25500000 | AC91: 43800000 | AD91: -
A92: 17015 | B92: 0.0286 | C92: =+$C$46/(1+((K92/100)-1)) -> 44.444311 | K92: =+K91*(1+S92) -> 225.00068 | S92: 0.0286 | AA92: - | AB92: 25700000 | AC92: 44900000 | AD92: -
A93: 17046 | B93: -0.0246 | C93: =+$C$46/(1+((K93/100)-1)) -> 45.565215 | K93: =+K92*(1+S93) -> 219.46566 | S93: -0.0246 | AA93: - | AB93: 25700000 | AC93: 45300000 | AD93: -
A94: 17076 | B94: 0.0104 | C94: =+$C$46/(1+((K94/100)-1)) -> 45.096215 | K94: =+K93*(1+S94) -> 221.7481 | S94: 0.0104 | AA94: - | AB94: 25600000 | AC94: 45400000 | AD94: -
A95: 17107 | B95: 0.0128 | C95: =+$C$46/(1+((K95/100)-1)) -> 44.526278 | K95: =+K94*(1+S95) -> 224.58648 | S95: 0.0128 | AA95: - | AB95: 25300000 | AC95: 45800000 | AD95: -
A96: 17137 | B96: -0.0032 | C96: =+$C$46/(1+((K96/100)-1)) -> 44.66922 | K96: =+K95*(1+S96) -> 223.8678 | S96: -0.0032 | AA96: - | AB96: 25700000 | AC96: 45400000 | AD96: -
... A336: 24442 | B336: 0.018 | C336: =+$C$46/(1+((K336/100)-1)) -> 0.24557719 | K336: =+K335*(1+S336) -> 40720.393 | S336: 0.018 | AA336: - | AB336: 4761100000 | AC336: 10482000000 | AD336: -
A337: 24473 | B337: 0.0298 | C337: =+$C$46/(1+((K337/100)-1)) -> 0.23847077 | D337: 100 | K337: =+K336*(1+S337) -> 41933.861 | L337: 100 | S337: 0.0298 | AA337: - | AB337: 4630500000 | AC337: 10338000000 | AD337: -
A338: 24504 | B338: 0.0152 | D338: =+$D$337/(1+((L338/100)-1)) -> 98.502758 | L338: =+L337*(1+T338) -> 101.52 | T338: 0.0152 | AA338: - | AB338: 4844600 | AC338: 10584000 | AD338: -
A339: 24532 | B339: 0.0313 | D339: =+$D$337/(1+((L339/100)-1)) -> 95.513195 | L339: =+L338*(1+T339) -> 104.69758 | T339: 0.0313 | AA339: - | AB339: 5145000 | AC339: 10989000 | AD339: -
A340: 24563 | B340: 0.0378 | D340: =+$D$337/(1+((L340/100)-1)) -> 92.034299 | L340: =+L339*(1+T340) -> 108.65514 | T340: 0.0378 | AA340: - | AB340: 4979100 | AC340: 11599000 | AD340: -
A341: 24593 | B341: 0.0104 | D341: =+$D$337/(1+((L341/100)-1)) -> 91.086994 | L341: =+L340*(1+T341) -> 109.78516 | T341: 0.0104 | AA341: - | AB341: 5066000 | AC341: 12189000 | AD341: -
A342: 24624 | B342: 0.0101 | D342: =+$D$337/(1+((L342/100)-1)) -> 90.176214 | L342: =+L341*(1+T342) -> 110.89399 | T342: 0.0101 | AA342: - | AB342: 5188500 | AC342: 12753000 | AD342: -
A343: 24654 | B343: 0.0231 | D343: =+$D$337/(1+((L343/100)-1)) -> 88.140176 | L343: =+L342*(1+T343) -> 113.45564 | T343: 0.0231 | AA343: - | AB343: 5281600 | AC343: 12971000 | AD343: -
A344: 24685 | B344: 0.0101 | D344: =+$D$337/(1+((L344/100)-1)) -> 87.258862 | L344: =+L343*(1+T344) -> 114.60154 | T344: 0.0101 | AA344: - | AB344: 5246000 | AC344: 13479000 | AD344: -
A345: 24716 | B345: 0.0165 | D345: =+$D$337/(1+((L345/100)-1)) -> 85.842461 | L345: =+L344*(1+T345) -> 116.49247 | T345: 0.0165 | AA345: - | AB345: 5550300 | AC345: 13845000 | AD345: -
A346: 24746 | B346: 0.0183 | D346: =+$D$337/(1+((L346/100)-1)) -> 84.299775 | L346: =+L345*(1+T346) -> 118.62428 | T346: 0.0183 | AA346: - | AB346: 5511800 | AC346: 14120000 | AD346: -
A347: 24777 | B347: 0.0179 | D347: =+$D$337/(1+((L347/100)-1)) -> 82.817345 | L347: =+L346*(1+T347) -> 120.74765 | T347: 0.0179 | AA347: - | AB347: 5756300 | AC347: 14771000 | AD347: -
A348: 24807 | B348: 0.0079 | D348: =+$D$337/(1+((L348/100)-1)) -> 82.168216 | L348: =+L347*(1+T348) -> 121.70156 | T348: 0.0079 | AA348: - | AB348: 6095400 | AC348: 15004000 | AD348: -
A349: 24838 | B349: 0.0222 | D349: =+$D$337/(1+((L349/100)-1)) -> 80.383698 | L349: =+L348*(1+T349) -> 124.40333 | T349: 0.0222 | AA349: - | AB349: 6167900 | AC349: 15087000 | AD349: -
... A376: 25659 | B376: 0.0136 | D376: =+$D$337/(1+((L376/100)-1)) -> 50.745314 | L376: =+L375*(1+T376) -> 197.06253 | T376: 0.0136 | AA376: - | AB376: 9594000 | AC376: 28703000 | AD376: -
A377: 25689 | B377: 0.0098 | D377: =+$D$337/(1+((L377/100)-1)) -> 50.252836 | E377: 100 | L377: =+L376*(1+T377) -> 198.99374 | M377: 100 | T377: 0.0098 | AA377: - | AB377: 9927000 | AC377: 29723000 | AD377: -
A378: 25720 | B378: 0.0151 | E378: =+E$377/(1+((M378/100)-1)) -> 98.512462 | M378: =+M377*(1+U378) -> 101.51 | U378: 0.0151 | AA378: - | AB378: 10391000 | AC378: 30919000 | AD378: -
A379: 25750 | B379: 0.0079 | E379: =+E$377/(1+((M379/100)-1)) -> 97.740313 | M379: =+M378*(1+U379) -> 102.31193 | U379: 0.0079 | AA379: - | AB379: 10275000 | AC379: 30891000 | AD379: -
A380: 25781 | B380: 0.0158 | E380: =+E$377/(1+((M380/100)-1)) -> 96.220037 | M380: =+M379*(1+U380) -> 103.92846 | U380: 0.0158 | AA380: - | AB380: 10235000 | AC380: 31258000 | AD380: -
A381: 25812 | B381: 0.0242 | E381: =+E$377/(1+((M381/100)-1)) -> 93.946531 | M381: =+M380*(1+U381) -> 106.44353 | U381: 0.0242 | AA381: - | AB381: 10190000 | AC381: 31423000 | AD381: -
A382: 25842 | B382: 0.0115 | E382: =+E$377/(1+((M382/100)-1)) -> 92.878429 | M382: =+M381*(1+U382) -> 107.66763 | U382: 0.0115 | AA382: - | AB382: 10646000 | AC382: 32049000 | AD382: -
A383: 25873 | B383: 0.0096 | E383: =+E$377/(1+((M383/100)-1)) -> 91.995274 | M383: =+M382*(1+U383) -> 108.70124 | U383: 0.0096 | AA383: - | AB383: 10889000 | AC383: 33337000 | AD383: -
A384: 25903 | B384: 0.0152 | E384: =+E$377/(1+((M384/100)-1)) -> 90.617882 | M384: =+M383*(1+U384) -> 110.35349 | U384: 0.0152 | AA384: - | AB384: 12361000 | AC384: 35455000 | AD384: -
A385: 25934 | B385: 0.0218 | E385: =+E$377/(1+((M385/100)-1)) -> 88.684559 | M385: =+M384*(1+U385) -> 112.7592 | U385: 0.0218 | AA385: - | AB385: 11641000 | AC385: 34489000 | AD385: -
A386: 25965 | B386: 0.0185 | E386: =+E$377/(1+((M386/100)-1)) -> 87.073696 | M386: =+M385*(1+U386) -> 114.84525 | U386: 0.0185 | AA386: - | AB386: 11698000 | AC386: 34785000 | AD386: -
A387: 25993 | B387: 0.029 | E387: =+E$377/(1+((M387/100)-1)) -> 84.619724 | M387: =+M386*(1+U387) -> 118.17576 | U387: 0.029 | AA387: - | AB387: 11335000 | AC387: 35056000 | AD387: -
A388: 26024 | B388: 0.0133 | E388: =+E$377/(1+((M388/100)-1)) -> 83.509053 | M388: =+M387*(1+U388) -> 119.7475 | U388: 0.0133 | AA388: - | AB388: 11955000 | AC388: 36061000 | AD388: -
A389: 26054 | B389: 0.0174 | E389: =+E$377/(1+((M389/100)-1)) -> 82.080846 | M389: =+M388*(1+U389) -> 121.8311 | U389: 0.0174 | AA389: - | AB389: 12412000 | AC389: 37163000 | AD389: -
... A492: 29190 | B492: 0.0706 | E492: =+E$377/(1+((M492/100)-1)) -> 7.1623142 | M492: =+M491*(1+U492) -> 1396.1968 | U492: 0.0706 | AA492: - | AB492: 366247000 | AC492: 838226000 | AD492: -
A493: 29221 | B493: 0.0448 | E493: =+E$377/(1+((M493/100)-1)) -> 6.8552012 | M493: =+M492*(1+U493) -> 1458.7464 | U493: 0.0448 | AA493: 6.62 | AB493: 339824000 | AC493: 814000000 | AD493: -
A494: 29252 | B494: 0.0335 | E494: =+E$377/(1+((M494/100)-1)) -> 6.6329959 | M494: =+M493*(1+U494) -> 1507.6144 | U494: 0.0335 | AA494: 4.62 | AB494: 323939000 | AC494: 845000000 | AD494: -
A495: 29281 | B495: 0.0434 | E495: =+E$377/(1+((M495/100)-1)) -> 6.3570978 | M495: =+M494*(1+U495) -> 1573.0449 | U495: 0.0434 | AA495: 6.04 | AB495: 337933000 | AC495: 878000000 | AD495: -
A496: 29312 | B496: 0.0393 | E496: =+E$377/(1+((M496/100)-1)) -> 6.1167111 | M496: =+M495*(1+U496) -> 1634.8655 | U496: 0.0393 | AA496: 5.29 | AB496: 364959000 | AC496: 957000000 | AD496: -
A497: 29342 | B497: 0.0652 | E497: =+E$377/(1+((M497/100)-1)) -> 5.7423123 | M497: =+M496*(1+U497) -> 1741.4588 | U497: 0.0652 | AA497: 5.7 | AB497: 372738000 | AC497: 1011000000 | AD497: -
A498: 29373 | B498: 0.0502 | E498: =+E$377/(1+((M498/100)-1)) -> 5.4678274 | M498: =+M497*(1+U498) -> 1828.88 | U498: 0.0502 | AA498: 5.31 | AB498: 416236000 | AC498: 1101000000 | AD498: -
A499: 29403 | B499: 0.0524 | E499: =+E$377/(1+((M499/100)-1)) -> 5.195579 | M499: =+M498*(1+U499) -> 1924.7133 | U499: 0.0524 | AA499: 5.55 | AB499: 439890000 | AC499: 1076000000 | AD499: -
A500: 29434 | B500: 0.0546 | E500: =+E$377/(1+((M500/100)-1)) -> 4.9265874 | M500: =+M499*(1+U500) -> 2029.8026 | U500: 0.0546 | AA500: 4.95 | AB500: 446615000 | AC500: 1129000000 | AD500: -
A501: 29465 | B501: 0.0615 | E501: =+E$377/(1+((M501/100)-1)) -> 4.6411562 | M501: =+M500*(1+U501) -> 2154.6355 | U501: 0.0615 | AA501: 4.23 | AB501: 459175000 | AC501: 1170000000 | AD501: -
A502: 29495 | B502: 0.0678 | E502: =+E$377/(1+((M502/100)-1)) -> 4.3464659 | M502: =+M501*(1+U502) -> 2300.7198 | U502: 0.0678 | AA502: 9.48 | AB502: 468517000 | AC502: 1221000000 | AD502: -
A503: 29526 | B503: 0.0682 | E503: =+E$377/(1+((M503/100)-1)) -> 4.0689626 | M503: =+M502*(1+U503) -> 2457.6289 | U503: 0.0682 | AA503: 6.67 | AB503: 512562000 | AC503: 1326000000 | AD503: -
A504: 29556 | B504: 0.0497 | E504: =+E$377/(1+((M504/100)-1)) -> 3.87631 | M504: =+M503*(1+U504) -> 2579.773 | U504: 0.0497 | AA504: 6.61 | AB504: 580353000 | AC504: 1487000000 | AD504: -
... A565: 31413 | B565: 0.1405 | E565: =+E$377/(1+((M565/100)-1)) -> 0.037889802 | M565: =+M564*(1+U565) -> 263923.26 | U565: 0.1405 | AA565: 14.37 | AB565: 45941000000 | AC565: 102136000000 | AD565: -
A566: 31444 | B566: 0.1086 | E566: =+E$377/(1+((M566/100)-1)) -> 0.034178064 | F566: 100 | M566: =+M565*(1+U566) -> 292585.32 | N566: 100 | U566: 0.1086 | AA566: 12.72 | AB566: 51535000000 | AC566: 116536000000 | AD566: -
A567: 31472 | B567: 0.0183 | F567: =+F$566/(1+((N567/100)-1)) -> 98.202887 | N567: =+N566*(1+V567) -> 101.83 | V567: 0.0183 | AA567: 4.77 | AB567: 70029000 | AC567: 210012000 | AD567: -
A568: 31503 | B568: 0.0231 | F568: =+F$566/(1+((N568/100)-1)) -> 95.985619 | N568: =+N567*(1+V568) -> 104.18227 | V568: 0.0231 | AA568: 0.78 | AB568: 94782000 | AC568: 250481000 | AD568: -
A569: 31533 | B569: 0.0192 | F569: =+F$566/(1+((N569/100)-1)) -> 94.177413 | N569: =+N568*(1+V569) -> 106.18257 | V569: 0.0192 | AA569: 1.4 | AB569: 109024000 | AC569: 288894000 | AD569: -
A570: 31564 | B570: 0.0096 | F570: =+F$566/(1+((N570/100)-1)) -> 93.281907 | N570: =+N569*(1+V570) -> 107.20193 | V570: 0.0096 | AA570: 1.27 | AB570: 120553000 | AC570: 334090000 | AD570: -
A571: 31594 | B571: 0.0107 | F571: =+F$566/(1+((N571/100)-1)) -> 92.294357 | N571: =+N570*(1+V571) -> 108.34899 | V571: 0.0107 | AA571: 1.71 | AB571: 137558000 | AC571: 333311000 | AD571: -
A572: 31625 | B572: 0.0188 | F572: =+F$566/(1+((N572/100)-1)) -> 90.591242 | N572: =+N571*(1+V572) -> 110.38595 | V572: 0.0188 | AA572: 3.55 | AB572: 145798000 | AC572: 356193000 | AD572: -
A573: 31656 | B573: 0.0143 | F573: =+F$566/(1+((N573/100)-1)) -> 89.314051 | N573: =+N572*(1+V573) -> 111.96447 | V573: 0.0143 | AA573: 1.72 | AB573: 149852000 | AC573: 375906000 | AD573: -
A574: 31686 | B574: 0.0308 | F574: =+F$566/(1+((N574/100)-1)) -> 86.645373 | N574: =+N573*(1+V574) -> 115.41297 | V574: 0.0308 | AA574: 1.9 | AB574: 157605000 | AC574: 403240000 | AD574: -
A575: 31717 | B575: 0.0443 | F575: =+F$566/(1+((N575/100)-1)) -> 82.969811 | N575: =+N574*(1+V575) -> 120.52577 | V575: 0.0443 | AA575: 5.45 | AB575: 172456000 | AC575: 421915000 | AD575: -
A576: 31747 | B576: 0.103 | F576: =+F$566/(1+((N576/100)-1)) -> 75.22195 | N576: =+N575*(1+V576) -> 132.93992 | V576: 0.103 | AA576: 11.65 | AB576: 178895000 | AC576: 455476000 | AD576: -
A577: 31778 | B577: 0.1375 | F577: =+F$566/(1+((N577/100)-1)) -> 66.129187 | N577: =+N576*(1+V577) -> 151.21916 | V577: 0.1375 | AA577: 13.21 | AB577: 172444000 | AC577: 356055000 | AD577: -
A578: 31809 | B578: 0.1128 | F578: =+F$566/(1+((N578/100)-1)) -> 59.425941 | N578: =+N577*(1+V578) -> 168.27668 | V578: 0.1128 | AA578: 12.64 | AB578: 164309000 | AC578: 377484000 | AD578: -
... A594: 32295 | B594: 0.217 | F594: =+F$566/(1+((N594/100)-1)) -> 6.0878789 | N594: =+N593*(1+V594) -> 1642.6082 | V594: 0.217 | AA594: 22 | AB594: 911031000 | AC594: 1844000000 | AD594: -
A595: 32325 | B595: 0.2265 | F595: =+F$566/(1+((N595/100)-1)) -> 4.9636191 | N595: =+N594*(1+V595) -> 2014.659 | V595: 0.2265 | AA595: 21.91 | AB595: 1003891000 | AC595: 2047000000 | AD595: 14328802230
A596: 32356 | B596: 0.1967 | F596: =+F$566/(1+((N596/100)-1)) -> 4.1477556 | N596: =+N595*(1+V596) -> 2410.9424 | V596: 0.1967 | AA596: 21.59 | AB596: 1083191000 | AC596: 2275000000 | AD596: 17432364000
A597: 32387 | B597: 0.236 | F597: =+F$566/(1+((N597/100)-1)) -> 3.3557893 | N597: =+N596*(1+V597) -> 2979.9248 | V597: 0.236 | AA597: 27.45 | AB597: 1426396000 | AC597: 2899000000 | AD597: 21652380000
A598: 32417 | B598: 0.2848 | F598: =+F$566/(1+((N598/100)-1)) -> 2.6119157 | N598: =+N597*(1+V598) -> 3828.6074 | V598: 0.2848 | AA598: 25.62 | AB598: 1850104000 | AC598: 3837000000 | AD598: 27485102903
...

Sheet BRL e USD Chart
A1: Data | C1: Mês | D1: Real (jul/94 a set/23) | E1: Dólar (jul/94 a set/23) | F1: Câmbio pela PPC | G1: Cruzado (fev-86 a jan-89) | H1: Cruzado Novo (jan-89 a mar-90) | I1: Cruzeiro (mar-90 a ago/93) | J1: Cruzeiro real (ago/93 a jun-94) | K1: Real (jul/94 a jun-21)
A2: 15615 | C2: 34486 | D2: 100 | E2: =+'USD PP 1994'!C989 -> 100 | F2: =+E2/D2 -> 1 | G2: 100 | H2: 100 | I2: 100 | J2: 100 | K2: 100
A3: 15646 | C3: 34516 | D3: 93.597903 | E3: =+'USD PP 1994'!C990 -> 99.704142 | F3: =+E3/D3 -> 1.0652391 | G3: 98.202887 | H3: 87.711604 | I3: 83.201597 | J3: 74.560095 | K3: 93.501636 | P3: =5.2/4.9-1 -> 0.06122449
A4: 15676 | C4: 34547 | D4: 91.888772 | E4: =+'USD PP 1994'!C991 -> 99.260355 | F4: =+E4/D4 -> 1.0802229 | G4: 95.985619 | H4: 82.389258 | I4: 76.662303 | J4: 55.135765 | K4: 91.713228
A5: 15707 | C5: 34578 | D5: 90.50406 | E5: =+'USD PP 1994'!C992 -> 98.964497 | F5: =+E5/D5 -> 1.0934813 | G5: 94.177413 | H5: 74.88571 | I5: 68.632321 | J5: 40.588755 | K5: 90.967296
A6: 15738 | C6: 34608 | D6: 88.193393 | E6: =+'USD PP 1994'!C993 -> 98.964497 | F6: =+E6/D6 -> 1.1221305 | G6: 93.281907 | H6: 64.22996 | I6: 61.65872 | J6: 29.301729 | K6: 88.172237
A7: 15766 | C7: 34639 | D7: 85.782894 | E7: =+'USD PP 1994'!C994 -> 98.816568 | F7: =+E7/D7 -> 1.1519379 | G7: 92.294357 | H7: 51.265033 | I7: 55.136117 | J7: 20.885053 | K7: 85.587494
A8: 15797 | C8: 34669 | D8: 84.340668 | E8: =+'USD PP 1994'!C995 -> 98.816568 | F8: =+E8/D8 -> 1.1716361 | G8: 90.591242 | H8: 40.032042 | I8: 48.736955 | J8: 15.113288 | K8: 84.530859
A9: 15827 | C9: 34700 | D9: 82.930844 | E9: =+'USD PP 1994'!C996 -> 98.372781 | F9: =+E9/D9 -> 1.1862026 | G9: 89.314051 | H9: 30.570479 | I9: 42.07628 | J9: 10.64766 | K9: 83.859979
A10: 15858 | C10: 34731 | D10: 82.093491 | E10: =+'USD PP 1994'!C997 -> 98.076923 | F10: =+E10/D10 -> 1.1946979 | G10: 86.645373 | H10: 22.506426 | I10: 35.48944 | J10: 7.2819448 | K10: 82.767448
A11: 15888 | C11: 34759 | D11: 80.840463 | E11: =+'USD PP 1994'!C998 -> 97.633136 | F11: =+E11/D11 -> 1.2077261 | G11: 82.969811 | H11: 16.393347 | I11: 30.586435 | J11: 5.0185698 | K11: 81.20825
A12: 15919 | C12: 34790 | D12: 78.922643 | E12: =+'USD PP 1994'!C999 -> 97.337278 | F12: =+E12/D12 -> 1.2333251 | G12: 75.22195 | H12: 11.467087 | I12: 25.273868 | J12: 3.3290679 | K12: 79.119495
A13: 15950 | C13: 34820 | D13: 76.870209 | E13: =+'USD PP 1994'!C1000 -> 97.189349 | F13: =+E13/D13 -> 1.2643305 | G13: 66.129187 | H13: 7.5530804 | I13: 20.967204 | K13: 77.590954
A14: 15980 | C14: 34851 | D14: 75.171336 | E14: =+'USD PP 1994'!C1001 -> 97.04142 | F14: =+E14/D14 -> 1.2909365 | G14: 59.425941 | H14: 4.3276688 | I14: 19.508005 | K14: 75.580512
A15: 16011 | C15: 34881 | D15: 73.438195 | E15: =+'USD PP 1994'!C1002 -> 97.04142 | F15: =+E15/D15 -> 1.3214026 | G15: 53.073092 | H15: 2.5432939 | I15: 18.199464 | K15: 72.869757
A16: 16041 | C16: 34912 | D16: 72.718284 | E16: =+'USD PP 1994'!C1003 -> 96.745562 | F16: =+E16/D16 -> 1.3304159 | G16: 45.536758 | H16: 1.419962 | I16: 17.208267 | K16: 71.84241
A17: 16072 | C17: 34943 | D17: 72.00543 | E17: =+'USD PP 1994'!C1004 -> 96.597633 | F17: =+E17/D17 -> 1.3415326 | G17: 36.000283 | I17: 15.67523 | K17: 71.314682
A18: 16103 | C18: 34973 | D18: 71.00427 | E18: =+'USD PP 1994'!C1005 -> 96.301775 | F18: =+E18/D18 -> 1.3562815 | G18: 28.40035 | I18: 14.083765 | K18: 70.274617
A19: 16132 | C19: 35004 | D19: 69.975628 | E19: =+'USD PP 1994'!C1006 -> 96.301775 | F19: =+E19/D19 -> 1.3762188 | G19: 25.998123 | I19: 12.308831 | K19: 69.461913
A20: 16163 | C20: 35034 | D20: 68.900776 | E20: =+'USD PP 1994'!C1007 -> 96.301775 | F20: =+E20/D20 -> 1.3976878 | G20: 24.890496 | I20: 10.591886 | K20: 68.631472
A21: 16193 | C21: 35065 | D21: 67.989714 | E21: =+'USD PP 1994'!C1008 -> 95.857988 | F21: =+E21/D21 -> 1.4098896 | G21: 23.320993 | I21: 8.4620008 | K21: 67.404707
A22: 16224 | C22: 35096 | D22: 67.296559 | E22: =+'USD PP 1994'!C1009 -> 95.414201 | F22: =+E22/D22 -> 1.4178169 | G22: 21.168188 | I22: 6.7485452 | K22: 67.136162
A23: 16254 | C23: 35125 | D23: 67.061843 | E23: =+'USD PP 1994'!C1010 -> 94.970414 | F23: =+E23/D23 -> 1.4161617 | G23: 18.666833 | I23: 5.475493 | K23: 66.982103
A24: 16285 | C24: 35156 | D24: 66.227378 | E24: =+'USD PP 1994'!C1011 -> 94.674556 | F24: =+E24/D24 -> 1.429538 | G24: 16.103203 | I24: 4.3494265 | K24: 65.914292
A25: 16316 | C25: 35186 | D25: 65.429142 | E25: =+'USD PP 1994'!C1012 -> 94.526627 | F25: =+E25/D25 -> 1.4447175 | G25: 14.03941 | I25: 3.5777137 | K25: 65.042719
A26: 16346 | C26: 35217 | D26: 64.659692 | E26: =+'USD PP 1994'!C1013 -> 94.378698 | F26: =+E26/D26 -> 1.4596218 | G26: 12.382616 | I26: 2.9388152 | K26: 64.138368
A27: 16377 | C27: 35247 | D27: 63.949849 | E27: =+'USD PP 1994'!C1014 -> 94.230769 | F27: =+E27/D27 -> 1.4735104 | G27: 10.436254 | I27: 2.394537 | K27: 63.30902
A28: 16407 | C28: 35278 | D28: 63.669702 | E28: =+'USD PP 1994'!C1015 -> 94.08284 | F28: =+E28/D28 -> 1.4776705 | G28: 8.6129027 | I28: 1.9542455 | K28: 63.094499
... A37: 16681 | C37: 35551 | D37: 60.744219 | E37: =+'USD PP 1994'!C1024 -> 92.455621 | F37: =+E37/D37 -> 1.5220481 | G37: 1.238539 | I37: 0.27939501 | K37: 60.750207
A38: 16711 | C38: 35582 | D38: 60.417962 | E38: =+'USD PP 1994'!C1025 -> 92.307692 | F38: =+E38/D38 -> 1.5278187 | I38: 0.22323027 | K38: 59.899632
A39: 16742 | C39: 35612 | D39: 60.285335 | E39: =+'USD PP 1994'!C1026 -> 92.159763 | F39: =+E39/D39 -> 1.5287261 | I39: 0.1733962 | K39: 59.833815
A40: 16772 | C40: 35643 | D40: 60.297394 | E40: =+'USD PP 1994'!C1027 -> 92.011834 | F40: =+E40/D40 -> 1.525967 | I40: 0.13426994 | K40: 60.292035
A41: 16803 | C41: 35674 | D41: 60.261237 | E41: =+'USD PP 1994'!C1028 -> 91.715976 | F41: =+E41/D41 -> 1.521973 | I41: 0.1028652 | K41: 60.286006
A42: 16834 | C42: 35704 | D42: 60.122955 | E42: =+'USD PP 1994'!C1029 -> 91.568047 | F42: =+E42/D42 -> 1.5230131 | I42: 0.078589041 | K42: 60.153668
A43: 16862 | C43: 35735 | D43: 60.020919 | E43: =+'USD PP 1994'!C1030 -> 91.568047 | F43: =+E43/D43 -> 1.5256022 | I43: 0.058661671 | K43: 59.836534
A44: 16893 | C44: 35765 | D44: 59.763934 | E44: =+'USD PP 1994'!C1031 -> 91.715976 | F44: =+E44/D44 -> 1.5346375 | K44: 59.497399
A45: 16923 | C45: 35796 | D45: 59.342602 | E45: =+'USD PP 1994'!C1032 -> 91.568047 | F45: =+E45/D45 -> 1.5430407 | K45: 59.354947
A46: 16954 | C46: 35827 | D46: 59.070876 | E46: =+'USD PP 1994'!C1033 -> 91.420118 | F46: =+E46/D46 -> 1.5476344 | K46: 59.450067
A47: 16984 | C47: 35855 | D47: 58.870715 | E47: =+'USD PP 1994'!C1034 -> 91.272189 | F47: =+E47/D47 -> 1.5503836 | K47: 59.587118
A48: 17015 | C48: 35886 | D48: 58.729764 | E48: =+'USD PP 1994'!C1035 -> 90.976331 | F48: =+E48/D48 -> 1.5490669 | K48: 59.219954
A49: 17046 | C49: 35916 | D49: 58.437576 | E49: =+'USD PP 1994'!C1036 -> 90.828402 | F49: =+E49/D49 -> 1.5542808 | K49: 58.913603
A50: 17076 | C50: 35947 | D50: 58.425891 | E50: =+'USD PP 1994'!C1037 -> 90.828402 | F50: =+E50/D50 -> 1.5545917 | K50: 58.80188
A51: 17107 | C51: 35977 | D51: 58.496086 | E51: =+'USD PP 1994'!C1038 -> 90.680473 | F51: =+E51/D51 -> 1.5501973 | K51: 59.258168
A52: 17137 | C52: 36008 | D52: 58.795945 | E52: =+'USD PP 1994'!C1039 -> 90.532544 | F52: =+E52/D52 -> 1.5397753 | K52: 59.856735
A53: 17168 | C53: 36039 | D53: 58.925582 | E53: =+'USD PP 1994'!C1040 -> 90.384615 | F53: =+E53/D53 -> 1.5338774 | K53: 60.254414
A54: 17199 | C54: 36069 | D54: 58.913799 | E54: =+'USD PP 1994'!C1041 -> 90.236686 | F54: =+E54/D54 -> 1.5316732 | K54: 60.242366
A55: 17227 | C55: 36100 | D55: 58.98458 | E55: =+'USD PP 1994'!C1042 -> 90.236686 | F55: =+E55/D55 -> 1.5298352 | K55: 60.508604
... A324: 25416 | C324: 44287 | D324: 15.060202 | E324: =+'USD PP 1994'!C1311 -> 55.325444 | F324: =+E324/D324 -> 3.6736189 | K324: 17.583093
A325: 25447 | C325: 44317 | D325: =+'BRL IPCA'!J989 -> 14.936232 | E325: =+'USD PP 1994'!C1312 -> 54.881657 | F325: =+E325/D325 -> 3.6743978 | K325: 17.511297
A326: 25477 | C326: 44348 | D326: =+'BRL IPCA'!J990 -> 14.857487 | E326: =+'USD PP 1994'!C1313 -> 54.43787 | F326: =+E326/D326 -> 3.6640025 | K326: 17.370595
A327: 25508 | C327: 44378 | D327: =+'BRL IPCA'!J991 -> 14.716211 | E327: =+'USD PP 1994'!C1314 -> 54.142012 | F327: =+E327/D327 -> 3.6790727
A328: 25538 | C328: 44409 | D328: =+'BRL IPCA'!J992 -> 14.589285 | E328: =+'USD PP 1994'!C1315 -> 54.142012 | F328: =+E328/D328 -> 3.7110806
A329: 25569 | C329: 44440 | D329: =+'BRL IPCA'!J993 -> 14.42199 | E329: =+'USD PP 1994'!C1316 -> 53.994083 | F329: =+E329/D329 -> 3.743872 | H329: 7.6 | I329: =+H329/F329*100 -> 202.99839
A330: 25600 | C330: 44470 | D330: =+'BRL IPCA'!J994 -> 14.24394 | E330: =+'USD PP 1994'!C1317 -> 53.550296 | F330: =+E330/D330 -> 3.7595142
A331: 25628 | C331: 44501 | D331: =+'BRL IPCA'!J995 -> 14.109896 | E331: =+'USD PP 1994'!C1318 -> 53.254438 | F331: =+E331/D331 -> 3.7742615
A332: 25659 | C332: 44531 | D332: =+'BRL IPCA'!J996 -> 14.007641 | E332: =+'USD PP 1994'!C1319 -> 53.106509 | F332: =+E332/D332 -> 3.791253
A333: 25689 | C333: 44562 | D333: =+'BRL IPCA'!J997 -> 13.932406 | E333: =+'USD PP 1994'!C1320 -> 52.662722 | F333: =+E333/D333 -> 3.7798729
A334: 25720 | C334: 44593 | D334: =+'BRL IPCA'!J998 -> 13.793095 | E334: =+'USD PP 1994'!C1321 -> 52.071006 | F334: =+E334/D334 -> 3.7751502
A335: 25750 | C335: 44621 | D335: =+'BRL IPCA'!J999 -> 13.573209 | E335: =+'USD PP 1994'!C1322 -> 51.47929 | F335: =+E335/D335 -> 3.7927132
A336: 25781 | C336: 44652 | D336: =+'BRL IPCA'!J1000 -> 13.430842 | E336: =+'USD PP 1994'!C1323 -> 51.183432 | F336: =+E336/D336 -> 3.8108877
A337: 25812 | C337: 44682 | D337: =+'BRL IPCA'!J1001 -> 13.368013 | E337: =+'USD PP 1994'!C1324 -> 50.591716 | F337: =+E337/D337 -> 3.7845353
A338: 25842 | C338: 44713 | D338: =+'BRL IPCA'!J1002 -> 13.279043 | E338: =+'USD PP 1994'!C1325 -> 49.852071 | F338: =+E338/D338 -> 3.7541915
A339: 25873 | C339: 44743 | D339: =+'BRL IPCA'!J1003 -> 13.369959 | E339: =+'USD PP 1994'!C1326 -> 50 | F339: =+E339/D339 -> 3.7397273
A340: 25903 | C340: 44774 | D340: =+'BRL IPCA'!J1004 -> 13.418265 | E340: =+'USD PP 1994'!C1327 -> 50 | F340: =+E340/D340 -> 3.7262643
A341: 25934 | C341: 44805 | D341: =+'BRL IPCA'!J1005 -> 13.457291 | E341: =+'USD PP 1994'!C1328 -> 49.852071 | F341: =+E341/D341 -> 3.7044656
... A383: 27211 | C383: 46082 | D383: =+'BRL IPCA'!J1047 -> 11.361349 | E383: =+'USD PP 1994'!C1370 -> 44.822485 | F383: =+E383/D383 -> 3.9451727
A384: 27242 | C384: 46113 | D384: =+'BRL IPCA'!J1048 -> 11.285735 | F384: =+E384/D384 -> 0
A385: 27273 | C385: 46143 | D385: =+'BRL IPCA'!J1049 -> 11.220655 | F385: =+E385/D385 -> 0
A386: 27303 | C386: 46174 | D386: =+'BRL IPCA'!J1050 -> 11.202731 | F386: =+E386/D386 -> 0
A387: 27334 | C387: 46204 | D387: =+'BRL IPCA'!J1051 -> 11.194894 | F387: =+E387/D387 -> 0
A388: 27364 | C388: 46235 | D388: =+'BRL IPCA'!J1052 -> 11.230833 | F388: =+E388/D388 -> 0
A389: 27395
A390: 27426
A391: 27454
A392: 27485
A393: 27515
A394: 27546
A395: 27576
A396: 27607
A397: 27638
A398: 27668
A399: 27699
A400: 27729
... A946: 44348

Sheet BRL e USD Chart 99
A1: Data | C1: Mês | D1: Real (mar/99 a set/24) | E1: Dólar (mar/99 a set/24) | F1: Câmbio pela PPC | G1: Cruzado (fev-86 a jan-89) | H1: Cruzado Novo (jan-89 a mar-90) | I1: Cruzeiro (mar-90 a ago/93) | J1: Cruzeiro real (ago/93 a jun-94) | K1: Real (jul/94 a jun-21)
A2: 15615 | C2: 34486 | D2: 100 | E2: =+'USD PP 1994'!C989 -> 100 | F2: =+E2/D2 -> 1 | G2: 100 | H2: 100 | I2: 100 | J2: 100 | K2: 100
A3: 15646 | C3: 34516 | D3: 93.597903 | E3: =+'USD PP 1994'!C990 -> 99.704142 | F3: =+E3/D3 -> 1.0652391 | G3: 98.202887 | H3: 87.711604 | I3: 83.201597 | J3: 74.560095 | K3: 93.501636 | P3: =5.2/4.9-1 -> 0.06122449
A4: 15676 | C4: 34547 | D4: 91.888772 | E4: =+'USD PP 1994'!C991 -> 99.260355 | F4: =+E4/D4 -> 1.0802229 | G4: 95.985619 | H4: 82.389258 | I4: 76.662303 | J4: 55.135765 | K4: 91.713228
A5: 15707 | C5: 34578 | D5: 90.50406 | E5: =+'USD PP 1994'!C992 -> 98.964497 | F5: =+E5/D5 -> 1.0934813 | G5: 94.177413 | H5: 74.88571 | I5: 68.632321 | J5: 40.588755 | K5: 90.967296
A6: 15738 | C6: 34608 | D6: 88.193393 | E6: =+'USD PP 1994'!C993 -> 98.964497 | F6: =+E6/D6 -> 1.1221305 | G6: 93.281907 | H6: 64.22996 | I6: 61.65872 | J6: 29.301729 | K6: 88.172237
A7: 15766 | C7: 34639 | D7: 85.782894 | E7: =+'USD PP 1994'!C994 -> 98.816568 | F7: =+E7/D7 -> 1.1519379 | G7: 92.294357 | H7: 51.265033 | I7: 55.136117 | J7: 20.885053 | K7: 85.587494
A8: 15797 | C8: 34669 | D8: 84.340668 | E8: =+'USD PP 1994'!C995 -> 98.816568 | F8: =+E8/D8 -> 1.1716361 | G8: 90.591242 | H8: 40.032042 | I8: 48.736955 | J8: 15.113288 | K8: 84.530859
A9: 15827 | C9: 34700 | D9: 82.930844 | E9: =+'USD PP 1994'!C996 -> 98.372781 | F9: =+E9/D9 -> 1.1862026 | G9: 89.314051 | H9: 30.570479 | I9: 42.07628 | J9: 10.64766 | K9: 83.859979
A10: 15858 | C10: 34731 | D10: 82.093491 | E10: =+'USD PP 1994'!C997 -> 98.076923 | F10: =+E10/D10 -> 1.1946979 | G10: 86.645373 | H10: 22.506426 | I10: 35.48944 | J10: 7.2819448 | K10: 82.767448
A11: 15888 | C11: 34759 | D11: 80.840463 | E11: =+'USD PP 1994'!C998 -> 97.633136 | F11: =+E11/D11 -> 1.2077261 | G11: 82.969811 | H11: 16.393347 | I11: 30.586435 | J11: 5.0185698 | K11: 81.20825
A12: 15919 | C12: 34790 | D12: 78.922643 | E12: =+'USD PP 1994'!C999 -> 97.337278 | F12: =+E12/D12 -> 1.2333251 | G12: 75.22195 | H12: 11.467087 | I12: 25.273868 | J12: 3.3290679 | K12: 79.119495
A13: 15950 | C13: 34820 | D13: 76.870209 | E13: =+'USD PP 1994'!C1000 -> 97.189349 | F13: =+E13/D13 -> 1.2643305 | G13: 66.129187 | H13: 7.5530804 | I13: 20.967204 | K13: 77.590954
A14: 15980 | C14: 34851 | D14: 75.171336 | E14: =+'USD PP 1994'!C1001 -> 97.04142 | F14: =+E14/D14 -> 1.2909365 | G14: 59.425941 | H14: 4.3276688 | I14: 19.508005 | K14: 75.580512
A15: 16011 | C15: 34881 | D15: 73.438195 | E15: =+'USD PP 1994'!C1002 -> 97.04142 | F15: =+E15/D15 -> 1.3214026 | G15: 53.073092 | H15: 2.5432939 | I15: 18.199464 | K15: 72.869757
A16: 16041 | C16: 34912 | D16: 72.718284 | E16: =+'USD PP 1994'!C1003 -> 96.745562 | F16: =+E16/D16 -> 1.3304159 | G16: 45.536758 | H16: 1.419962 | I16: 17.208267 | K16: 71.84241
A17: 16072 | C17: 34943 | D17: 72.00543 | E17: =+'USD PP 1994'!C1004 -> 96.597633 | F17: =+E17/D17 -> 1.3415326 | G17: 36.000283 | I17: 15.67523 | K17: 71.314682
A18: 16103 | C18: 34973 | D18: 71.00427 | E18: =+'USD PP 1994'!C1005 -> 96.301775 | F18: =+E18/D18 -> 1.3562815 | G18: 28.40035 | I18: 14.083765 | K18: 70.274617
A19: 16132 | C19: 35004 | D19: 69.975628 | E19: =+'USD PP 1994'!C1006 -> 96.301775 | F19: =+E19/D19 -> 1.3762188 | G19: 25.998123 | I19: 12.308831 | K19: 69.461913
A20: 16163 | C20: 35034 | D20: 68.900776 | E20: =+'USD PP 1994'!C1007 -> 96.301775 | F20: =+E20/D20 -> 1.3976878 | G20: 24.890496 | I20: 10.591886 | K20: 68.631472
A21: 16193 | C21: 35065 | D21: 67.989714 | E21: =+'USD PP 1994'!C1008 -> 95.857988 | F21: =+E21/D21 -> 1.4098896 | G21: 23.320993 | I21: 8.4620008 | K21: 67.404707
A22: 16224 | C22: 35096 | D22: 67.296559 | E22: =+'USD PP 1994'!C1009 -> 95.414201 | F22: =+E22/D22 -> 1.4178169 | G22: 21.168188 | I22: 6.7485452 | K22: 67.136162
A23: 16254 | C23: 35125 | D23: 67.061843 | E23: =+'USD PP 1994'!C1010 -> 94.970414 | F23: =+E23/D23 -> 1.4161617 | G23: 18.666833 | I23: 5.475493 | K23: 66.982103
A24: 16285 | C24: 35156 | D24: 66.227378 | E24: =+'USD PP 1994'!C1011 -> 94.674556 | F24: =+E24/D24 -> 1.429538 | G24: 16.103203 | I24: 4.3494265 | K24: 65.914292
A25: 16316 | C25: 35186 | D25: 65.429142 | E25: =+'USD PP 1994'!C1012 -> 94.526627 | F25: =+E25/D25 -> 1.4447175 | G25: 14.03941 | I25: 3.5777137 | K25: 65.042719
A26: 16346 | C26: 35217 | D26: 64.659692 | E26: =+'USD PP 1994'!C1013 -> 94.378698 | F26: =+E26/D26 -> 1.4596218 | G26: 12.382616 | I26: 2.9388152 | K26: 64.138368
A27: 16377 | C27: 35247 | D27: 63.949849 | E27: =+'USD PP 1994'!C1014 -> 94.230769 | F27: =+E27/D27 -> 1.4735104 | G27: 10.436254 | I27: 2.394537 | K27: 63.30902
A28: 16407 | C28: 35278 | D28: 63.669702 | E28: =+'USD PP 1994'!C1015 -> 94.08284 | F28: =+E28/D28 -> 1.4776705 | G28: 8.6129027 | I28: 1.9542455 | K28: 63.094499
... A36: 16650 | C36: 35521 | D36: 60.993271 | E36: =+'USD PP 1994'!C1023 -> 92.307692 | F36: =+E36/D36 -> 1.5134078 | G36: 1.6238485 | I36: 0.34952315 | K36: 61.084333
A37: 16681 | C37: 35551 | D37: 60.744219 | E37: =+'USD PP 1994'!C1024 -> 92.455621 | F37: =+E37/D37 -> 1.5220481 | G37: =+USDBRL!D534/'BRL e USD Chart 99'!F37*100 -> 70.162042 | I37: 0.27939501 | K37: 60.750207
A38: 16711 | C38: 35582 | D38: 60.417962 | E38: =+'USD PP 1994'!C1025 -> 92.307692 | F38: =+E38/D38 -> 1.5278187 | G38: =+USDBRL!D535/'BRL e USD Chart 99'!F38*100 -> 70.30939 | I38: 0.22323027 | K38: 59.899632
A39: 16742 | C39: 35612 | D39: 60.285335 | E39: =+'USD PP 1994'!C1026 -> 92.159763 | F39: =+E39/D39 -> 1.5287261 | G39: =+USDBRL!D536/'BRL e USD Chart 99'!F39*100 -> 70.666682 | I39: 0.1733962 | K39: 59.833815
A40: 16772 | C40: 35643 | D40: 60.297394 | E40: =+'USD PP 1994'!C1027 -> 92.011834 | F40: =+E40/D40 -> 1.525967 | G40: =+USDBRL!D537/'BRL e USD Chart 99'!F40*100 -> 71.266285 | I40: 0.13426994 | K40: 60.292035
A41: 16803 | C41: 35674 | D41: 60.261237 | E41: =+'USD PP 1994'!C1028 -> 91.715976 | F41: =+E41/D41 -> 1.521973 | G41: =+USDBRL!D538/'BRL e USD Chart 99'!F41*100 -> 71.827818 | I41: 0.1028652 | K41: 60.286006
A42: 16834 | C42: 35704 | D42: 60.122955 | E42: =+'USD PP 1994'!C1029 -> 91.568047 | F42: =+E42/D42 -> 1.5230131 | G42: =+USDBRL!D539/'BRL e USD Chart 99'!F42*100 -> 72.205551 | I42: 0.078589041 | K42: 60.153668
A43: 16862 | C43: 35735 | D43: 60.020919 | E43: =+'USD PP 1994'!C1030 -> 91.568047 | F43: =+E43/D43 -> 1.5256022 | G43: =+USDBRL!D540/'BRL e USD Chart 99'!F43*100 -> 72.554955 | I43: 0.058661671 | K43: 59.836534
A44: 16893 | C44: 35765 | D44: 59.763934 | E44: =+'USD PP 1994'!C1031 -> 91.715976 | F44: =+E44/D44 -> 1.5346375 | G44: =+USDBRL!D541/'BRL e USD Chart 99'!F44*100 -> 72.538301 | K44: 59.497399
A45: 16923 | C45: 35796 | D45: 59.342602 | E45: =+'USD PP 1994'!C1032 -> 91.568047 | F45: =+E45/D45 -> 1.5430407 | G45: =+USDBRL!D542/'BRL e USD Chart 99'!F45*100 -> 72.551555 | K45: 59.354947
A46: 16954 | C46: 35827 | D46: 59.070876 | E46: =+'USD PP 1994'!C1033 -> 91.420118 | F46: =+E46/D46 -> 1.5476344 | G46: =+USDBRL!D543/'BRL e USD Chart 99'!F46*100 -> 72.801432 | K46: 59.450067
A47: 16984 | C47: 35855 | D47: 58.870715 | E47: =+'USD PP 1994'!C1034 -> 91.272189 | F47: =+E47/D47 -> 1.5503836 | G47: =+USDBRL!D544/'BRL e USD Chart 99'!F47*100 -> 73.09804 | K47: 59.587118
A48: 17015 | C48: 35886 | D48: 58.729764 | E48: =+'USD PP 1994'!C1035 -> 90.976331 | F48: =+E48/D48 -> 1.5490669 | G48: =+USDBRL!D545/'BRL e USD Chart 99'!F48*100 -> 73.644335 | K48: 59.219954
A49: 17046 | C49: 35916 | D49: 58.437576 | E49: =+'USD PP 1994'!C1036 -> 90.828402 | F49: =+E49/D49 -> 1.5542808 | G49: =+USDBRL!D546/'BRL e USD Chart 99'!F49*100 -> 73.841226 | K49: 58.913603
A50: 17076 | C50: 35947 | D50: 58.425891 | E50: =+'USD PP 1994'!C1037 -> 90.828402 | F50: =+E50/D50 -> 1.5545917 | G50: =+USDBRL!D547/'BRL e USD Chart 99'!F50*100 -> 74.244577 | K50: 58.80188
A51: 17107 | C51: 35977 | D51: 58.496086 | E51: =+'USD PP 1994'!C1038 -> 90.680473 | F51: =+E51/D51 -> 1.5501973 | G51: =+USDBRL!D548/'BRL e USD Chart 99'!F51*100 -> 74.900144 | K51: 59.258168
A52: 17137 | C52: 36008 | D52: 58.795945 | E52: =+'USD PP 1994'!C1039 -> 90.532544 | F52: =+E52/D52 -> 1.5397753 | G52: =+USDBRL!D549/'BRL e USD Chart 99'!F52*100 -> 76.069541 | K52: 59.856735
A53: 17168 | C53: 36039 | D53: 58.925582 | E53: =+'USD PP 1994'!C1040 -> 90.384615 | F53: =+E53/D53 -> 1.5338774 | G53: =+USDBRL!D550/'BRL e USD Chart 99'!F53*100 -> 76.961824 | K53: 60.254414
A54: 17199 | C54: 36069 | D54: 58.913799 | E54: =+'USD PP 1994'!C1041 -> 90.236686 | F54: =+E54/D54 -> 1.5316732 | G54: =+USDBRL!D551/'BRL e USD Chart 99'!F54*100 -> 77.562237 | K54: 60.242366
A55: 17227 | C55: 36100 | D55: 58.98458 | E55: =+'USD PP 1994'!C1042 -> 90.236686 | F55: =+E55/D55 -> 1.5298352 | G55: =+USDBRL!D552/'BRL e USD Chart 99'!F55*100 -> 78.001866 | K55: 60.508604
... A57: 17288 | C57: 36161 | D57: 58.381898 | E57: =+'USD PP 1994'!C1044 -> 89.940828 | F57: =+E57/D57 -> 1.5405602 | G57: =+USDBRL!D554/'BRL e USD Chart 99'!F57*100 -> 97.464546 | K57: 60.279902
A58: 17319 | C58: 36192 | D58: 57.775258 | E58: =+'USD PP 1999'!C1045 -> 89.940828 | F58: =+E58/D58 -> 1.5567361 | G58: =+USDBRL!D555/'BRL e USD Chart 99'!F58*100 -> 122.90458 | K58: 59.441773
A59: 17349 | C59: 36220 | D59: =+E59/F59 -> 52.749477 | E59: =+'USD PP 1999'!C1046 -> 100 | F59: =+'STP-20220201164925715'!D136 -> 1.8957534 | G59: =+USDBRL!D556/'BRL e USD Chart 99'!F59*100 -> 100.03411 | K59: 59.110752
A60: 17380 | C60: 36251 | D60: =+D59/(1+('BRL IPCA'!AA724)/100) -> 52.455724 | E60: =+'USD PP 1999'!C1047 -> 99.339934 | F60: =+E60/D60 -> 1.8937863 | G60: =+USDBRL!D557/'BRL e USD Chart 99'!F60*100 -> 89.434588 | K60: 58.834232
A61: 17411 | C61: 36281 | D61: =+D60/(1+('BRL IPCA'!AA725)/100) -> 52.298828 | E61: =+'USD PP 1999'!C1048 -> 99.339934 | F61: =+E61/D61 -> 1.8994677 | G61: =+USDBRL!D558/'BRL e USD Chart 99'!F61*100 -> 88.609036 | K61: 59.052727
A62: 17441 | C62: 36312 | D62: =+D61/(1+('BRL IPCA'!AA726)/100) -> 52.199649 | E62: =+'USD PP 1999'!C1049 -> 99.339934 | F62: =+E62/D62 -> 1.9030767 | G62: =+USDBRL!D559/'BRL e USD Chart 99'!F62*100 -> 92.744555 | K62: 59.100007
A63: 17472 | C63: 36342 | D63: =+D62/(1+('BRL IPCA'!AA727)/100) -> 51.636807 | E63: =+'USD PP 1999'!C1050 -> 99.009901 | F63: =+E63/D63 -> 1.9174288 | G63: =+USDBRL!D560/'BRL e USD Chart 99'!F63*100 -> 93.870501 | K63: 58.462762
A64: 17502 | C64: 36373 | D64: =+D63/(1+('BRL IPCA'!AA728)/100) -> 51.349252 | E64: =+'USD PP 1999'!C1051 -> 98.679868 | F64: =+E64/D64 -> 1.9217392 | G64: =+USDBRL!D561/'BRL e USD Chart 99'!F64*100 -> 97.846265 | K64: 58.033316
A65: 17533 | C65: 36404 | D65: =+D64/(1+('BRL IPCA'!AA729)/100) -> 51.190561 | E65: =+'USD PP 1999'!C1052 -> 98.349835 | F65: =+E65/D65 -> 1.9212494 | G65: =+USDBRL!D562/'BRL e USD Chart 99'!F65*100 -> 98.774266 | K65: 57.509975
A66: 17564 | C66: 36434 | D66: =+D65/(1+('BRL IPCA'!AA730)/100) -> 50.588557 | E66: =+'USD PP 1999'!C1053 -> 98.019802 | F66: =+E66/D66 -> 1.9375884 | G66: =+USDBRL!D563/'BRL e USD Chart 99'!F66*100 -> 101.62633 | K66: 56.867374
A67: 17593 | C67: 36465 | D67: =+D66/(1+('BRL IPCA'!AA731)/100) -> 50.112488 | E67: =+'USD PP 1999'!C1054 -> 98.019802 | F67: =+E67/D67 -> 1.9559955 | G67: =+USDBRL!D564/'BRL e USD Chart 99'!F67*100 -> 98.645421 | K67: 56.038011
A68: 17624 | C68: 36495 | D68: =+D67/(1+('BRL IPCA'!AA732)/100) -> 49.813607 | E68: =+'USD PP 1999'!C1055 -> 98.019802 | F68: =+E68/D68 -> 1.9677315 | G68: =+USDBRL!D565/'BRL e USD Chart 99'!F68*100 -> 93.630662 | K68: 55.764764
A69: 17654 | C69: 36526 | D69: =+D68/(1+('BRL IPCA'!AA733)/100) -> 49.506665 | E69: =+'USD PP 1999'!C1056 -> 97.689769 | F69: =+E69/D69 -> 1.973265 | G69: =+USDBRL!D566/'BRL e USD Chart 99'!F69*100 -> 91.386612 | K69: 55.448706
A70: 17685 | C70: 36557 | D70: =+D69/(1+('BRL IPCA'!AA734)/100) -> 49.44239 | E70: =+'USD PP 1999'!C1057 -> 97.194719 | F70: =+E70/D70 -> 1.9658176 | G70: =+USDBRL!D567/'BRL e USD Chart 99'!F70*100 -> 90.288134 | K70: 55.576532
A71: 17715 | C71: 36586 | D71: =+D70/(1+('BRL IPCA'!AA735)/100) -> 49.333856 | E71: =+'USD PP 1999'!C1058 -> 96.369637 | F71: =+E71/D71 -> 1.9534179 | G71: =+USDBRL!D568/'BRL e USD Chart 99'!F71*100 -> 89.15655 | K71: 55.449
... A326: 25477 | C326: 44348 | D326: =+D325/(1+('BRL IPCA'!AA990)/100) -> 13.714273 | E326: =+'USD PP 1999'!C1313 -> 60.726073 | F326: =+E326/D326 -> 4.427947 | G326: =+USDBRL!D823/'BRL e USD Chart 99'!F326*100 -> 113.6328 | K326: 17.370595
A327: 25508 | C327: 44378 | D327: =+D326/(1+('BRL IPCA'!AA991)/100) -> 13.583867 | E327: =+'USD PP 1999'!C1314 -> 60.39604 | F327: =+E327/D327 -> 4.4461594 | G327: =+USDBRL!D824/'BRL e USD Chart 99'!F327*100 -> 115.97313
A328: 25538 | C328: 44409 | D328: =+D327/(1+('BRL IPCA'!AA992)/100) -> 13.466707 | E328: =+'USD PP 1999'!C1315 -> 60.39604 | F328: =+E328/D328 -> 4.484841 | G328: =+USDBRL!D825/'BRL e USD Chart 99'!F328*100 -> 117.09222 | I328: 37530 | J328: 40695 | S328: 4.93
A329: 25569 | C329: 44440 | D329: =+D328/(1+('BRL IPCA'!AA993)/100) -> 13.312285 | E329: =+'USD PP 1999'!C1316 -> 60.231023 | F329: =+E329/D329 -> 4.5244693 | G329: =+USDBRL!D826/'BRL e USD Chart 99'!F329*100 -> 116.68551 | I329: =+G102 -> 170.47564 | J329: =+G207 -> 50.902808 | S329: =+F334/S328-1 -> -0.074590472
A330: 25600 | C330: 44470 | D330: =+D329/(1+('BRL IPCA'!AA994)/100) -> 13.147935 | E330: =+'USD PP 1999'!C1317 -> 59.735974 | F330: =+E330/D330 -> 4.5433729 | G330: =+USDBRL!D827/'BRL e USD Chart 99'!F330*100 -> 121.92924 | H330: USDBRL | I330: =+F356*I329/100 -> 7.8497837 | J330: =+F356*J329/100 -> 2.3438893
A331: 25628 | C331: 44501 | D331: =+D330/(1+('BRL IPCA'!AA995)/100) -> 13.024205 | E331: =+'USD PP 1999'!C1318 -> 59.405941 | F331: =+E331/D331 -> 4.561195 | G331: =+USDBRL!D828/'BRL e USD Chart 99'!F331*100 -> 121.82334 | N331: 5.15
A332: 25659 | C332: 44531 | D332: =+D331/(1+('BRL IPCA'!AA996)/100) -> 12.929818 | E332: =+'USD PP 1999'!C1319 -> 59.240924 | F332: =+E332/D332 -> 4.5817292 | G332: =+USDBRL!D829/'BRL e USD Chart 99'!F332*100 -> 123.33771 | N332: =+F334/N331-1 -> -0.11412253
A333: 25689 | C333: 44562 | D333: =+D332/(1+('BRL IPCA'!AA997)/100) -> 12.860372 | E333: =+'USD PP 1999'!C1320 -> 58.745875 | F333: =+E333/D333 -> 4.5679764 | G333: =+USDBRL!D830/'BRL e USD Chart 99'!F333*100 -> 121.14336
A334: 25720 | C334: 44593 | D334: =+D333/(1+('BRL IPCA'!AA998)/100) -> 12.731781 | E334: =+'USD PP 1999'!C1321 -> 58.085809 | F334: =+E334/D334 -> 4.562269 | G334: =+USDBRL!D831/'BRL e USD Chart 99'!F334*100 -> 113.89727 | H334: 11
A335: 25750 | C335: 44621 | D335: =+D334/(1+('BRL IPCA'!AA999)/100) -> 12.528814 | E335: =+'USD PP 1999'!C1322 -> 57.425743 | F335: =+E335/D335 -> 4.5834939 | G335: =+USDBRL!D832/'BRL e USD Chart 99'!F335*100 -> 108.39111
A336: 25781 | C336: 44652 | D336: =+D335/(1+('BRL IPCA'!AA1000)/100) -> 12.397402 | E336: =+'USD PP 1999'!C1323 -> 57.09571 | F336: =+E336/D336 -> 4.6054578 | G336: =+USDBRL!D833/'BRL e USD Chart 99'!F336*100 -> 103.30569
A337: 25812 | C337: 44682 | D337: =+D336/(1+('BRL IPCA'!AA1001)/100) -> 12.339406 | E337: =+'USD PP 1999'!C1324 -> 56.435644 | F337: =+E337/D337 -> 4.5736109 | G337: =+USDBRL!D834/'BRL e USD Chart 99'!F337*100 -> 108.33453
A338: 25842 | C338: 44713 | D338: =+D337/(1+('BRL IPCA'!AA1002)/100) -> 12.257283 | E338: =+'USD PP 1999'!C1325 -> 55.610561 | F338: =+E338/D338 -> 4.5369404 | G338: =+USDBRL!D835/'BRL e USD Chart 99'!F338*100 -> 111.28425
A339: 25873 | C339: 44743 | D339: =+D338/(1+('BRL IPCA'!AA1003)/100) -> 12.341203 | E339: =+'USD PP 1999'!C1326 -> 55.775578 | F339: =+E339/D339 -> 4.5194604 | G339: =+USDBRL!D836/'BRL e USD Chart 99'!F339*100 -> 118.77082
A340: 25903 | C340: 44774 | D340: =+D339/(1+('BRL IPCA'!AA1004)/100) -> 12.385792 | E340: =+'USD PP 1999'!C1327 -> 55.775578 | F340: =+E340/D340 -> 4.5031904 | G340: =+USDBRL!D837/'BRL e USD Chart 99'!F340*100 -> 114.20792
A341: 25934 | C341: 44805 | D341: =+D340/(1+('BRL IPCA'!AA1005)/100) -> 12.421815 | E341: =+'USD PP 1999'!C1328 -> 55.610561 | F341: =+E341/D341 -> 4.4768467 | G341: =+USDBRL!D838/'BRL e USD Chart 99'!F341*100 -> 116.97296
A342: 25965 | C342: 44835 | D342: =+D341/(1+('BRL IPCA'!AA1006)/100) -> 12.348956 | E342: =+'USD PP 1999'!C1329 -> 55.445545 | F342: =+E342/D342 -> 4.4898973 | G342: =+USDBRL!D839/'BRL e USD Chart 99'!F342*100 -> 116.92918
A343: 25993 | C343: 44866 | D343: =+D342/(1+('BRL IPCA'!AA1007)/100) -> 12.298532 | E343: =+'USD PP 1999'!C1330 -> 55.445545 | F343: =+E343/D343 -> 4.5083059 | G343: =+USDBRL!D840/'BRL e USD Chart 99'!F343*100 -> 116.99295
A344: 26024 | C344: 44896 | D344: =+D343/(1+('BRL IPCA'!AA1008)/100) -> 12.222751 | E344: =+'USD PP 1999'!C1331 -> 55.610561 | F344: =+E344/D344 -> 4.5497582 | G344: =+USDBRL!D841/'BRL e USD Chart 99'!F344*100 -> 115.21711
A345: 26054 | C345: 44927 | D345: =+D344/(1+('BRL IPCA'!AA1009)/100) -> 12.158312 | E345: =+'USD PP 1999'!C1332 -> 55.115512 | F345: =+E345/D345 -> 4.5331549 | G345: =+USDBRL!D842/'BRL e USD Chart 99'!F345*100 -> 114.71922
A346: 26085 | C346: 44958 | D346: =+D345/(1+('BRL IPCA'!AA1010)/100) -> 12.057033 | E346: =+'USD PP 1999'!C1333 -> 54.785479 | F346: =+E346/D346 -> 4.5438608 | G346: =+USDBRL!D843/'BRL e USD Chart 99'!F346*100 -> 113.81071
... A359: 26481 | C359: 45352 | D359: =+D358/(1+('BRL IPCA'!AA1023)/100) -> 11.51981 | E359: =+'USD PP 1999'!C1346 -> 52.805281 | F359: =+E359/D359 -> 4.5838672 | G359: =+USDBRL!D856/'BRL e USD Chart 99'!F359*100 -> 108.63753
A360: 26512 | C360: 45383 | D360: =+D359/(1+('BRL IPCA'!AA1024)/100) -> 11.476201 | E360: =+'USD PP 1999'!C1347 -> 52.640264 | F360: =+E360/D360 -> 4.5869069
A361: 26543 | C361: 45413 | D361: =+D360/(1+('BRL IPCA'!AA1025)/100) -> 11.423652 | E361: =+'USD PP 1999'!C1348 -> 52.475248 | F361: =+E361/D361 -> 4.5935615
A362: 26573 | C362: 45444 | D362: =+D361/(1+('BRL IPCA'!AA1026)/100) -> 11.399712 | E362: =+'USD PP 1999'!C1349 -> 52.475248 | F362: =+E362/D362 -> 4.603208
A363: 26604 | C363: 45474 | D363: =+D362/(1+('BRL IPCA'!AA1027)/100) -> 11.356558 | E363: =+'USD PP 1999'!C1350 -> 52.475248 | F363: =+E363/D363 -> 4.6207002
A364: 26634 | C364: 45505 | D364: =+D363/(1+('BRL IPCA'!AA1028)/100) -> 11.358829 | E364: =+'USD PP 1999'!C1351 -> 52.475248 | F364: =+E364/D364 -> 4.619776
A365: 26665 | C365: 45536 | D365: =+D364/(1+('BRL IPCA'!AA1029)/100) -> 11.309069 | E365: =+'USD PP 1999'!C1352 -> 52.310231 | F365: =+E365/D365 -> 4.6255115
A366: 26696 | C366: 45566 | D366: =+D365/(1+('BRL IPCA'!AA1030)/100) -> 11.246091 | E366: =+'USD PP 1999'!C1353 -> 52.310231 | F366: =+E366/D366 -> 4.6514144
A367: 26724 | C367: 45597 | D367: =+D366/(1+('BRL IPCA'!AA1031)/100) -> 11.202402 | E367: =+'USD PP 1999'!C1354 -> 52.310231 | F367: =+E367/D367 -> 4.6695549
A368: 26755 | C368: 45627 | D368: =+D367/(1+('BRL IPCA'!AA1032)/100) -> 11.144451 | E368: =+'USD PP 1999'!C1355 -> 52.310231 | F368: =+E368/D368 -> 4.6938366
A369: 26785 | C369: 45658 | D369: =+D368/(1+('BRL IPCA'!AA1033)/100) -> 11.126648 | E369: =+'USD PP 1999'!C1356 -> 51.980198 | F369: =+E369/D369 -> 4.6716853
A370: 26816 | C370: 45689 | D370: =+D369/(1+('BRL IPCA'!AA1034)/100) -> 10.982774 | E370: =+'USD PP 1999'!C1357 -> 51.650165 | F370: =+E370/D370 -> 4.7028343
A371: 26846 | C371: 45717 | D371: =+D370/(1+('BRL IPCA'!AA1035)/100) -> 10.921613 | E371: =+'USD PP 1999'!C1358 -> 51.650165 | F371: =+E371/D371 -> 4.7291701
... A389: 27395 | C389: 46266 | D389: =+D388/(1+('BRL IPCA'!AA1053)/100) -> 10.037648 | E389: =+'USD PP 1999'!C1376 -> 0 | F389: =+E389/D389 -> 0
A390: 27426
A391: 27454
...

Sheet IPCA Chart
A1: Data | B1: IPCA Anual | C1: IPCA Anual | D1: 1
A2: 34516 | D2: =+D1*(1+B2) -> 1
A3: 34547 | D3: =+D2*(1+B3) -> 1
A4: 34578 | D4: =+D3*(1+B4) -> 1
A5: 34608 | D5: =+D4*(1+B5) -> 1
A6: 34639 | D6: =+D5*(1+B6) -> 1
A7: 34669 | D7: =+D6*(1+B7) -> 1
A8: 34700 | D8: =+D7*(1+B8) -> 1
A9: 34731 | D9: =+D8*(1+B9) -> 1
A10: 34759 | D10: =+D9*(1+B10) -> 1
A11: 34790 | D11: =+D10*(1+B11) -> 1
A12: 34820 | D12: =+D11*(1+B12) -> 1
A13: 34851 | B13: 0.3302943 | C13: 0.3302943 | D13: =+D12*(1+B13) -> 1.3302943
A14: 34881 | B14: 0.27451258 | C14: 0.27451258 | D14: =+D13*(1+B14) -> 1.6954768
A15: 34912 | B15: 0.2636268 | C15: 0.2636268 | D15: =+D14*(1+B15) -> 2.1424499
A16: 34943 | B16: 0.25690604 | C16: 0.25690604 | D16: =+D15*(1+B16) -> 2.6928583
A17: 34973 | B17: 0.24208577 | C17: 0.24208577 | D17: =+D16*(1+B17) -> 3.3447609
A18: 35004 | B18: 0.22589673 | C18: 0.22589673 | D18: =+D17*(1+B18) -> 4.1003315
A19: 35034 | B19: 0.2240888 | C19: 0.2240888 | D19: =+D18*(1+B19) -> 5.0191699
A20: 35065 | B20: 0.21975574 | C20: 0.21975574 | D20: =+D19*(1+B20) -> 6.1221613
A21: 35096 | B21: 0.21987649 | C21: 0.21987649 | D21: =+D20*(1+B21) -> 7.4682806
A22: 35125 | B22: 0.2054614 | C22: 0.2054614 | D22: =+D21*(1+B22) -> 9.002724
A23: 35156 | B23: 0.1916921 | C23: 0.1916921 | D23: =+D22*(1+B23) -> 10.728475
A24: 35186 | B24: 0.17486193 | C24: 0.17486193 | D24: =+D23*(1+B24) -> 12.604477
... A358: 45352 | B358: 0.039255961 | C358: 0.039255961 | D358: =+D357*(1+B358) -> 9.1097917e+09

Sheet BRL e USD
A1: Data | C1: Mês | D1: Real (jul/94 a mai-21) | E1: Dólar (jul/94 a mai-21) | F1: Cruzeiro (mai-70 a fev-86) | G1: Cruzado (fev-86 a jan-89) | H1: Cruzado Novo (jan-89 a mar-90) | I1: Cruzeiro (mar-90 a ago/93) | J1: Cruzeiro real (ago/93 a jun-94) | K1: Real (jul/94 a jun-21)
A2: 15615 | C2: 0 | D2: 100 | E2: =+'USD PP 1994'!C989 -> 100 | F2: 100 | G2: 100 | H2: 100 | I2: 100 | J2: 100 | K2: 100
A3: 15646 | C3: 1 | D3: 93.501636 | E3: =+'USD PP 1994'!C990 -> 99.704142 | F3: 98.512462 | G3: 98.202887 | H3: 87.711604 | I3: 83.201597 | J3: 74.560095 | K3: 93.501636
A4: 15676 | C4: 2 | D4: 91.713228 | E4: =+'USD PP 1994'!C991 -> 99.260355 | F4: 97.740313 | G4: 95.985619 | H4: 82.389258 | I4: 76.662303 | J4: 55.135765 | K4: 91.713228
A5: 15707 | C5: 3 | D5: 90.967296 | E5: =+'USD PP 1994'!C992 -> 98.964497 | F5: 96.220037 | G5: 94.177413 | H5: 74.88571 | I5: 68.632321 | J5: 40.588755 | K5: 90.967296
A6: 15738 | C6: 4 | D6: 88.172237 | E6: =+'USD PP 1994'!C993 -> 98.964497 | F6: 93.946531 | G6: 93.281907 | H6: 64.22996 | I6: 61.65872 | J6: 29.301729 | K6: 88.172237
A7: 15766 | C7: 5 | D7: 85.587494 | E7: =+'USD PP 1994'!C994 -> 98.816568 | F7: 92.878429 | G7: 92.294357 | H7: 51.265033 | I7: 55.136117 | J7: 20.885053 | K7: 85.587494
A8: 15797 | C8: 6 | D8: 84.530859 | E8: =+'USD PP 1994'!C995 -> 98.816568 | F8: 91.995274 | G8: 90.591242 | H8: 40.032042 | I8: 48.736955 | J8: 15.113288 | K8: 84.530859
A9: 15827 | C9: 7 | D9: 83.859979 | E9: =+'USD PP 1994'!C996 -> 98.372781 | F9: 90.617882 | G9: 89.314051 | H9: 30.570479 | I9: 42.07628 | J9: 10.64766 | K9: 83.859979
A10: 15858 | C10: 8 | D10: 82.767448 | E10: =+'USD PP 1994'!C997 -> 98.076923 | F10: 88.684559 | G10: 86.645373 | H10: 22.506426 | I10: 35.48944 | J10: 7.2819448 | K10: 82.767448
A11: 15888 | C11: 9 | D11: 81.20825 | E11: =+'USD PP 1994'!C998 -> 97.633136 | F11: 87.073696 | G11: 82.969811 | H11: 16.393347 | I11: 30.586435 | J11: 5.0185698 | K11: 81.20825
A12: 15919 | C12: 10 | D12: 79.119495 | E12: =+'USD PP 1994'!C999 -> 97.337278 | F12: 84.619724 | G12: 75.22195 | H12: 11.467087 | I12: 25.273868 | J12: 3.3290679 | K12: 79.119495
A13: 15950 | C13: 11 | D13: 77.590954 | E13: =+'USD PP 1994'!C1000 -> 97.189349 | F13: 83.509053 | G13: 66.129187 | H13: 7.5530804 | I13: 20.967204 | K13: 77.590954
A14: 15980 | C14: 12 | D14: 75.580512 | E14: =+'USD PP 1994'!C1001 -> 97.04142 | F14: 82.080846 | G14: 59.425941 | H14: 4.3276688 | I14: 19.508005 | K14: 75.580512
A15: 16011 | C15: 13 | D15: 72.869757 | E15: =+'USD PP 1994'!C1002 -> 97.04142 | F15: 80.46353 | G15: 53.073092 | H15: 2.5432939 | I15: 18.199464 | K15: 72.869757
A16: 16041 | C16: 14 | D16: 71.84241 | E16: =+'USD PP 1994'!C1003 -> 96.745562 | F16: 79.407411 | G16: 45.536758 | H16: 1.419962 | I16: 17.208267 | K16: 71.84241
A17: 16072 | C17: 15 | D17: 71.314682 | E17: =+'USD PP 1994'!C1004 -> 96.597633 | F17: 78.303334 | G17: 36.000283 | I17: 15.67523 | K17: 71.314682
A18: 16103 | C18: 16 | D18: 70.274617 | E18: =+'USD PP 1994'!C1005 -> 96.301775 | F18: 77.705005 | G18: 28.40035 | I18: 14.083765 | K18: 70.274617
A19: 16132 | C19: 17 | D19: 69.461913 | E19: =+'USD PP 1994'!C1006 -> 96.301775 | F19: 76.79119 | G19: 25.998123 | I19: 12.308831 | K19: 69.461913
A20: 16163 | C20: 18 | D20: 68.631472 | E20: =+'USD PP 1994'!C1007 -> 96.301775 | F20: 75.8132 | G20: 24.890496 | I20: 10.591886 | K20: 68.631472
A21: 16193 | C21: 19 | D21: 67.404707 | E21: =+'USD PP 1994'!C1008 -> 95.857988 | F21: 75.136967 | G21: 23.320993 | I21: 8.4620008 | K21: 67.404707
A22: 16224 | C22: 20 | D22: 67.136162 | E22: =+'USD PP 1994'!C1009 -> 95.414201 | F22: 73.490774 | G22: 21.168188 | I22: 6.7485452 | K22: 67.136162
A23: 16254 | C23: 21 | D23: 66.982103 | E23: =+'USD PP 1994'!C1010 -> 94.970414 | F23: 72.468962 | G23: 18.666833 | I23: 5.475493 | K23: 66.982103
A24: 16285 | C24: 22 | D24: 65.914292 | E24: =+'USD PP 1994'!C1011 -> 94.674556 | F24: 71.751447 | G24: 16.103203 | I24: 4.3494265 | K24: 65.914292
A25: 16316 | C25: 23 | D25: 65.042719 | E25: =+'USD PP 1994'!C1012 -> 94.526627 | F25: 70.88663 | G25: 14.03941 | I25: 3.5777137 | K25: 65.042719
A26: 16346 | C26: 24 | D26: 64.138368 | E26: =+'USD PP 1994'!C1013 -> 94.378698 | F26: 70.421846 | G26: 12.382616 | I26: 2.9388152 | K26: 64.138368
A27: 16377 | C27: 25 | D27: 63.30902 | E27: =+'USD PP 1994'!C1014 -> 94.230769 | F27: 69.641857 | G27: 10.436254 | I27: 2.394537 | K27: 63.30902
A28: 16407 | C28: 26 | D28: 63.094499 | E28: =+'USD PP 1994'!C1015 -> 94.08284 | F28: 68.0628 | G28: 8.6129027 | I28: 1.9542455 | K28: 63.094499
... A37: 16681 | C37: 35 | D37: 60.750207 | E37: =+'USD PP 1994'!C1024 -> 92.455621 | F37: 60.509572 | G37: 1.238539 | I37: 0.27939501 | K37: 60.750207
A38: 16711 | C38: 36 | D38: 59.899632 | E38: =+'USD PP 1994'!C1025 -> 92.307692 | F38: 60.023382 | I38: 0.22323027 | K38: 59.899632
A39: 16742 | C39: 37 | D39: 59.833815 | E39: =+'USD PP 1994'!C1026 -> 92.159763 | F39: 59.558824 | I39: 0.1733962 | K39: 59.833815
A40: 16772 | C40: 38 | D40: 60.292035 | E40: =+'USD PP 1994'!C1027 -> 92.011834 | F40: 58.922461 | I40: 0.13426994 | K40: 60.292035
A41: 16803 | C41: 39 | D41: 60.286006 | E41: =+'USD PP 1994'!C1028 -> 91.715976 | F41: 58.298665 | I41: 0.1028652 | K41: 60.286006
A42: 16834 | C42: 40 | D42: 60.153668 | E42: =+'USD PP 1994'!C1029 -> 91.568047 | F42: 57.584616 | I42: 0.078589041 | K42: 60.153668
A43: 16862 | C43: 41 | D43: 59.836534 | E43: =+'USD PP 1994'!C1030 -> 91.568047 | F43: 56.946812 | I43: 0.058661671 | K43: 59.836534
A44: 16893 | C44: 42 | D44: 59.497399 | E44: =+'USD PP 1994'!C1031 -> 91.715976 | F44: 56.422086 | K44: 59.497399
A45: 16923 | C45: 43 | D45: 59.354947 | E45: =+'USD PP 1994'!C1032 -> 91.568047 | F45: 56.130209 | K45: 59.354947
A46: 16954 | C46: 44 | D46: 59.450067 | E46: =+'USD PP 1994'!C1033 -> 91.420118 | F46: 55.607499 | K46: 59.450067
A47: 16984 | C47: 45 | D47: 59.587118 | E47: =+'USD PP 1994'!C1034 -> 91.272189 | F47: 53.695924 | K47: 59.587118
A48: 17015 | C48: 46 | D48: 59.219954 | E48: =+'USD PP 1994'!C1035 -> 90.976331 | F48: 51.551386 | K48: 59.219954
A49: 17046 | C49: 47 | D49: 58.913603 | E49: =+'USD PP 1994'!C1036 -> 90.828402 | F49: 49.040512 | K49: 58.913603
A50: 17076 | C50: 48 | D50: 58.80188 | E50: =+'USD PP 1994'!C1037 -> 90.828402 | F50: 48.145015 | K50: 58.80188
A51: 17107 | C51: 49 | D51: 59.258168 | E51: =+'USD PP 1994'!C1038 -> 90.680473 | F51: 47.536547 | K51: 59.258168
A52: 17137 | C52: 50 | D52: 59.856735 | E52: =+'USD PP 1994'!C1039 -> 90.532544 | F52: 46.504155 | K52: 59.856735
A53: 17168 | C53: 51 | D53: 60.254414 | E53: =+'USD PP 1994'!C1040 -> 90.384615 | F53: 45.614669 | K53: 60.254414
A54: 17199 | C54: 52 | D54: 60.242366 | E54: =+'USD PP 1994'!C1041 -> 90.236686 | F54: 44.891909 | K54: 60.242366
A55: 17227 | C55: 53 | D55: 60.508604 | E55: =+'USD PP 1994'!C1042 -> 90.236686 | F55: 44.150186 | K55: 60.508604
... A191: 21367 | C191: 189 | D191: 31.212247 | E191: =+'USD PP 1994'!C1178 -> 67.899408 | F191: 0.034178064 | K191: 31.212247
A192: 21398 | C192: 190 | D192: 31.090992 | E192: =+'USD PP 1994'!C1179 -> 67.899408 | K192: 31.090992
A193: 21429 | C193: 191 | D193: 31.022742 | E193: =+'USD PP 1994'!C1180 -> 67.751479 | K193: 31.022742
A194: 21459 | C194: 192 | D194: 31.010338 | E194: =+'USD PP 1994'!C1181 -> 67.899408 | K194: 31.010338
A195: 21490 | C195: 193 | D195: 30.95771 | E195: =+'USD PP 1994'!C1182 -> 67.899408 | K195: 30.95771
A196: 21520 | C196: 194 | D196: 30.905171 | E196: =+'USD PP 1994'!C1183 -> 67.751479 | K196: 30.905171
A197: 21551 | C197: 195 | D197: 30.742237 | E197: =+'USD PP 1994'!C1184 -> 67.751479 | K197: 30.742237
A198: 21582 | C198: 196 | D198: 30.425809 | E198: =+'USD PP 1994'!C1185 -> 67.60355 | K198: 30.425809
A199: 21610 | C199: 197 | D199: 30.208309 | E199: =+'USD PP 1994'!C1186 -> 67.60355 | K199: 30.208309
A200: 21641 | C200: 198 | D200: 30.04606 | E200: =+'USD PP 1994'!C1187 -> 67.455621 | K200: 30.04606
A201: 21671 | C201: 199 | D201: 29.704459 | E201: =+'USD PP 1994'!C1188 -> 67.159763 | K201: 29.704459
A202: 21702 | C202: 200 | D202: 29.527295 | E202: =+'USD PP 1994'!C1189 -> 66.863905 | K202: 29.527295
A203: 21732 | C203: 201 | D203: 29.42431 | E203: =+'USD PP 1994'!C1190 -> 66.12426 | K203: 29.42431
... A326: 25477 | C326: 324 | D326: 17.370595 | E326: =+'USD PP 1994'!C1313 -> 54.43787 | K326: 17.370595
A327: 25508
A328: 25538
A329: 25569
A330: 25600
A331: 25628
A332: 25659
A333: 25689
A334: 25720
A335: 25750
A336: 25781
A337: 25812
A338: 25842
... A946: 44348

Sheet BD
A1: Data | B1: 193 - Índice de preços ao consumidor-São Paulo (IPC-Fipe) - Var. % mensal | C1: 433 - Índice nacional de preços ao consumidor-amplo (IPCA) - Var. % mensal | D1: 1788 - BM - Base monetária restrita (saldo em final de período) - u.m.c. (mil) | E1: 1827 - Meios de pagamento - M1 (saldo em final de período) - u.m.c. (mil) | F1: 1837 - Meios de pagamento amplos - M2 (saldo em final de período) - u.m.c. (mil) | M1: 433 - Índice nacional de preços ao consumidor-amplo (IPCA) - Var. % mensal
A2: 14277 | B2: -1.52 | C2: - | D2: - | E2: - | F2: - | M2: -
A3: 14305 | B3: 2.48 | C3: - | D3: - | E3: - | F3: - | M3: -
A4: 14336 | B4: 1.81 | C4: - | D4: - | E4: - | F4: - | M4: -
A5: 14366 | B5: 0 | C5: - | D5: - | E5: - | F5: - | M5: -
A6: 14397 | B6: -0.3 | C6: - | D6: - | E6: - | F6: - | M6: -
A7: 14427 | B7: -0.89 | C7: - | D7: - | E7: - | F7: - | M7: -
A8: 14458 | B8: 0.7 | C8: - | D8: - | E8: - | F8: - | M8: -
A9: 14489 | B9: -0.99 | C9: - | D9: - | E9: - | F9: - | M9: -
A10: 14519 | B10: 1.31 | C10: - | D10: - | E10: - | F10: - | M10: -
A11: 14550 | B11: 0.3 | C11: - | D11: - | E11: - | F11: - | M11: -
A12: 14580 | B12: -1.38 | C12: - | D12: - | E12: - | F12: - | M12: -
A13: 14611 | B13: 4.81 | C13: - | D13: - | E13: - | F13: - | M13: -
... A84: 16772 | B84: -0.08 | C84: - | D84: - | E84: - | F84: - | M84: -
A85: 16803 | B85: -3.14 | C85: - | D85: 22900000 | E85: 39600000 | F85: - | M85: -
A86: 16834 | B86: 2.11 | C86: - | D86: 23600000 | E86: 39300000 | F86: - | M86: -
A87: 16862 | B87: 8.29 | C87: - | D87: 23900000 | E87: 38600000 | F87: - | M87: -
A88: 16893 | B88: 1.34 | C88: - | D88: 23700000 | E88: 42000000 | F88: - | M88: -
A89: 16923 | B89: 1.6 | C89: - | D89: 24200000 | E89: 42700000 | F89: - | M89: -
A90: 16954 | B90: 1.99 | C90: - | D90: 24900000 | E90: 43400000 | F90: - | M90: -
A91: 16984 | B91: 3.36 | C91: - | D91: 25500000 | E91: 43800000 | F91: - | M91: -
A92: 17015 | B92: 2.86 | C92: - | D92: 25700000 | E92: 44900000 | F92: - | M92: -
A93: 17046 | B93: -2.46 | C93: - | D93: 25700000 | E93: 45300000 | F93: - | M93: -
A94: 17076 | B94: 1.04 | C94: - | D94: 25600000 | E94: 45400000 | F94: - | M94: -
A95: 17107 | B95: 1.28 | C95: - | D95: 25300000 | E95: 45800000 | F95: - | M95: -
A96: 17137 | B96: -0.32 | C96: - | D96: 25700000 | E96: 45400000 | F96: - | M96: -
... A492: 29190 | B492: 7.06 | C492: - | D492: 366247000 | E492: 838226000 | F492: - | M492: -
A493: 29221 | B493: 4.48 | C493: 6.62 | D493: 339824000 | E493: 814000000 | F493: - | M493: 0.0662
A494: 29252 | B494: 3.35 | C494: 4.62 | D494: 323939000 | E494: 845000000 | F494: - | M494: 0.0462
A495: 29281 | B495: 4.34 | C495: 6.04 | D495: 337933000 | E495: 878000000 | F495: - | M495: 0.0604
A496: 29312 | B496: 3.93 | C496: 5.29 | D496: 364959000 | E496: 957000000 | F496: - | M496: 0.0529
A497: 29342 | B497: 6.52 | C497: 5.7 | D497: 372738000 | E497: 1011000000 | F497: - | M497: 0.057
A498: 29373 | B498: 5.02 | C498: 5.31 | D498: 416236000 | E498: 1101000000 | F498: - | M498: 0.0531
A499: 29403 | B499: 5.24 | C499: 5.55 | D499: 439890000 | E499: 1076000000 | F499: - | M499: 0.0555
A500: 29434 | B500: 5.46 | C500: 4.95 | D500: 446615000 | E500: 1129000000 | F500: - | M500: 0.0495
A501: 29465 | B501: 6.15 | C501: 4.23 | D501: 459175000 | E501: 1170000000 | F501: - | M501: 0.0423
A502: 29495 | B502: 6.78 | C502: 9.48 | D502: 468517000 | E502: 1221000000 | F502: - | M502: 0.0948
A503: 29526 | B503: 6.82 | C503: 6.67 | D503: 512562000 | E503: 1326000000 | F503: - | M503: 0.0667
A504: 29556 | B504: 4.97 | C504: 6.61 | D504: 580353000 | E504: 1487000000 | F504: - | M504: 0.0661
... A594: 32295 | B594: 21.7 | C594: 22 | D594: 911031000 | E594: 1844000000 | F594: - | M594: 0.22
A595: 32325 | B595: 22.65 | C595: 21.91 | D595: 1003891000 | E595: 2047000000 | F595: 14328802230 | M595: 0.2191
A596: 32356 | B596: 19.67 | C596: 21.59 | D596: 1083191000 | E596: 2275000000 | F596: 17432364000 | M596: 0.2159
A597: 32387 | B597: 23.6 | C597: 27.45 | D597: 1426396000 | E597: 2899000000 | F597: 21652380000 | M597: 0.2745
A598: 32417 | B598: 28.48 | C598: 25.62 | D598: 1850104000 | E598: 3837000000 | F598: 27485102903 | M598: 0.2562
A599: 32448 | B599: 25.77 | C599: 27.94 | D599: 2197172000 | E599: 4613000000 | F599: 34626640000 | M599: 0.2794
A600: 32478 | B600: 27.89 | C600: 28.7 | D600: 3637152000 | E600: 6944000000 | F600: 46395824000 | M600: 0.287
A601: 32509 | B601: 31.11 | C601: 37.49 | D601: 4117000 | E601: 8469000 | F601: 53851000 | M601: 0.3749
A602: 32540 | B602: 14.01 | C602: 16.78 | D602: 4925000 | E602: 8892000 | F602: 60412000 | M602: 0.1678
A603: 32568 | B603: 6.46 | C603: 6.82 | D603: 5773000 | E603: 9749000 | F603: 70465682 | M603: 0.0682
A604: 32599 | B604: 10.02 | C604: 8.33 | D604: 6549000 | E604: 14624000 | F604: 83397000 | M604: 0.0833
A605: 32629 | B605: 16.59 | C605: 17.92 | D605: 8748000 | E605: 13985000 | F605: 89313395 | M605: 0.1792
A606: 32660 | B606: 25.29 | C606: 28.65 | D606: 10138000 | E606: 15872000 | F606: 106284000 | M606: 0.2865
... A954: 43252 | B954: 1.01 | C954: 1.26 | D954: 269827763 | E954: 334400842 | F954: 2556074458 | M954: 0.0126
A955: 43282 | B955: 0.23 | C955: 0.33 | D955: 275338550 | E955: - | F955: - | M955: 0.0033
A956: 43313 | B956: 0.41 | C956: -0.09 | D956: 277677286 | E956: - | F956: - | M956: -0.0009
A957: 43344 | B957: 0.39 | C957: 0.48 | D957: 279406906 | E957: - | F957: - | M957: 0.0048
A958: 43374 | B958: 0.48 | C958: 0.45 | D958: 286975496 | E958: - | F958: - | M958: 0.0045
A959: 43405 | B959: 0.15 | C959: -0.21 | D959: 279258830 | E959: - | F959: - | M959: -0.0021
A960: 43435 | B960: 0.09 | C960: 0.15 | D960: 302049461 | E960: - | F960: - | M960: 0.0015
A961: 43466 | B961: 0.58 | C961: 0.32 | D961: 279105602 | E961: - | F961: - | M961: 0.0032
A962: 43497 | B962: 0.54 | C962: 0.43 | D962: 290147814 | E962: - | F962: - | M962: 0.0043 | O962: 100
A963: 43525 | B963: 0.51 | C963: 0.75 | D963: 286741568 | E963: - | F963: - | M963: 0.0075
A964: 43556 | B964: 0.29 | C964: 0.57 | D964: 279604663 | E964: - | F964: - | M964: 0.0057
A965: 43586 | B965: -0.02 | C965: 0.13 | D965: 277875947 | E965: - | F965: - | M965: 0.0013
A966: 43617 | B966: 0.15 | C966: 0.01 | D966: 276039957 | E966: - | F966: - | M966: 0.0001
A967: 43647 | B967: 0.14 | C967: 0.19 | D967: 271344687 | E967: - | F967: - | M967: 0.0019
A968: 43678 | B968: 0.33 | C968: 0.11 | D968: 282617300 | E968: - | F968: - | M968: 0.0011
A969: 43709 | B969: 0 | C969: -0.04 | D969: 281136562 | E969: - | F969: - | M969: -0.0004
A970: 43739 | B970: 0.16 | C970: 0.1 | D970: 292347495 | E970: - | F970: - | M970: 0.001
A971: 43770 | B971: 0.68 | C971: 0.51 | D971: 296782893 | E971: - | F971: - | M971: 0.0051
A972: 43800 | B972: 0.94 | C972: 1.15 | D972: 316586707 | E972: - | F972: - | M972: 0.0115
A973: 43831 | B973: 0.29 | C973: 0.21 | D973: 317959396 | E973: - | F973: - | M973: 0.0021
A974: 43862 | B974: 0.11 | C974: 0.25 | D974: 303197485 | E974: - | F974: - | M974: 0.0025
... A989: 44317 | B989: 0.41 | C989: 0.83 | D989: 403527996 | E989: - | F989: - | M989: 0.0083
A990: 44348 | B990: 0.81 | C990: - | D990: - | E990: - | F990: - | M990: -

Sheet Moedas
A1: Data | B1: 193 - Índice de preços ao consumidor-São Paulo (IPC-Fipe) - Var. % mensal | C1: Cruzeiro (nov/42 a fev/67 | D1: Cruzeiro Novo (fev-67 a mai-70) | E1: Cruzeiro (mai-70 a fev-86) | F1: Cruzado (fev-86 a jan-89) | G1: Cruzado Novo (jan-89 a mar-90) | H1: Cruzeiro (mar-90 a ago/93) | I1: Cruzeiro real (ago/93 a jun-94) | J1: Real (jul/94 a jun-21) | K1: 433 - Índice nacional de preços ao consumidor-amplo (IPCA) - Var. % mensal | L1: 1788 - BM - Base monetária restrita (saldo em final de período) - u.m.c. (mil) | M1: 1827 - Meios de pagamento - M1 (saldo em final de período) - u.m.c. (mil) | N1: 1837 - Meios de pagamento amplos - M2 (saldo em final de período) - u.m.c. (mil)
A2: 14277 | B2: -1.52 | D2: -1.52 | E2: -1.52 | F2: -1.52 | G2: -1.52 | H2: -1.52 | I2: -1.52 | J2: -1.52 | K2: - | L2: - | M2: - | N2: -
A3: 14305 | B3: 2.48 | D3: 2.48 | E3: 2.48 | F3: 2.48 | G3: 2.48 | H3: 2.48 | I3: 2.48 | J3: 2.48 | K3: - | L3: - | M3: - | N3: -
A4: 14336 | B4: 1.81 | D4: 1.81 | E4: 1.81 | F4: 1.81 | G4: 1.81 | H4: 1.81 | I4: 1.81 | J4: 1.81 | K4: - | L4: - | M4: - | N4: -
A5: 14366 | B5: 0 | D5: 0 | E5: 0 | F5: 0 | G5: 0 | H5: 0 | I5: 0 | J5: 0 | K5: - | L5: - | M5: - | N5: -
A6: 14397 | B6: -0.3 | D6: -0.3 | E6: -0.3 | F6: -0.3 | G6: -0.3 | H6: -0.3 | I6: -0.3 | J6: -0.3 | K6: - | L6: - | M6: - | N6: -
A7: 14427 | B7: -0.89 | D7: -0.89 | E7: -0.89 | F7: -0.89 | G7: -0.89 | H7: -0.89 | I7: -0.89 | J7: -0.89 | K7: - | L7: - | M7: - | N7: -
A8: 14458 | B8: 0.7 | D8: 0.7 | E8: 0.7 | F8: 0.7 | G8: 0.7 | H8: 0.7 | I8: 0.7 | J8: 0.7 | K8: - | L8: - | M8: - | N8: -
A9: 14489 | B9: -0.99 | D9: -0.99 | E9: -0.99 | F9: -0.99 | G9: -0.99 | H9: -0.99 | I9: -0.99 | J9: -0.99 | K9: - | L9: - | M9: - | N9: -
A10: 14519 | B10: 1.31 | D10: 1.31 | E10: 1.31 | F10: 1.31 | G10: 1.31 | H10: 1.31 | I10: 1.31 | J10: 1.31 | K10: - | L10: - | M10: - | N10: -
A11: 14550 | B11: 0.3 | D11: 0.3 | E11: 0.3 | F11: 0.3 | G11: 0.3 | H11: 0.3 | I11: 0.3 | J11: 0.3 | K11: - | L11: - | M11: - | N11: -
A12: 14580 | B12: -1.38 | D12: -1.38 | E12: -1.38 | F12: -1.38 | G12: -1.38 | H12: -1.38 | I12: -1.38 | J12: -1.38 | K12: - | L12: - | M12: - | N12: -
A13: 14611 | B13: 4.81 | D13: 4.81 | E13: 4.81 | F13: 4.81 | G13: 4.81 | H13: 4.81 | I13: 4.81 | J13: 4.81 | K13: - | L13: - | M13: - | N13: -
... A46: 15615 | B46: -1.2 | D46: -1.2 | E46: -1.2 | F46: -1.2 | G46: -1.2 | H46: -1.2 | I46: -1.2 | J46: -1.2 | K46: - | L46: - | M46: - | N46: -
A47: 15646 | B47: 0.28 | C47: 0.28 | D47: 0.28 | E47: 0.28 | F47: 0.28 | G47: 0.28 | H47: 0.28 | I47: 0.28 | J47: 0.28 | K47: - | L47: - | M47: - | N47: -
A48: 15676 | B48: -0.21 | C48: -0.21 | D48: -0.21 | E48: -0.21 | F48: -0.21 | G48: -0.21 | H48: -0.21 | I48: -0.21 | J48: -0.21 | K48: - | L48: - | M48: - | N48: -
A49: 15707 | B49: 1.85 | C49: 1.85 | D49: 1.85 | E49: 1.85 | F49: 1.85 | G49: 1.85 | H49: 1.85 | I49: 1.85 | J49: 1.85 | K49: - | L49: - | M49: - | N49: -
A50: 15738 | B50: 1.4 | C50: 1.4 | D50: 1.4 | E50: 1.4 | F50: 1.4 | G50: 1.4 | H50: 1.4 | I50: 1.4 | J50: 1.4 | K50: - | L50: - | M50: - | N50: -
A51: 15766 | B51: -0.14 | C51: -0.14 | D51: -0.14 | E51: -0.14 | F51: -0.14 | G51: -0.14 | H51: -0.14 | I51: -0.14 | J51: -0.14 | K51: - | L51: - | M51: - | N51: -
A52: 15797 | B52: 3.11 | C52: 3.11 | D52: 3.11 | E52: 3.11 | F52: 3.11 | G52: 3.11 | H52: 3.11 | I52: 3.11 | J52: 3.11 | K52: - | L52: - | M52: - | N52: -
A53: 15827 | B53: 0.4 | C53: 0.4 | D53: 0.4 | E53: 0.4 | F53: 0.4 | G53: 0.4 | H53: 0.4 | I53: 0.4 | J53: 0.4 | K53: - | L53: - | M53: - | N53: -
A54: 15858 | B54: -0.47 | C54: -0.47 | D54: -0.47 | E54: -0.47 | F54: -0.47 | G54: -0.47 | H54: -0.47 | I54: -0.47 | J54: -0.47 | K54: - | L54: - | M54: - | N54: -
A55: 15888 | B55: 3.08 | C55: 3.08 | D55: 3.08 | E55: 3.08 | F55: 3.08 | G55: 3.08 | H55: 3.08 | I55: 3.08 | J55: 3.08 | K55: - | L55: - | M55: - | N55: -
A56: 15919 | B56: 0.19 | C56: 0.19 | D56: 0.19 | E56: 0.19 | F56: 0.19 | G56: 0.19 | H56: 0.19 | I56: 0.19 | J56: 0.19 | K56: - | L56: - | M56: - | N56: -
A57: 15950 | B57: 2.08 | C57: 2.08 | D57: 2.08 | E57: 2.08 | F57: 2.08 | G57: 2.08 | H57: 2.08 | I57: 2.08 | J57: 2.08 | K57: - | L57: - | M57: - | N57: -
A58: 15980 | B58: 4.19 | C58: 4.19 | D58: 4.19 | E58: 4.19 | F58: 4.19 | G58: 4.19 | H58: 4.19 | I58: 4.19 | J58: 4.19 | K58: - | L58: - | M58: - | N58: -
... A84: 16772 | B84: -0.08 | C84: -0.08 | D84: -0.08 | E84: -0.08 | F84: -0.08 | G84: -0.08 | H84: -0.08 | I84: -0.08 | J84: -0.08 | K84: - | L84: - | M84: - | N84: -
A85: 16803 | B85: -3.14 | C85: -3.14 | D85: -3.14 | E85: -3.14 | F85: -3.14 | G85: -3.14 | H85: -3.14 | I85: -3.14 | J85: -3.14 | K85: - | L85: 22900000 | M85: 39600000 | N85: -
A86: 16834 | B86: 2.11 | C86: 2.11 | D86: 2.11 | E86: 2.11 | F86: 2.11 | G86: 2.11 | H86: 2.11 | I86: 2.11 | J86: 2.11 | K86: - | L86: 23600000 | M86: 39300000 | N86: -
A87: 16862 | B87: 8.29 | C87: 8.29 | D87: 8.29 | E87: 8.29 | F87: 8.29 | G87: 8.29 | H87: 8.29 | I87: 8.29 | J87: 8.29 | K87: - | L87: 23900000 | M87: 38600000 | N87: -
A88: 16893 | B88: 1.34 | C88: 1.34 | D88: 1.34 | E88: 1.34 | F88: 1.34 | G88: 1.34 | H88: 1.34 | I88: 1.34 | J88: 1.34 | K88: - | L88: 23700000 | M88: 42000000 | N88: -
A89: 16923 | B89: 1.6 | C89: 1.6 | D89: 1.6 | E89: 1.6 | F89: 1.6 | G89: 1.6 | H89: 1.6 | I89: 1.6 | J89: 1.6 | K89: - | L89: 24200000 | M89: 42700000 | N89: -
A90: 16954 | B90: 1.99 | C90: 1.99 | D90: 1.99 | E90: 1.99 | F90: 1.99 | G90: 1.99 | H90: 1.99 | I90: 1.99 | J90: 1.99 | K90: - | L90: 24900000 | M90: 43400000 | N90: -
A91: 16984 | B91: 3.36 | C91: 3.36 | D91: 3.36 | E91: 3.36 | F91: 3.36 | G91: 3.36 | H91: 3.36 | I91: 3.36 | J91: 3.36 | K91: - | L91: 25500000 | M91: 43800000 | N91: -
A92: 17015 | B92: 2.86 | C92: 2.86 | D92: 2.86 | E92: 2.86 | F92: 2.86 | G92: 2.86 | H92: 2.86 | I92: 2.86 | J92: 2.86 | K92: - | L92: 25700000 | M92: 44900000 | N92: -
A93: 17046 | B93: -2.46 | C93: -2.46 | D93: -2.46 | E93: -2.46 | F93: -2.46 | G93: -2.46 | H93: -2.46 | I93: -2.46 | J93: -2.46 | K93: - | L93: 25700000 | M93: 45300000 | N93: -
A94: 17076 | B94: 1.04 | C94: 1.04 | D94: 1.04 | E94: 1.04 | F94: 1.04 | G94: 1.04 | H94: 1.04 | I94: 1.04 | J94: 1.04 | K94: - | L94: 25600000 | M94: 45400000 | N94: -
A95: 17107 | B95: 1.28 | C95: 1.28 | D95: 1.28 | E95: 1.28 | F95: 1.28 | G95: 1.28 | H95: 1.28 | I95: 1.28 | J95: 1.28 | K95: - | L95: 25300000 | M95: 45800000 | N95: -
A96: 17137 | B96: -0.32 | C96: -0.32 | D96: -0.32 | E96: -0.32 | F96: -0.32 | G96: -0.32 | H96: -0.32 | I96: -0.32 | J96: -0.32 | K96: - | L96: 25700000 | M96: 45400000 | N96: -
... A338: 24504 | B338: 1.52 | C338: 1.52 | D338: 1.52 | E338: 1.52 | F338: 1.52 | G338: 1.52 | H338: 1.52 | I338: 1.52 | J338: 1.52 | K338: - | L338: 4844600 | M338: 10584000 | N338: -
A339: 24532 | B339: 3.13 | D339: 3.13 | E339: 3.13 | F339: 3.13 | G339: 3.13 | H339: 3.13 | I339: 3.13 | J339: 3.13 | K339: - | L339: 5145000 | M339: 10989000 | N339: -
A340: 24563 | B340: 3.78 | D340: 3.78 | E340: 3.78 | F340: 3.78 | G340: 3.78 | H340: 3.78 | I340: 3.78 | J340: 3.78 | K340: - | L340: 4979100 | M340: 11599000 | N340: -
A341: 24593 | B341: 1.04 | D341: 1.04 | E341: 1.04 | F341: 1.04 | G341: 1.04 | H341: 1.04 | I341: 1.04 | J341: 1.04 | K341: - | L341: 5066000 | M341: 12189000 | N341: -
A342: 24624 | B342: 1.01 | D342: 1.01 | E342: 1.01 | F342: 1.01 | G342: 1.01 | H342: 1.01 | I342: 1.01 | J342: 1.01 | K342: - | L342: 5188500 | M342: 12753000 | N342: -
A343: 24654 | B343: 2.31 | D343: 2.31 | E343: 2.31 | F343: 2.31 | G343: 2.31 | H343: 2.31 | I343: 2.31 | J343: 2.31 | K343: - | L343: 5281600 | M343: 12971000 | N343: -
A344: 24685 | B344: 1.01 | D344: 1.01 | E344: 1.01 | F344: 1.01 | G344: 1.01 | H344: 1.01 | I344: 1.01 | J344: 1.01 | K344: - | L344: 5246000 | M344: 13479000 | N344: -
A345: 24716 | B345: 1.65 | D345: 1.65 | E345: 1.65 | F345: 1.65 | G345: 1.65 | H345: 1.65 | I345: 1.65 | J345: 1.65 | K345: - | L345: 5550300 | M345: 13845000 | N345: -
A346: 24746 | B346: 1.83 | D346: 1.83 | E346: 1.83 | F346: 1.83 | G346: 1.83 | H346: 1.83 | I346: 1.83 | J346: 1.83 | K346: - | L346: 5511800 | M346: 14120000 | N346: -
A347: 24777 | B347: 1.79 | D347: 1.79 | E347: 1.79 | F347: 1.79 | G347: 1.79 | H347: 1.79 | I347: 1.79 | J347: 1.79 | K347: - | L347: 5756300 | M347: 14771000 | N347: -
A348: 24807 | B348: 0.79 | D348: 0.79 | E348: 0.79 | F348: 0.79 | G348: 0.79 | H348: 0.79 | I348: 0.79 | J348: 0.79 | K348: - | L348: 6095400 | M348: 15004000 | N348: -
A349: 24838 | B349: 2.22 | D349: 2.22 | E349: 2.22 | F349: 2.22 | G349: 2.22 | H349: 2.22 | I349: 2.22 | J349: 2.22 | K349: - | L349: 6167900 | M349: 15087000 | N349: -
A350: 24869 | B350: 3.14 | D350: 3.14 | E350: 3.14 | F350: 3.14 | G350: 3.14 | H350: 3.14 | I350: 3.14 | J350: 3.14 | K350: - | L350: 6311300 | M350: 15508000 | N350: -
... A492: 29190 | B492: 7.06 | D492: 7.06 | E492: 7.06 | F492: 7.06 | G492: 7.06 | H492: 7.06 | I492: 7.06 | J492: 7.06 | K492: - | L492: 366247000 | M492: 838226000 | N492: -
A493: 29221 | B493: 4.48 | D493: 4.48 | E493: 4.48 | F493: 4.48 | G493: 4.48 | H493: 4.48 | I493: 4.48 | J493: 4.48 | K493: 6.62 | L493: 339824000 | M493: 814000000 | N493: -
A494: 29252 | B494: 3.35 | D494: 3.35 | E494: 3.35 | F494: 3.35 | G494: 3.35 | H494: 3.35 | I494: 3.35 | J494: 3.35 | K494: 4.62 | L494: 323939000 | M494: 845000000 | N494: -
A495: 29281 | B495: 4.34 | D495: 4.34 | E495: 4.34 | F495: 4.34 | G495: 4.34 | H495: 4.34 | I495: 4.34 | J495: 4.34 | K495: 6.04 | L495: 337933000 | M495: 878000000 | N495: -
A496: 29312 | B496: 3.93 | D496: 3.93 | E496: 3.93 | F496: 3.93 | G496: 3.93 | H496: 3.93 | I496: 3.93 | J496: 3.93 | K496: 5.29 | L496: 364959000 | M496: 957000000 | N496: -
A497: 29342 | B497: 6.52 | D497: 6.52 | E497: 6.52 | F497: 6.52 | G497: 6.52 | H497: 6.52 | I497: 6.52 | J497: 6.52 | K497: 5.7 | L497: 372738000 | M497: 1011000000 | N497: -
A498: 29373 | B498: 5.02 | D498: 5.02 | E498: 5.02 | F498: 5.02 | G498: 5.02 | H498: 5.02 | I498: 5.02 | J498: 5.02 | K498: 5.31 | L498: 416236000 | M498: 1101000000 | N498: -
A499: 29403 | B499: 5.24 | D499: 5.24 | E499: 5.24 | F499: 5.24 | G499: 5.24 | H499: 5.24 | I499: 5.24 | J499: 5.24 | K499: 5.55 | L499: 439890000 | M499: 1076000000 | N499: -
A500: 29434 | B500: 5.46 | D500: 5.46 | E500: 5.46 | F500: 5.46 | G500: 5.46 | H500: 5.46 | I500: 5.46 | J500: 5.46 | K500: 4.95 | L500: 446615000 | M500: 1129000000 | N500: -
A501: 29465 | B501: 6.15 | D501: 6.15 | E501: 6.15 | F501: 6.15 | G501: 6.15 | H501: 6.15 | I501: 6.15 | J501: 6.15 | K501: 4.23 | L501: 459175000 | M501: 1170000000 | N501: -
A502: 29495 | B502: 6.78 | D502: 6.78 | E502: 6.78 | F502: 6.78 | G502: 6.78 | H502: 6.78 | I502: 6.78 | J502: 6.78 | K502: 9.48 | L502: 468517000 | M502: 1221000000 | N502: -
A503: 29526 | B503: 6.82 | D503: 6.82 | E503: 6.82 | F503: 6.82 | G503: 6.82 | H503: 6.82 | I503: 6.82 | J503: 6.82 | K503: 6.67 | L503: 512562000 | M503: 1326000000 | N503: -
A504: 29556 | B504: 4.97 | D504: 4.97 | E504: 4.97 | F504: 4.97 | G504: 4.97 | H504: 4.97 | I504: 4.97 | J504: 4.97 | K504: 6.61 | L504: 580353000 | M504: 1487000000 | N504: -
... A594: 32295 | B594: 21.7 | D594: 21.7 | E594: 21.7 | F594: 21.7 | G594: 21.7 | H594: 21.7 | I594: 21.7 | J594: 21.7 | K594: 22 | L594: 911031000 | M594: 1844000000 | N594: -
A595: 32325 | B595: 22.65 | D595: 22.65 | E595: 22.65 | F595: 22.65 | G595: 22.65 | H595: 22.65 | I595: 22.65 | J595: 22.65 | K595: 21.91 | L595: 1003891000 | M595: 2047000000 | N595: 14328802230
A596: 32356 | B596: 19.67 | D596: 19.67 | E596: 19.67 | F596: 19.67 | G596: 19.67 | H596: 19.67 | I596: 19.67 | J596: 19.67 | K596: 21.59 | L596: 1083191000 | M596: 2275000000 | N596: 17432364000
A597: 32387 | B597: 23.6 | D597: 23.6 | E597: 23.6 | F597: 23.6 | G597: 23.6 | H597: 23.6 | I597: 23.6 | J597: 23.6 | K597: 27.45 | L597: 1426396000 | M597: 2899000000 | N597: 21652380000
A598: 32417 | B598: 28.48 | D598: 28.48 | E598: 28.48 | F598: 28.48 | G598: 28.48 | H598: 28.48 | I598: 28.48 | J598: 28.48 | K598: 25.62 | L598: 1850104000 | M598: 3837000000 | N598: 27485102903
A599: 32448 | B599: 25.77 | D599: 25.77 | E599: 25.77 | F599: 25.77 | G599: 25.77 | H599: 25.77 | I599: 25.77 | J599: 25.77 | K599: 27.94 | L599: 2197172000 | M599: 4613000000 | N599: 34626640000
A600: 32478 | B600: 27.89 | D600: 27.89 | E600: 27.89 | F600: 27.89 | G600: 27.89 | H600: 27.89 | I600: 27.89 | J600: 27.89 | K600: 28.7 | L600: 3637152000 | M600: 6944000000 | N600: 46395824000
A601: 32509 | B601: 31.11 | D601: 31.11 | E601: 31.11 | F601: 31.11 | G601: 31.11 | H601: 31.11 | I601: 31.11 | J601: 31.11 | K601: 37.49 | L601: 4117000 | M601: 8469000 | N601: 53851000
A602: 32540 | B602: 14.01 | D602: 14.01 | E602: 14.01 | F602: 14.01 | G602: 14.01 | H602: 14.01 | I602: 14.01 | J602: 14.01 | K602: 16.78 | L602: 4925000 | M602: 8892000 | N602: 60412000
A603: 32568 | B603: 6.46 | D603: 6.46 | E603: 6.46 | F603: 6.46 | G603: 6.46 | H603: 6.46 | I603: 6.46 | J603: 6.46 | K603: 6.82 | L603: 5773000 | M603: 9749000 | N603: 70465682
A604: 32599 | B604: 10.02 | D604: 10.02 | E604: 10.02 | F604: 10.02 | G604: 10.02 | H604: 10.02 | I604: 10.02 | J604: 10.02 | K604: 8.33 | L604: 6549000 | M604: 14624000 | N604: 83397000
A605: 32629 | B605: 16.59 | D605: 16.59 | E605: 16.59 | F605: 16.59 | G605: 16.59 | H605: 16.59 | I605: 16.59 | J605: 16.59 | K605: 17.92 | L605: 8748000 | M605: 13985000 | N605: 89313395
A606: 32660 | B606: 25.29 | D606: 25.29 | E606: 25.29 | F606: 25.29 | G606: 25.29 | H606: 25.29 | I606: 25.29 | J606: 25.29 | K606: 28.65 | L606: 10138000 | M606: 15872000 | N606: 106284000
... A954: 43252 | B954: 1.01 | D954: 1.01 | E954: 1.01 | F954: 1.01 | G954: 1.01 | H954: 1.01 | I954: 1.01 | J954: 1.01 | K954: 1.26 | L954: 269827763 | M954: 334400842 | N954: 2556074458
A955: 43282 | B955: 0.23 | D955: 0.23 | E955: 0.23 | F955: 0.23 | G955: 0.23 | H955: 0.23 | I955: 0.23 | J955: 0.23 | K955: 0.33 | L955: 275338550 | M955: - | N955: -
A956: 43313 | B956: 0.41 | D956: 0.41 | E956: 0.41 | F956: 0.41 | G956: 0.41 | H956: 0.41 | I956: 0.41 | J956: 0.41 | K956: -0.09 | L956: 277677286 | M956: - | N956: -
A957: 43344 | B957: 0.39 | D957: 0.39 | E957: 0.39 | F957: 0.39 | G957: 0.39 | H957: 0.39 | I957: 0.39 | J957: 0.39 | K957: 0.48 | L957: 279406906 | M957: - | N957: -
A958: 43374 | B958: 0.48 | D958: 0.48 | E958: 0.48 | F958: 0.48 | G958: 0.48 | H958: 0.48 | I958: 0.48 | J958: 0.48 | K958: 0.45 | L958: 286975496 | M958: - | N958: -
A959: 43405 | B959: 0.15 | D959: 0.15 | E959: 0.15 | F959: 0.15 | G959: 0.15 | H959: 0.15 | I959: 0.15 | J959: 0.15 | K959: -0.21 | L959: 279258830 | M959: - | N959: -
A960: 43435 | B960: 0.09 | D960: 0.09 | E960: 0.09 | F960: 0.09 | G960: 0.09 | H960: 0.09 | I960: 0.09 | J960: 0.09 | K960: 0.15 | L960: 302049461 | M960: - | N960: -
A961: 43466 | B961: 0.58 | D961: 0.58 | E961: 0.58 | F961: 0.58 | G961: 0.58 | H961: 0.58 | I961: 0.58 | J961: 0.58 | K961: 0.32 | L961: 279105602 | M961: - | N961: -
A962: 43497 | B962: 0.54 | D962: 0.54 | E962: 0.54 | F962: 0.54 | G962: 0.54 | H962: 0.54 | I962: 0.54 | J962: 0.54 | K962: 0.43 | L962: 290147814 | M962: - | N962: -
A963: 43525 | B963: 0.51 | D963: 0.51 | E963: 0.51 | F963: 0.51 | G963: 0.51 | H963: 0.51 | I963: 0.51 | J963: 0.51 | K963: 0.75 | L963: 286741568 | M963: - | N963: -
A964: 43556 | B964: 0.29 | D964: 0.29 | E964: 0.29 | F964: 0.29 | G964: 0.29 | H964: 0.29 | I964: 0.29 | J964: 0.29 | K964: 0.57 | L964: 279604663 | M964: - | N964: -
A965: 43586 | B965: -0.02 | D965: -0.02 | E965: -0.02 | F965: -0.02 | G965: -0.02 | H965: -0.02 | I965: -0.02 | J965: -0.02 | K965: 0.13 | L965: 277875947 | M965: - | N965: -
A966: 43617 | B966: 0.15 | D966: 0.15 | E966: 0.15 | F966: 0.15 | G966: 0.15 | H966: 0.15 | I966: 0.15 | J966: 0.15 | K966: 0.01 | L966: 276039957 | M966: - | N966: -
... A989: 44317 | B989: 0.41 | D989: 0.41 | E989: 0.41 | F989: 0.41 | G989: 0.41 | H989: 0.41 | I989: 0.41 | J989: 0.41 | K989: 0.83 | L989: 403527996 | M989: - | N989: -
A990: 44348 | B990: 0.81 | D990: 0.81 | E990: 0.81 | F990: 0.81 | G990: 0.81 | H990: 0.81 | I990: 0.81 | J990: 0.81 | K990: - | L990: - | M990: - | N990: -

Sheet Moedas BD
A1: Data | B1: 193 - Índice de preços ao consumidor-São Paulo (IPC-Fipe) - Var. % mensal | C1: Cruzeiro (nov/42 a fev/67 | D1: Cruzeiro Novo (fev-67 a mai-70) | E1: Cruzeiro (mai-70 a fev-86) | F1: Cruzado (fev-86 a jan-89) | G1: Cruzado Novo (jan-89 a mar-90) | H1: Cruzeiro (mar-90 a ago/93) | I1: Cruzeiro real (ago/93 a jun-94) | J1: Real (jul/94 a jun-21) | K1: 433 - Índice nacional de preços ao consumidor-amplo (IPCA) - Var. % mensal | L1: 1788 - BM - Base monetária restrita (saldo em final de período) - u.m.c. (mil) | M1: 1827 - Meios de pagamento - M1 (saldo em final de período) - u.m.c. (mil) | N1: 1837 - Meios de pagamento amplos - M2 (saldo em final de período) - u.m.c. (mil)
A2: 14277 | B2: -1.52 | K2: - | L2: - | M2: - | N2: -
A3: 14305 | B3: 2.48 | K3: - | L3: - | M3: - | N3: -
A4: 14336 | B4: 1.81 | K4: - | L4: - | M4: - | N4: -
A5: 14366 | B5: 0 | K5: - | L5: - | M5: - | N5: -
A6: 14397 | B6: -0.3 | K6: - | L6: - | M6: - | N6: -
A7: 14427 | B7: -0.89 | K7: - | L7: - | M7: - | N7: -
A8: 14458 | B8: 0.7 | K8: - | L8: - | M8: - | N8: -
A9: 14489 | B9: -0.99 | K9: - | L9: - | M9: - | N9: -
A10: 14519 | B10: 1.31 | K10: - | L10: - | M10: - | N10: -
A11: 14550 | B11: 0.3 | K11: - | L11: - | M11: - | N11: -
A12: 14580 | B12: -1.38 | K12: - | L12: - | M12: - | N12: -
A13: 14611 | B13: 4.81 | K13: - | L13: - | M13: - | N13: -
... A46: 15615 | B46: -1.2 | K46: - | L46: - | M46: - | N46: -
A47: 15646 | B47: 0.28 | C47: 0.28 | K47: - | L47: - | M47: - | N47: -
A48: 15676 | B48: -0.21 | C48: -0.21 | K48: - | L48: - | M48: - | N48: -
A49: 15707 | B49: 1.85 | C49: 1.85 | K49: - | L49: - | M49: - | N49: -
A50: 15738 | B50: 1.4 | C50: 1.4 | K50: - | L50: - | M50: - | N50: -
A51: 15766 | B51: -0.14 | C51: -0.14 | K51: - | L51: - | M51: - | N51: -
A52: 15797 | B52: 3.11 | C52: 3.11 | K52: - | L52: - | M52: - | N52: -
A53: 15827 | B53: 0.4 | C53: 0.4 | K53: - | L53: - | M53: - | N53: -
A54: 15858 | B54: -0.47 | C54: -0.47 | K54: - | L54: - | M54: - | N54: -
A55: 15888 | B55: 3.08 | C55: 3.08 | K55: - | L55: - | M55: - | N55: -
A56: 15919 | B56: 0.19 | C56: 0.19 | K56: - | L56: - | M56: - | N56: -
A57: 15950 | B57: 2.08 | C57: 2.08 | K57: - | L57: - | M57: - | N57: -
A58: 15980 | B58: 4.19 | C58: 4.19 | K58: - | L58: - | M58: - | N58: -
... A84: 16772 | B84: -0.08 | C84: -0.08 | K84: - | L84: - | M84: - | N84: -
A85: 16803 | B85: -3.14 | C85: -3.14 | K85: - | L85: 22900000 | M85: 39600000 | N85: -
A86: 16834 | B86: 2.11 | C86: 2.11 | K86: - | L86: 23600000 | M86: 39300000 | N86: -
A87: 16862 | B87: 8.29 | C87: 8.29 | K87: - | L87: 23900000 | M87: 38600000 | N87: -
A88: 16893 | B88: 1.34 | C88: 1.34 | K88: - | L88: 23700000 | M88: 42000000 | N88: -
A89: 16923 | B89: 1.6 | C89: 1.6 | K89: - | L89: 24200000 | M89: 42700000 | N89: -
A90: 16954 | B90: 1.99 | C90: 1.99 | K90: - | L90: 24900000 | M90: 43400000 | N90: -
A91: 16984 | B91: 3.36 | C91: 3.36 | K91: - | L91: 25500000 | M91: 43800000 | N91: -
A92: 17015 | B92: 2.86 | C92: 2.86 | K92: - | L92: 25700000 | M92: 44900000 | N92: -
A93: 17046 | B93: -2.46 | C93: -2.46 | K93: - | L93: 25700000 | M93: 45300000 | N93: -
A94: 17076 | B94: 1.04 | C94: 1.04 | K94: - | L94: 25600000 | M94: 45400000 | N94: -
A95: 17107 | B95: 1.28 | C95: 1.28 | K95: - | L95: 25300000 | M95: 45800000 | N95: -
A96: 17137 | B96: -0.32 | C96: -0.32 | K96: - | L96: 25700000 | M96: 45400000 | N96: -
... A338: 24504 | B338: 1.52 | C338: 1.52 | K338: - | L338: 4844600 | M338: 10584000 | N338: -
A339: 24532 | B339: 3.13 | D339: 3.13 | K339: - | L339: 5145000 | M339: 10989000 | N339: -
A340: 24563 | B340: 3.78 | D340: 3.78 | K340: - | L340: 4979100 | M340: 11599000 | N340: -
A341: 24593 | B341: 1.04 | D341: 1.04 | K341: - | L341: 5066000 | M341: 12189000 | N341: -
A342: 24624 | B342: 1.01 | D342: 1.01 | K342: - | L342: 5188500 | M342: 12753000 | N342: -
A343: 24654 | B343: 2.31 | D343: 2.31 | K343: - | L343: 5281600 | M343: 12971000 | N343: -
A344: 24685 | B344: 1.01 | D344: 1.01 | K344: - | L344: 5246000 | M344: 13479000 | N344: -
A345: 24716 | B345: 1.65 | D345: 1.65 | K345: - | L345: 5550300 | M345: 13845000 | N345: -
A346: 24746 | B346: 1.83 | D346: 1.83 | K346: - | L346: 5511800 | M346: 14120000 | N346: -
A347: 24777 | B347: 1.79 | D347: 1.79 | K347: - | L347: 5756300 | M347: 14771000 | N347: -
A348: 24807 | B348: 0.79 | D348: 0.79 | K348: - | L348: 6095400 | M348: 15004000 | N348: -
A349: 24838 | B349: 2.22 | D349: 2.22 | K349: - | L349: 6167900 | M349: 15087000 | N349: -
A350: 24869 | B350: 3.14 | D350: 3.14 | K350: - | L350: 6311300 | M350: 15508000 | N350: -
... A377: 25689 | B377: 0.98 | D377: 0.98 | K377: - | L377: 9927000 | M377: 29723000 | N377: -
A378: 25720 | B378: 1.51 | E378: 1.51 | K378: - | L378: 10391000 | M378: 30919000 | N378: -
A379: 25750 | B379: 0.79 | E379: 0.79 | K379: - | L379: 10275000 | M379: 30891000 | N379: -
A380: 25781 | B380: 1.58 | E380: 1.58 | K380: - | L380: 10235000 | M380: 31258000 | N380: -
A381: 25812 | B381: 2.42 | E381: 2.42 | K381: - | L381: 10190000 | M381: 31423000 | N381: -
A382: 25842 | B382: 1.15 | E382: 1.15 | K382: - | L382: 10646000 | M382: 32049000 | N382: -
A383: 25873 | B383: 0.96 | E383: 0.96 | K383: - | L383: 10889000 | M383: 33337000 | N383: -
A384: 25903 | B384: 1.52 | E384: 1.52 | K384: - | L384: 12361000 | M384: 35455000 | N384: -
A385: 25934 | B385: 2.18 | E385: 2.18 | K385: - | L385: 11641000 | M385: 34489000 | N385: -
A386: 25965 | B386: 1.85 | E386: 1.85 | K386: - | L386: 11698000 | M386: 34785000 | N386: -
A387: 25993 | B387: 2.9 | E387: 2.9 | K387: - | L387: 11335000 | M387: 35056000 | N387: -
A388: 26024 | B388: 1.33 | E388: 1.33 | K388: - | L388: 11955000 | M388: 36061000 | N388: -
A389: 26054 | B389: 1.74 | E389: 1.74 | K389: - | L389: 12412000 | M389: 37163000 | N389: -
... A492: 29190 | B492: 7.06 | E492: 7.06 | K492: - | L492: 366247000 | M492: 838226000 | N492: -
A493: 29221 | B493: 4.48 | E493: 4.48 | K493: 6.62 | L493: 339824000 | M493: 814000000 | N493: -
A494: 29252 | B494: 3.35 | E494: 3.35 | K494: 4.62 | L494: 323939000 | M494: 845000000 | N494: -
A495: 29281 | B495: 4.34 | E495: 4.34 | K495: 6.04 | L495: 337933000 | M495: 878000000 | N495: -
A496: 29312 | B496: 3.93 | E496: 3.93 | K496: 5.29 | L496: 364959000 | M496: 957000000 | N496: -
A497: 29342 | B497: 6.52 | E497: 6.52 | K497: 5.7 | L497: 372738000 | M497: 1011000000 | N497: -
A498: 29373 | B498: 5.02 | E498: 5.02 | K498: 5.31 | L498: 416236000 | M498: 1101000000 | N498: -
A499: 29403 | B499: 5.24 | E499: 5.24 | K499: 5.55 | L499: 439890000 | M499: 1076000000 | N499: -
A500: 29434 | B500: 5.46 | E500: 5.46 | K500: 4.95 | L500: 446615000 | M500: 1129000000 | N500: -
A501: 29465 | B501: 6.15 | E501: 6.15 | K501: 4.23 | L501: 459175000 | M501: 1170000000 | N501: -
A502: 29495 | B502: 6.78 | E502: 6.78 | K502: 9.48 | L502: 468517000 | M502: 1221000000 | N502: -
A503: 29526 | B503: 6.82 | E503: 6.82 | K503: 6.67 | L503: 512562000 | M503: 1326000000 | N503: -
A504: 29556 | B504: 4.97 | E504: 4.97 | K504: 6.61 | L504: 580353000 | M504: 1487000000 | N504: -
... A566: 31444 | B566: 10.86 | E566: 10.86 | K566: 12.72 | L566: 51535000000 | M566: 116536000000 | N566: -
A567: 31472 | B567: 1.83 | F567: 1.83 | K567: 4.77 | L567: 70029000 | M567: 210012000 | N567: -
A568: 31503 | B568: 2.31 | F568: 2.31 | K568: 0.78 | L568: 94782000 | M568: 250481000 | N568: -
A569: 31533 | B569: 1.92 | F569: 1.92 | K569: 1.4 | L569: 109024000 | M569: 288894000 | N569: -
A570: 31564 | B570: 0.96 | F570: 0.96 | K570: 1.27 | L570: 120553000 | M570: 334090000 | N570: -
A571: 31594 | B571: 1.07 | F571: 1.07 | K571: 1.71 | L571: 137558000 | M571: 333311000 | N571: -
A572: 31625 | B572: 1.88 | F572: 1.88 | K572: 3.55 | L572: 145798000 | M572: 356193000 | N572: -
A573: 31656 | B573: 1.43 | F573: 1.43 | K573: 1.72 | L573: 149852000 | M573: 375906000 | N573: -
A574: 31686 | B574: 3.08 | F574: 3.08 | K574: 1.9 | L574: 157605000 | M574: 403240000 | N574: -
A575: 31717 | B575: 4.43 | F575: 4.43 | K575: 5.45 | L575: 172456000 | M575: 421915000 | N575: -
A576: 31747 | B576: 10.3 | F576: 10.3 | K576: 11.65 | L576: 178895000 | M576: 455476000 | N576: -
A577: 31778 | B577: 13.75 | F577: 13.75 | K577: 13.21 | L577: 172444000 | M577: 356055000 | N577: -
A578: 31809 | B578: 11.28 | F578: 11.28 | K578: 12.64 | L578: 164309000 | M578: 377484000 | N578: -
... A594: 32295 | B594: 21.7 | F594: 21.7 | K594: 22 | L594: 911031000 | M594: 1844000000 | N594: -
A595: 32325 | B595: 22.65 | F595: 22.65 | K595: 21.91 | L595: 1003891000 | M595: 2047000000 | N595: 14328802230
A596: 32356 | B596: 19.67 | F596: 19.67 | K596: 21.59 | L596: 1083191000 | M596: 2275000000 | N596: 17432364000
A597: 32387 | B597: 23.6 | F597: 23.6 | K597: 27.45 | L597: 1426396000 | M597: 2899000000 | N597: 21652380000
A598: 32417 | B598: 28.48 | F598: 28.48 | K598: 25.62 | L598: 1850104000 | M598: 3837000000 | N598: 27485102903
A599: 32448 | B599: 25.77 | F599: 25.77 | K599: 27.94 | L599: 2197172000 | M599: 4613000000 | N599: 34626640000
A600: 32478 | B600: 27.89 | F600: 27.89 | K600: 28.7 | L600: 3637152000 | M600: 6944000000 | N600: 46395824000
A601: 32509 | B601: 31.11 | F601: 31.11 | K601: 37.49 | L601: 4117000 | M601: 8469000 | N601: 53851000
A602: 32540 | B602: 14.01 | G602: 14.01 | K602: 16.78 | L602: 4925000 | M602: 8892000 | N602: 60412000
...

Sheet Moedas Final
A1: Data | B1: 193 - Índice de preços ao consumidor-São Paulo (IPC-Fipe) - Var. % mensal | C1: Cruzeiro (nov/42 a jan/67 | D1: Cruzeiro Novo (fev-67 a mai-70) | E1: Cruzeiro (jun-70 a fev-86) | F1: Cruzado (mar-86 a dez-88) | G1: Cruzado Novo (jan-89 a fev-90) | H1: Cruzeiro (mar-90 a jul/93) | I1: Cruzeiro Real (ago/93 a jun-94) | J1: Real (jul/94 a jun-21) | K1: Cruzeiro (nov/42 a jan/67 | L1: Cruzeiro Novo (fev-67 a mai-70) | M1: Cruzeiro (jun-70 a fev-86) | N1: Cruzado (mar-86 a dez-88) | O1: Cruzado Novo (jan-89 a fev-90) | P1: Cruzeiro (mar-90 a jul/93) | Q1: Cruzeiro Real (ago/93 a jun-94) | R1: Real (jul/94 a jun-21) | S1: Cruzeiro (nov/42 a jan/67 | T1: Cruzeiro Novo (fev-67 a mai-70) | U1: Cruzeiro (jun-70 a fev-86) | V1: Cruzado (mar-86 a dez-88) | W1: Cruzado Novo (jan-89 a fev-90) | X1: Cruzeiro (mar-90 a jul/93) | Y1: Cruzeiro Real (ago/93 a jun-94) | Z1: Real (jul/94 a jun-21) | AA1: 433 - Índice nacional de preços ao consumidor-amplo (IPCA) - Var. % mensal | AB1: 1788 - BM - Base monetária restrita (saldo em final de período) - u.m.c. (mil) | AC1: 1827 - Meios de pagamento - M1 (saldo em final de período) - u.m.c. (mil) | AD1: 1837 - Meios de pagamento amplos - M2 (saldo em final de período) - u.m.c. (mil)
A2: 14277 | B2: -0.0152 | AA2: - | AB2: - | AC2: - | AD2: -
A3: 14305 | B3: 0.0248 | AA3: - | AB3: - | AC3: - | AD3: -
A4: 14336 | B4: 0.0181 | AA4: - | AB4: - | AC4: - | AD4: -
A5: 14366 | B5: 0 | AA5: - | AB5: - | AC5: - | AD5: -
A6: 14397 | B6: -0.003 | AA6: - | AB6: - | AC6: - | AD6: -
A7: 14427 | B7: -0.0089 | AA7: - | AB7: - | AC7: - | AD7: -
A8: 14458 | B8: 0.007 | AA8: - | AB8: - | AC8: - | AD8: -
A9: 14489 | B9: -0.0099 | AA9: - | AB9: - | AC9: - | AD9: -
A10: 14519 | B10: 0.0131 | AA10: - | AB10: - | AC10: - | AD10: -
A11: 14550 | B11: 0.003 | AA11: - | AB11: - | AC11: - | AD11: -
A12: 14580 | B12: -0.0138 | AA12: - | AB12: - | AC12: - | AD12: -
A13: 14611 | B13: 0.0481 | AA13: - | AB13: - | AC13: - | AD13: -
... A45: 15585 | B45: 0.0208 | AA45: - | AB45: - | AC45: - | AD45: -
A46: 15615 | B46: -0.012 | C46: 100 | K46: 100 | AA46: - | AB46: - | AC46: - | AD46: -
A47: 15646 | B47: 0.0028 | C47: =+$C$46/(1+((K47/100)-1)) -> 99.720782 | K47: =+K46*(1+S47) -> 100.28 | S47: 0.0028 | AA47: - | AB47: - | AC47: - | AD47: -
A48: 15676 | B48: -0.0021 | C48: =+$C$46/(1+((K48/100)-1)) -> 99.930636 | K48: =+K47*(1+S48) -> 100.06941 | S48: -0.0021 | AA48: - | AB48: - | AC48: - | AD48: -
A49: 15707 | B49: 0.0185 | C49: =+$C$46/(1+((K49/100)-1)) -> 98.115499 | K49: =+K48*(1+S49) -> 101.9207 | S49: 0.0185 | AA49: - | AB49: - | AC49: - | AD49: -
A50: 15738 | B50: 0.014 | C50: =+$C$46/(1+((K50/100)-1)) -> 96.760848 | K50: =+K49*(1+S50) -> 103.34759 | S50: 0.014 | AA50: - | AB50: - | AC50: - | AD50: -
A51: 15766 | B51: -0.0014 | C51: =+$C$46/(1+((K51/100)-1)) -> 96.896503 | K51: =+K50*(1+S51) -> 103.2029 | S51: -0.0014 | AA51: - | AB51: - | AC51: - | AD51: -
A52: 15797 | B52: 0.0311 | C52: =+$C$46/(1+((K52/100)-1)) -> 93.973914 | K52: =+K51*(1+S52) -> 106.41251 | S52: 0.0311 | AA52: - | AB52: - | AC52: - | AD52: -
A53: 15827 | B53: 0.004 | C53: =+$C$46/(1+((K53/100)-1)) -> 93.599516 | K53: =+K52*(1+S53) -> 106.83816 | S53: 0.004 | AA53: - | AB53: - | AC53: - | AD53: -
A54: 15858 | B54: -0.0047 | C54: =+$C$46/(1+((K54/100)-1)) -> 94.041511 | K54: =+K53*(1+S54) -> 106.33602 | S54: -0.0047 | AA54: - | AB54: - | AC54: - | AD54: -
A55: 15888 | B55: 0.0308 | C55: =+$C$46/(1+((K55/100)-1)) -> 91.231578 | K55: =+K54*(1+S55) -> 109.61117 | S55: 0.0308 | AA55: - | AB55: - | AC55: - | AD55: -
A56: 15919 | B56: 0.0019 | C56: =+$C$46/(1+((K56/100)-1)) -> 91.058567 | K56: =+K55*(1+S56) -> 109.81943 | S56: 0.0019 | AA56: - | AB56: - | AC56: - | AD56: -
A57: 15950 | B57: 0.0208 | C57: =+$C$46/(1+((K57/100)-1)) -> 89.203142 | K57: =+K56*(1+S57) -> 112.10367 | S57: 0.0208 | AA57: - | AB57: - | AC57: - | AD57: -
A58: 15980 | B58: 0.0419 | C58: =+$C$46/(1+((K58/100)-1)) -> 85.615838 | K58: =+K57*(1+S58) -> 116.80082 | S58: 0.0419 | AA58: - | AB58: - | AC58: - | AD58: -
... A84: 16772 | B84: -0.0008 | C84: =+$C$46/(1+((K84/100)-1)) -> 53.143297 | K84: =+K83*(1+S84) -> 188.17049 | S84: -0.0008 | AA84: - | AB84: - | AC84: - | AD84: -
A85: 16803 | B85: -0.0314 | C85: =+$C$46/(1+((K85/100)-1)) -> 54.866092 | K85: =+K84*(1+S85) -> 182.26193 | S85: -0.0314 | AA85: - | AB85: 22900000 | AC85: 39600000 | AD85: -
A86: 16834 | B86: 0.0211 | C86: =+$C$46/(1+((K86/100)-1)) -> 53.73234 | K86: =+K85*(1+S86) -> 186.10766 | S86: 0.0211 | AA86: - | AB86: 23600000 | AC86: 39300000 | AD86: -
A87: 16862 | B87: 0.0829 | C87: =+$C$46/(1+((K87/100)-1)) -> 49.61893 | K87: =+K86*(1+S87) -> 201.53598 | S87: 0.0829 | AA87: - | AB87: 23900000 | AC87: 38600000 | AD87: -
A88: 16893 | B88: 0.0134 | C88: =+$C$46/(1+((K88/100)-1)) -> 48.962829 | K88: =+K87*(1+S88) -> 204.23657 | S88: 0.0134 | AA88: - | AB88: 23700000 | AC88: 42000000 | AD88: -
A89: 16923 | B89: 0.016 | C89: =+$C$46/(1+((K89/100)-1)) -> 48.19176 | K89: =+K88*(1+S89) -> 207.50435 | S89: 0.016 | AA89: - | AB89: 24200000 | AC89: 42700000 | AD89: -
A90: 16954 | B90: 0.0199 | C90: =+$C$46/(1+((K90/100)-1)) -> 47.251456 | K90: =+K89*(1+S90) -> 211.63369 | S90: 0.0199 | AA90: - | AB90: 24900000 | AC90: 43400000 | AD90: -
A91: 16984 | B91: 0.0336 | C91: =+$C$46/(1+((K91/100)-1)) -> 45.715418 | K91: =+K90*(1+S91) -> 218.74458 | S91: 0.0336 | AA91: - | AB91: 25500000 | AC91: 43800000 | AD91: -
A92: 17015 | B92: 0.0286 | C92: =+$C$46/(1+((K92/100)-1)) -> 44.444311 | K92: =+K91*(1+S92) -> 225.00068 | S92: 0.0286 | AA92: - | AB92: 25700000 | AC92: 44900000 | AD92: -
A93: 17046 | B93: -0.0246 | C93: =+$C$46/(1+((K93/100)-1)) -> 45.565215 | K93: =+K92*(1+S93) -> 219.46566 | S93: -0.0246 | AA93: - | AB93: 25700000 | AC93: 45300000 | AD93: -
A94: 17076 | B94: 0.0104 | C94: =+$C$46/(1+((K94/100)-1)) -> 45.096215 | K94: =+K93*(1+S94) -> 221.7481 | S94: 0.0104 | AA94: - | AB94: 25600000 | AC94: 45400000 | AD94: -
A95: 17107 | B95: 0.0128 | C95: =+$C$46/(1+((K95/100)-1)) -> 44.526278 | K95: =+K94*(1+S95) -> 224.58648 | S95: 0.0128 | AA95: - | AB95: 25300000 | AC95: 45800000 | AD95: -
A96: 17137 | B96: -0.0032 | C96: =+$C$46/(1+((K96/100)-1)) -> 44.66922 | K96: =+K95*(1+S96) -> 223.8678 | S96: -0.0032 | AA96: - | AB96: 25700000 | AC96: 45400000 | AD96: -
... A336: 24442 | B336: 0.018 | C336: =+$C$46/(1+((K336/100)-1)) -> 0.24557719 | K336: =+K335*(1+S336) -> 40720.393 | S336: 0.018 | AA336: - | AB336: 4761100000 | AC336: 10482000000 | AD336: -
A337: 24473 | B337: 0.0298 | C337: =+$C$46/(1+((K337/100)-1)) -> 0.23847077 | D337: 100 | K337: =+K336*(1+S337) -> 41933.861 | L337: 100 | S337: 0.0298 | AA337: - | AB337: 4630500000 | AC337: 10338000000 | AD337: -
A338: 24504 | B338: 0.0152 | D338: =+$D$337/(1+((L338/100)-1)) -> 98.502758 | L338: =+L337*(1+T338) -> 101.52 | T338: 0.0152 | AA338: - | AB338: 4844600 | AC338: 10584000 | AD338: -
A339: 24532 | B339: 0.0313 | D339: =+$D$337/(1+((L339/100)-1)) -> 95.513195 | L339: =+L338*(1+T339) -> 104.69758 | T339: 0.0313 | AA339: - | AB339: 5145000 | AC339: 10989000 | AD339: -
A340: 24563 | B340: 0.0378 | D340: =+$D$337/(1+((L340/100)-1)) -> 92.034299 | L340: =+L339*(1+T340) -> 108.65514 | T340: 0.0378 | AA340: - | AB340: 4979100 | AC340: 11599000 | AD340: -
A341: 24593 | B341: 0.0104 | D341: =+$D$337/(1+((L341/100)-1)) -> 91.086994 | L341: =+L340*(1+T341) -> 109.78516 | T341: 0.0104 | AA341: - | AB341: 5066000 | AC341: 12189000 | AD341: -
A342: 24624 | B342: 0.0101 | D342: =+$D$337/(1+((L342/100)-1)) -> 90.176214 | L342: =+L341*(1+T342) -> 110.89399 | T342: 0.0101 | AA342: - | AB342: 5188500 | AC342: 12753000 | AD342: -
A343: 24654 | B343: 0.0231 | D343: =+$D$337/(1+((L343/100)-1)) -> 88.140176 | L343: =+L342*(1+T343) -> 113.45564 | T343: 0.0231 | AA343: - | AB343: 5281600 | AC343: 12971000 | AD343: -
A344: 24685 | B344: 0.0101 | D344: =+$D$337/(1+((L344/100)-1)) -> 87.258862 | L344: =+L343*(1+T344) -> 114.60154 | T344: 0.0101 | AA344: - | AB344: 5246000 | AC344: 13479000 | AD344: -
A345: 24716 | B345: 0.0165 | D345: =+$D$337/(1+((L345/100)-1)) -> 85.842461 | L345: =+L344*(1+T345) -> 116.49247 | T345: 0.0165 | AA345: - | AB345: 5550300 | AC345: 13845000 | AD345: -
A346: 24746 | B346: 0.0183 | D346: =+$D$337/(1+((L346/100)-1)) -> 84.299775 | L346: =+L345*(1+T346) -> 118.62428 | T346: 0.0183 | AA346: - | AB346: 5511800 | AC346: 14120000 | AD346: -
A347: 24777 | B347: 0.0179 | D347: =+$D$337/(1+((L347/100)-1)) -> 82.817345 | L347: =+L346*(1+T347) -> 120.74765 | T347: 0.0179 | AA347: - | AB347: 5756300 | AC347: 14771000 | AD347: -
A348: 24807 | B348: 0.0079 | D348: =+$D$337/(1+((L348/100)-1)) -> 82.168216 | L348: =+L347*(1+T348) -> 121.70156 | T348: 0.0079 | AA348: - | AB348: 6095400 | AC348: 15004000 | AD348: -
A349: 24838 | B349: 0.0222 | D349: =+$D$337/(1+((L349/100)-1)) -> 80.383698 | L349: =+L348*(1+T349) -> 124.40333 | T349: 0.0222 | AA349: - | AB349: 6167900 | AC349: 15087000 | AD349: -
... A376: 25659 | B376: 0.0136 | D376: =+$D$337/(1+((L376/100)-1)) -> 50.745314 | L376: =+L375*(1+T376) -> 197.06253 | T376: 0.0136 | AA376: - | AB376: 9594000 | AC376: 28703000 | AD376: -
A377: 25689 | B377: 0.0098 | D377: =+$D$337/(1+((L377/100)-1)) -> 50.252836 | E377: 100 | L377: =+L376*(1+T377) -> 198.99374 | M377: 100 | T377: 0.0098 | AA377: - | AB377: 9927000 | AC377: 29723000 | AD377: -
A378: 25720 | B378: 0.0151 | E378: =+E$377/(1+((M378/100)-1)) -> 98.512462 | M378: =+M377*(1+U378) -> 101.51 | U378: 0.0151 | AA378: - | AB378: 10391000 | AC378: 30919000 | AD378: -
A379: 25750 | B379: 0.0079 | E379: =+E$377/(1+((M379/100)-1)) -> 97.740313 | M379: =+M378*(1+U379) -> 102.31193 | U379: 0.0079 | AA379: - | AB379: 10275000 | AC379: 30891000 | AD379: -
A380: 25781 | B380: 0.0158 | E380: =+E$377/(1+((M380/100)-1)) -> 96.220037 | M380: =+M379*(1+U380) -> 103.92846 | U380: 0.0158 | AA380: - | AB380: 10235000 | AC380: 31258000 | AD380: -
A381: 25812 | B381: 0.0242 | E381: =+E$377/(1+((M381/100)-1)) -> 93.946531 | M381: =+M380*(1+U381) -> 106.44353 | U381: 0.0242 | AA381: - | AB381: 10190000 | AC381: 31423000 | AD381: -
A382: 25842 | B382: 0.0115 | E382: =+E$377/(1+((M382/100)-1)) -> 92.878429 | M382: =+M381*(1+U382) -> 107.66763 | U382: 0.0115 | AA382: - | AB382: 10646000 | AC382: 32049000 | AD382: -
A383: 25873 | B383: 0.0096 | E383: =+E$377/(1+((M383/100)-1)) -> 91.995274 | M383: =+M382*(1+U383) -> 108.70124 | U383: 0.0096 | AA383: - | AB383: 10889000 | AC383: 33337000 | AD383: -
A384: 25903 | B384: 0.0152 | E384: =+E$377/(1+((M384/100)-1)) -> 90.617882 | M384: =+M383*(1+U384) -> 110.35349 | U384: 0.0152 | AA384: - | AB384: 12361000 | AC384: 35455000 | AD384: -
A385: 25934 | B385: 0.0218 | E385: =+E$377/(1+((M385/100)-1)) -> 88.684559 | M385: =+M384*(1+U385) -> 112.7592 | U385: 0.0218 | AA385: - | AB385: 11641000 | AC385: 34489000 | AD385: -
A386: 25965 | B386: 0.0185 | E386: =+E$377/(1+((M386/100)-1)) -> 87.073696 | M386: =+M385*(1+U386) -> 114.84525 | U386: 0.0185 | AA386: - | AB386: 11698000 | AC386: 34785000 | AD386: -
A387: 25993 | B387: 0.029 | E387: =+E$377/(1+((M387/100)-1)) -> 84.619724 | M387: =+M386*(1+U387) -> 118.17576 | U387: 0.029 | AA387: - | AB387: 11335000 | AC387: 35056000 | AD387: -
A388: 26024 | B388: 0.0133 | E388: =+E$377/(1+((M388/100)-1)) -> 83.509053 | M388: =+M387*(1+U388) -> 119.7475 | U388: 0.0133 | AA388: - | AB388: 11955000 | AC388: 36061000 | AD388: -
A389: 26054 | B389: 0.0174 | E389: =+E$377/(1+((M389/100)-1)) -> 82.080846 | M389: =+M388*(1+U389) -> 121.8311 | U389: 0.0174 | AA389: - | AB389: 12412000 | AC389: 37163000 | AD389: -
... A492: 29190 | B492: 0.0706 | E492: =+E$377/(1+((M492/100)-1)) -> 7.1623142 | M492: =+M491*(1+U492) -> 1396.1968 | U492: 0.0706 | AA492: - | AB492: 366247000 | AC492: 838226000 | AD492: -
A493: 29221 | B493: 0.0448 | E493: =+E$377/(1+((M493/100)-1)) -> 6.8552012 | M493: =+M492*(1+U493) -> 1458.7464 | U493: 0.0448 | AA493: 6.62 | AB493: 339824000 | AC493: 814000000 | AD493: -
A494: 29252 | B494: 0.0335 | E494: =+E$377/(1+((M494/100)-1)) -> 6.6329959 | M494: =+M493*(1+U494) -> 1507.6144 | U494: 0.0335 | AA494: 4.62 | AB494: 323939000 | AC494: 845000000 | AD494: -
A495: 29281 | B495: 0.0434 | E495: =+E$377/(1+((M495/100)-1)) -> 6.3570978 | M495: =+M494*(1+U495) -> 1573.0449 | U495: 0.0434 | AA495: 6.04 | AB495: 337933000 | AC495: 878000000 | AD495: -
A496: 29312 | B496: 0.0393 | E496: =+E$377/(1+((M496/100)-1)) -> 6.1167111 | M496: =+M495*(1+U496) -> 1634.8655 | U496: 0.0393 | AA496: 5.29 | AB496: 364959000 | AC496: 957000000 | AD496: -
A497: 29342 | B497: 0.0652 | E497: =+E$377/(1+((M497/100)-1)) -> 5.7423123 | M497: =+M496*(1+U497) -> 1741.4588 | U497: 0.0652 | AA497: 5.7 | AB497: 372738000 | AC497: 1011000000 | AD497: -
A498: 29373 | B498: 0.0502 | E498: =+E$377/(1+((M498/100)-1)) -> 5.4678274 | M498: =+M497*(1+U498) -> 1828.88 | U498: 0.0502 | AA498: 5.31 | AB498: 416236000 | AC498: 1101000000 | AD498: -
A499: 29403 | B499: 0.0524 | E499: =+E$377/(1+((M499/100)-1)) -> 5.195579 | M499: =+M498*(1+U499) -> 1924.7133 | U499: 0.0524 | AA499: 5.55 | AB499: 439890000 | AC499: 1076000000 | AD499: -
A500: 29434 | B500: 0.0546 | E500: =+E$377/(1+((M500/100)-1)) -> 4.9265874 | M500: =+M499*(1+U500) -> 2029.8026 | U500: 0.0546 | AA500: 4.95 | AB500: 446615000 | AC500: 1129000000 | AD500: -
A501: 29465 | B501: 0.0615 | E501: =+E$377/(1+((M501/100)-1)) -> 4.6411562 | M501: =+M500*(1+U501) -> 2154.6355 | U501: 0.0615 | AA501: 4.23 | AB501: 459175000 | AC501: 1170000000 | AD501: -
A502: 29495 | B502: 0.0678 | E502: =+E$377/(1+((M502/100)-1)) -> 4.3464659 | M502: =+M501*(1+U502) -> 2300.7198 | U502: 0.0678 | AA502: 9.48 | AB502: 468517000 | AC502: 1221000000 | AD502: -
A503: 29526 | B503: 0.0682 | E503: =+E$377/(1+((M503/100)-1)) -> 4.0689626 | M503: =+M502*(1+U503) -> 2457.6289 | U503: 0.0682 | AA503: 6.67 | AB503: 512562000 | AC503: 1326000000 | AD503: -
A504: 29556 | B504: 0.0497 | E504: =+E$377/(1+((M504/100)-1)) -> 3.87631 | M504: =+M503*(1+U504) -> 2579.773 | U504: 0.0497 | AA504: 6.61 | AB504: 580353000 | AC504: 1487000000 | AD504: -
... A565: 31413 | B565: 0.1405 | E565: =+E$377/(1+((M565/100)-1)) -> 0.037889802 | M565: =+M564*(1+U565) -> 263923.26 | U565: 0.1405 | AA565: 14.37 | AB565: 45941000000 | AC565: 102136000000 | AD565: -
A566: 31444 | B566: 0.1086 | E566: =+E$377/(1+((M566/100)-1)) -> 0.034178064 | F566: 100 | M566: =+M565*(1+U566) -> 292585.32 | N566: 100 | U566: 0.1086 | AA566: 12.72 | AB566: 51535000000 | AC566: 116536000000 | AD566: -
A567: 31472 | B567: 0.0183 | F567: =+F$566/(1+((N567/100)-1)) -> 98.202887 | N567: =+N566*(1+V567) -> 101.83 | V567: 0.0183 | AA567: 4.77 | AB567: 70029000 | AC567: 210012000 | AD567: -
A568: 31503 | B568: 0.0231 | F568: =+F$566/(1+((N568/100)-1)) -> 95.985619 | N568: =+N567*(1+V568) -> 104.18227 | V568: 0.0231 | AA568: 0.78 | AB568: 94782000 | AC568: 250481000 | AD568: -
A569: 31533 | B569: 0.0192 | F569: =+F$566/(1+((N569/100)-1)) -> 94.177413 | N569: =+N568*(1+V569) -> 106.18257 | V569: 0.0192 | AA569: 1.4 | AB569: 109024000 | AC569: 288894000 | AD569: -
A570: 31564 | B570: 0.0096 | F570: =+F$566/(1+((N570/100)-1)) -> 93.281907 | N570: =+N569*(1+V570) -> 107.20193 | V570: 0.0096 | AA570: 1.27 | AB570: 120553000 | AC570: 334090000 | AD570: -
A571: 31594 | B571: 0.0107 | F571: =+F$566/(1+((N571/100)-1)) -> 92.294357 | N571: =+N570*(1+V571) -> 108.34899 | V571: 0.0107 | AA571: 1.71 | AB571: 137558000 | AC571: 333311000 | AD571: -
A572: 31625 | B572: 0.0188 | F572: =+F$566/(1+((N572/100)-1)) -> 90.591242 | N572: =+N571*(1+V572) -> 110.38595 | V572: 0.0188 | AA572: 3.55 | AB572: 145798000 | AC572: 356193000 | AD572: -
A573: 31656 | B573: 0.0143 | F573: =+F$566/(1+((N573/100)-1)) -> 89.314051 | N573: =+N572*(1+V573) -> 111.96447 | V573: 0.0143 | AA573: 1.72 | AB573: 149852000 | AC573: 375906000 | AD573: -
A574: 31686 | B574: 0.0308 | F574: =+F$566/(1+((N574/100)-1)) -> 86.645373 | N574: =+N573*(1+V574) -> 115.41297 | V574: 0.0308 | AA574: 1.9 | AB574: 157605000 | AC574: 403240000 | AD574: -
A575: 31717 | B575: 0.0443 | F575: =+F$566/(1+((N575/100)-1)) -> 82.969811 | N575: =+N574*(1+V575) -> 120.52577 | V575: 0.0443 | AA575: 5.45 | AB575: 172456000 | AC575: 421915000 | AD575: -
A576: 31747 | B576: 0.103 | F576: =+F$566/(1+((N576/100)-1)) -> 75.22195 | N576: =+N575*(1+V576) -> 132.93992 | V576: 0.103 | AA576: 11.65 | AB576: 178895000 | AC576: 455476000 | AD576: -
A577: 31778 | B577: 0.1375 | F577: =+F$566/(1+((N577/100)-1)) -> 66.129187 | N577: =+N576*(1+V577) -> 151.21916 | V577: 0.1375 | AA577: 13.21 | AB577: 172444000 | AC577: 356055000 | AD577: -
A578: 31809 | B578: 0.1128 | F578: =+F$566/(1+((N578/100)-1)) -> 59.425941 | N578: =+N577*(1+V578) -> 168.27668 | V578: 0.1128 | AA578: 12.64 | AB578: 164309000 | AC578: 377484000 | AD578: -
... A594: 32295 | B594: 0.217 | F594: =+F$566/(1+((N594/100)-1)) -> 6.0878789 | N594: =+N593*(1+V594) -> 1642.6082 | V594: 0.217 | AA594: 22 | AB594: 911031000 | AC594: 1844000000 | AD594: -
A595: 32325 | B595: 0.2265 | F595: =+F$566/(1+((N595/100)-1)) -> 4.9636191 | N595: =+N594*(1+V595) -> 2014.659 | V595: 0.2265 | AA595: 21.91 | AB595: 1003891000 | AC595: 2047000000 | AD595: 14328802230
A596: 32356 | B596: 0.1967 | F596: =+F$566/(1+((N596/100)-1)) -> 4.1477556 | N596: =+N595*(1+V596) -> 2410.9424 | V596: 0.1967 | AA596: 21.59 | AB596: 1083191000 | AC596: 2275000000 | AD596: 17432364000
A597: 32387 | B597: 0.236 | F597: =+F$566/(1+((N597/100)-1)) -> 3.3557893 | N597: =+N596*(1+V597) -> 2979.9248 | V597: 0.236 | AA597: 27.45 | AB597: 1426396000 | AC597: 2899000000 | AD597: 21652380000
A598: 32417 | B598: 0.2848 | F598: =+F$566/(1+((N598/100)-1)) -> 2.6119157 | N598: =+N597*(1+V598) -> 3828.6074 | V598: 0.2848 | AA598: 25.62 | AB598: 1850104000 | AC598: 3837000000 | AD598: 27485102903
...

Sheet BD ipca e tcr
A1: Data | B1: 433 - Índice nacional de preços ao consumidor-amplo (IPCA) - Var. % mensal | C1: 11753 - Índice da taxa de câmbio real (IPCA) - Jun/1994=100 - Dólar americano - Índice
A2: 29221 | B2: 6.62 | C2: -
A3: 29252 | B3: 4.62 | C3: -
A4: 29281 | B4: 6.04 | C4: -
A5: 29312 | B5: 5.29 | C5: -
A6: 29342 | B6: 5.7 | C6: -
A7: 29373 | B7: 5.31 | C7: -
A8: 29403 | B8: 5.55 | C8: -
A9: 29434 | B9: 4.95 | C9: -
A10: 29465 | B10: 4.23 | C10: -
A11: 29495 | B11: 9.48 | C11: -
A12: 29526 | B12: 6.67 | C12: -
A13: 29556 | B13: 6.61 | C13: -
... A97: 32112 | B97: 14.15 | C97: -
A98: 32143 | B98: 18.89 | C98: 132.26
A99: 32174 | B99: 15.7 | C99: 133.93
A100: 32203 | B100: 17.6 | C100: 134.91
A101: 32234 | B101: 19.29 | C101: 133.42
A102: 32264 | B102: 17.42 | C102: 136.6
A103: 32295 | B103: 22 | C103: 133.12
A104: 32325 | B104: 21.91 | C104: 132.73
A105: 32356 | B105: 21.59 | C105: 135.83
A106: 32387 | B106: 27.45 | C106: 130.88
A107: 32417 | B107: 25.62 | C107: 131.94
A108: 32448 | B108: 27.94 | C108: 131.92
A109: 32478 | B109: 28.7 | C109: 130.92
... A524: 45108 | B524: 0.12 | C524: 127.49
A525: 45139 | B525: 0.23 | C525: -
A526: 45170 | B526: 0.26 | C526: -
A527: Fonte | B527: IBGE | C527: BCB-DSTAT

Sheet Moedas Meses Chart
A1: Data | B1: Cruzeiro (nov/42 a jan/67 | C1: Cruzeiro (jun-70 a fev-86) | D1: Cruzado (mar-86 a dez-88) | E1: Cruzado Novo (jan-89 a fev-90) | F1: Cruzeiro (mar-90 a jul/93) | G1: Cruzeiro Real (ago/93 a jun-94)
A2: Qtd. Meses | B2: 173 | C2: 109 | D2: 26 | E2: 11 | F2: 15 | G2: 8

Sheet Moedas Chart Curto
A1: Data | C1: Mês | D1: Cruzeiro (nov/42 a jan/67 | E1: Cruzeiro Novo (fev-67 a mai-70) | F1: Cruzeiro (jun-70 a fev-86) | G1: Cruzado (mar-86 a dez-88) | H1: Cruzado Novo (jan-89 a fev-90) | I1: Cruzeiro (mar-90 a jul/93) | J1: Cruzeiro Real (ago/93 a jun-94) | K1: Real (jul/94 a jun-21)
A2: 15615 | C2: 0 | D2: 100 | E2: 100 | F2: 100 | G2: 100 | H2: 100 | I2: 100 | J2: 100 | K2: 100
A3: 15646 | C3: 1 | D3: 99.720782 | E3: 98.502758 | F3: 98.512462 | G3: 98.202887 | H3: 76.271833 | I3: 55.831612 | J3: 74.643577 | K3: 93.501636
A4: 15676 | C4: 2 | D4: 99.930636 | E4: 95.513195 | F4: 97.740313 | G4: 95.985619 | H4: 66.899248 | I4: 46.452793 | J4: 55.654322 | K4: 91.713228
A5: 15707 | C5: 3 | D5: 98.115499 | E5: 92.034299 | F5: 96.220037 | G5: 94.177413 | H5: 62.839797 | I5: 42.801799 | J5: 41.155307 | K5: 90.967296
A6: 15738 | C6: 4 | D6: 96.760848 | E6: 91.086994 | F6: 93.946531 | G6: 93.281907 | H6: 57.116704 | I6: 38.318531 | J6: 30.296899 | K6: 88.172237
A7: 15766 | C7: 5 | D7: 96.896503 | E7: 90.176214 | F7: 92.878429 | G7: 92.294357 | H7: 48.989367 | I7: 34.425057 | J7: 21.871859 | K7: 85.587494
A8: 15797 | C8: 6 | D8: 93.973914 | E8: 88.140176 | F8: 91.995274 | G8: 90.591242 | H8: 39.10078 | I8: 30.783383 | J8: 15.589351 | K8: 84.530859
A9: 15827 | C9: 7 | D9: 93.599516 | E9: 87.258862 | F9: 90.617882 | G9: 89.314051 | H9: 30.533172 | I9: 27.210628 | J9: 11.281099 | K9: 83.859979
A10: 15858 | C10: 8 | D10: 94.041511 | E10: 85.842461 | F10: 88.684559 | G10: 86.645373 | H10: 23.316664 | I10: 23.491865 | J10: 7.9477941 | K10: 82.767448
A11: 15888 | C11: 9 | D11: 91.231578 | E11: 84.299775 | F11: 87.073696 | G11: 82.969811 | H11: 17.166064 | I11: 19.814326 | J11: 5.4355041 | K11: 81.20825
A12: 15919 | C12: 10 | D12: 91.058567 | E12: 82.817345 | F12: 84.619724 | G12: 75.22195 | H12: 12.503506 | I12: 17.076899 | J12: 3.74604 | K12: 79.119495
A13: 15950 | C13: 11 | D13: 89.203142 | E13: 82.168216 | F13: 83.509053 | G13: 66.129187 | H13: 8.7461572 | I13: 14.110808 | J13: 2.4849353 | K13: 77.590954
A14: 15980 | C14: 12 | D14: 85.615838 | E14: 80.383698 | F14: 82.080846 | G14: 59.425941 | H14: 5.7608729 | I14: 11.706328 | K14: 75.580512
A15: 16011 | C15: 13 | D15: 85.513222 | E15: 77.936492 | F15: 80.46353 | G15: 53.073092 | H15: 3.3007923 | I15: 10.891634 | K15: 72.869757
A16: 16041 | C16: 14 | D16: 83.828274 | E16: 77.279615 | F16: 79.407411 | G16: 45.536758 | H16: 1.9398168 | I16: 10.161054 | K16: 71.84241
A17: 16072 | C17: 15 | D17: 75.897034 | E17: 75.357986 | F17: 78.303334 | G17: 36.000283 | I17: 9.6076531 | K17: 71.314682
A18: 16103 | C18: 16 | D18: 75.406889 | E18: 73.191517 | F18: 77.705005 | G18: 28.40035 | I18: 8.7517336 | K18: 70.274617
A19: 16132 | C19: 17 | D19: 74.483296 | E19: 72.402332 | F19: 76.79119 | G19: 25.998123 | I19: 7.8631928 | K19: 69.461913
A20: 16163 | C20: 18 | D20: 71.487951 | E20: 71.304247 | F20: 75.8132 | G20: 24.890496 | I20: 6.8722188 | K20: 68.631472
A21: 16193 | C21: 19 | D21: 69.130598 | E21: 70.271259 | F21: 75.136967 | G21: 23.320993 | I21: 5.9136209 | K21: 67.404707
A22: 16224 | C22: 20 | D22: 67.961657 | E22: 69.444865 | F22: 73.490774 | G22: 21.168188 | I22: 4.7244714 | K22: 67.136162
A23: 16254 | C23: 21 | D23: 64.260266 | E23: 67.863642 | F23: 72.468962 | G23: 18.666833 | I23: 3.7678215 | K23: 66.982103
A24: 16285 | C24: 22 | D24: 63.192316 | E24: 66.598275 | F24: 71.751447 | G24: 16.103203 | I24: 3.057056 | K24: 65.914292
A25: 16316 | C25: 23 | D25: 62.80918 | E25: 65.620529 | F25: 70.88663 | G25: 14.03941 | I25: 2.4283549 | K25: 65.042719
A26: 16346 | C26: 24 | D26: 62.640052 | E26: 64.296031 | F26: 70.421846 | G26: 12.382616 | I26: 1.9974952 | K26: 64.138368
A27: 16377 | C27: 25 | D27: 60.510096 | E27: 63.420824 | F27: 69.641857 | G27: 10.436254 | I27: 1.6407879 | K27: 63.30902
A28: 16407 | C28: 26 | D28: 61.139837 | E28: 62.712176 | F28: 68.0628 | G28: 8.6129027 | I28: 1.3369086 | K28: 63.094499
... A36: 16650 | C36: 34 | D36: 52.179108 | E36: 54.408886 | F36: 61.538235 | G36: 1.6238485 | I36: 0.24865301 | K36: 61.084333
A37: 16681 | C37: 35 | D37: 51.831835 | E37: 53.530978 | F37: 60.509572 | I37: 0.19514441 | K37: 60.750207
A38: 16711 | C38: 36 | D38: 52.803418 | E38: 52.802306 | F38: 60.023382 | I38: 0.15599073 | K38: 59.899632
A39: 16742 | C39: 37 | D39: 53.100782 | E39: 52.124686 | F39: 59.558824 | I39: 0.12463306 | K39: 59.833815
A40: 16772 | C40: 38 | D40: 53.143297 | E40: 51.435451 | F40: 58.922461 | I40: 0.096809894 | K40: 60.292035
A41: 16803 | C41: 39 | D41: 54.866092 | E41: 50.745314 | F41: 58.298665 | I41: 0.074965072 | K41: 60.286006
A42: 16834 | C42: 40 | D42: 53.73234 | E42: 50.252836 | F42: 57.584616 | I42: 0.057431297 | K42: 60.153668
A43: 16862 | C43: 41 | D43: 49.61893 | F43: 56.946812 | I43: 0.043877528 | K43: 59.836534
A44: 16893 | C44: 42 | D44: 48.962829 | F44: 56.422086 | K44: 59.497399
A45: 16923 | C45: 43 | D45: 48.19176 | F45: 56.130209 | K45: 59.354947
A46: 16954 | C46: 44 | D46: 47.251456 | F46: 55.607499 | K46: 59.450067
A47: 16984 | C47: 45 | D47: 45.715418 | F47: 53.695924 | K47: 59.587118
A48: 17015 | C48: 46 | D48: 44.444311 | F48: 51.551386 | K48: 59.219954
A49: 17046 | C49: 47 | D49: 45.565215 | F49: 49.040512 | K49: 58.913603
A50: 17076 | C50: 48 | D50: 45.096215 | F50: 48.145015 | K50: 58.80188
A51: 17107 | C51: 49 | D51: 44.526278 | F51: 47.536547 | K51: 59.258168
A52: 17137 | C52: 50 | D52: 44.66922 | F52: 46.504155 | K52: 59.856735
A53: 17168 | C53: 51 | D53: 38.244195 | F53: 45.614669 | K53: 60.254414
A54: 17199 | C54: 52 | D54: 37.04397 | F54: 44.891909 | K54: 60.242366
A55: 17227 | C55: 53 | D55: 35.818962 | F55: 44.150186 | K55: 60.508604
... A191: 21367 | C191: 189 | D191: 8.301152 | F191: 0.034178064 | K191: 31.212247
A192: 21398 | C192: 190 | D192: 8.2779737 | K192: 31.090992
A193: 21429 | C193: 191 | D193: 8.1180481 | K193: 31.022742
A194: 21459 | C194: 192 | D194: 7.9007768 | K194: 31.010338
A195: 21490 | C195: 193 | D195: 7.4416283 | K195: 30.95771
A196: 21520 | C196: 194 | D196: 7.4416283 | K196: 30.905171
A197: 21551 | C197: 195 | D197: 7.0496668 | K197: 30.742237
A198: 21582 | C198: 196 | D198: 6.7896242 | K198: 30.425809
A199: 21610 | C199: 197 | D199: 6.5190823 | K199: 30.208309
A200: 21641 | C200: 198 | D200: 6.4057014 | K200: 30.04606
A201: 21671 | C201: 199 | D201: 6.3504525 | K201: 29.704459
A202: 21702 | C202: 200 | D202: 6.2559871 | K202: 29.527295
A203: 21732 | C203: 201 | D203: 6.1641413 | K203: 29.42431
... A293: 24473 | C293: 291 | D293: 0.23847077 | K293: 19.96851
A294: 24504 | C294: 292 | K294: 19.87312
A295: 24532 | C295: 293 | K295: 19.843354
A296: 24563 | C296: 294 | K296: 19.825512
A297: 24593 | C297: 295 | K297: 19.711187
A298: 24624 | C298: 296 | K298: 19.605318
A299: 24654 | C299: 297 | K299: 19.505838
A300: 24685 | C300: 298 | K300: 19.449435
A301: 24716 | C301: 299 | K301: 19.453325
A302: 24746 | C302: 300 | K302: 19.424189
A303: 24777 | C303: 301 | K303: 19.397033
A304: 24807 | C304: 302 | K304: 19.333234
A305: 24838 | C305: 303 | K305: 19.333234
... A326: 25477 | C326: 324 | K326: 17.370595
A327: 25508
A328: 25538
A329: 25569
A330: 25600
A331: 25628
A332: 25659
A333: 25689
A334: 25720
A335: 25750
A336: 25781
A337: 25812
A338: 25842
... A946: 44348

Sheet Moedas Chart
A1: Data | C1: Mês | D1: Cruzeiro (nov/42 a jan/67 | E1: Cruzeiro Novo (fev-67 a mai-70) | F1: Cruzeiro (jun-70 a fev-86) | G1: Cruzado (mar-86 a dez-88) | H1: Cruzado Novo (jan-89 a fev-90) | I1: Cruzeiro (mar-90 a jul/93) | J1: Cruzeiro Real (ago/93 a jun-94) | K1: Real (jul/94 a jun-21)
A2: 15615 | C2: 0 | D2: 100 | E2: 100 | F2: 100 | G2: 100 | H2: 100 | I2: 100 | J2: 100 | K2: 100
A3: 15646 | C3: 1 | D3: 99.720782 | E3: 98.502758 | F3: 98.512462 | G3: 98.202887 | H3: 76.271833 | I3: 55.831612 | J3: 74.643577 | K3: 93.501636
A4: 15676 | C4: 2 | D4: 99.930636 | E4: 95.513195 | F4: 97.740313 | G4: 95.985619 | H4: 66.899248 | I4: 46.452793 | J4: 55.654322 | K4: 91.713228
A5: 15707 | C5: 3 | D5: 98.115499 | E5: 92.034299 | F5: 96.220037 | G5: 94.177413 | H5: 62.839797 | I5: 42.801799 | J5: 41.155307 | K5: 90.967296
A6: 15738 | C6: 4 | D6: 96.760848 | E6: 91.086994 | F6: 93.946531 | G6: 93.281907 | H6: 57.116704 | I6: 38.318531 | J6: 30.296899 | K6: 88.172237
A7: 15766 | C7: 5 | D7: 96.896503 | E7: 90.176214 | F7: 92.878429 | G7: 92.294357 | H7: 48.989367 | I7: 34.425057 | J7: 21.871859 | K7: 85.587494
A8: 15797 | C8: 6 | D8: 93.973914 | E8: 88.140176 | F8: 91.995274 | G8: 90.591242 | H8: 39.10078 | I8: 30.783383 | J8: 15.589351 | K8: 84.530859
A9: 15827 | C9: 7 | D9: 93.599516 | E9: 87.258862 | F9: 90.617882 | G9: 89.314051 | H9: 30.533172 | I9: 27.210628 | J9: 11.281099 | K9: 83.859979
A10: 15858 | C10: 8 | D10: 94.041511 | E10: 85.842461 | F10: 88.684559 | G10: 86.645373 | H10: 23.316664 | I10: 23.491865 | J10: 7.9477941 | K10: 82.767448
A11: 15888 | C11: 9 | D11: 91.231578 | E11: 84.299775 | F11: 87.073696 | G11: 82.969811 | H11: 17.166064 | I11: 19.814326 | J11: 5.4355041 | K11: 81.20825
A12: 15919 | C12: 10 | D12: 91.058567 | E12: 82.817345 | F12: 84.619724 | G12: 75.22195 | H12: 12.503506 | I12: 17.076899 | J12: 3.74604 | K12: 79.119495
A13: 15950 | C13: 11 | D13: 89.203142 | E13: 82.168216 | F13: 83.509053 | G13: 66.129187 | H13: 8.7461572 | I13: 14.110808 | J13: 2.4849353 | K13: 77.590954
A14: 15980 | C14: 12 | D14: 85.615838 | E14: 80.383698 | F14: 82.080846 | G14: 59.425941 | H14: 5.7608729 | I14: 11.706328 | K14: 75.580512
A15: 16011 | C15: 13 | D15: 85.513222 | E15: 77.936492 | F15: 80.46353 | G15: 53.073092 | H15: 3.3007923 | I15: 10.891634 | K15: 72.869757
A16: 16041 | C16: 14 | D16: 83.828274 | E16: 77.279615 | F16: 79.407411 | G16: 45.536758 | H16: 1.9398168 | I16: 10.161054 | K16: 71.84241
A17: 16072 | C17: 15 | D17: 75.897034 | E17: 75.357986 | F17: 78.303334 | G17: 36.000283 | I17: 9.6076531 | K17: 71.314682
A18: 16103 | C18: 16 | D18: 75.406889 | E18: 73.191517 | F18: 77.705005 | G18: 28.40035 | I18: 8.7517336 | K18: 70.274617
A19: 16132 | C19: 17 | D19: 74.483296 | E19: 72.402332 | F19: 76.79119 | G19: 25.998123 | I19: 7.8631928 | K19: 69.461913
A20: 16163 | C20: 18 | D20: 71.487951 | E20: 71.304247 | F20: 75.8132 | G20: 24.890496 | I20: 6.8722188 | K20: 68.631472
A21: 16193 | C21: 19 | D21: 69.130598 | E21: 70.271259 | F21: 75.136967 | G21: 23.320993 | I21: 5.9136209 | K21: 67.404707
A22: 16224 | C22: 20 | D22: 67.961657 | E22: 69.444865 | F22: 73.490774 | G22: 21.168188 | I22: 4.7244714 | K22: 67.136162
A23: 16254 | C23: 21 | D23: 64.260266 | E23: 67.863642 | F23: 72.468962 | G23: 18.666833 | I23: 3.7678215 | K23: 66.982103
A24: 16285 | C24: 22 | D24: 63.192316 | E24: 66.598275 | F24: 71.751447 | G24: 16.103203 | I24: 3.057056 | K24: 65.914292
A25: 16316 | C25: 23 | D25: 62.80918 | E25: 65.620529 | F25: 70.88663 | G25: 14.03941 | I25: 2.4283549 | K25: 65.042719
A26: 16346 | C26: 24 | D26: 62.640052 | E26: 64.296031 | F26: 70.421846 | G26: 12.382616 | I26: 1.9974952 | K26: 64.138368
A27: 16377 | C27: 25 | D27: 60.510096 | E27: 63.420824 | F27: 69.641857 | G27: 10.436254 | I27: 1.6407879 | K27: 63.30902
A28: 16407 | C28: 26 | D28: 61.139837 | E28: 62.712176 | F28: 68.0628 | G28: 8.6129027 | I28: 1.3369086 | K28: 63.094499
... A36: 16650 | C36: 34 | D36: 52.179108 | E36: 54.408886 | F36: 61.538235 | G36: 1.6238485 | I36: 0.24865301 | K36: 61.084333
A37: 16681 | C37: 35 | D37: 51.831835 | E37: 53.530978 | F37: 60.509572 | I37: 0.19514441 | K37: 60.750207
A38: 16711 | C38: 36 | D38: 52.803418 | E38: 52.802306 | F38: 60.023382 | I38: 0.15599073 | K38: 59.899632
A39: 16742 | C39: 37 | D39: 53.100782 | E39: 52.124686 | F39: 59.558824 | I39: 0.12463306 | K39: 59.833815
A40: 16772 | C40: 38 | D40: 53.143297 | E40: 51.435451 | F40: 58.922461 | I40: 0.096809894 | K40: 60.292035
A41: 16803 | C41: 39 | D41: 54.866092 | E41: 50.745314 | F41: 58.298665 | I41: 0.074965072 | K41: 60.286006
A42: 16834 | C42: 40 | D42: 53.73234 | E42: 50.252836 | F42: 57.584616 | I42: 0.057431297 | K42: 60.153668
A43: 16862 | C43: 41 | D43: 49.61893 | F43: 56.946812 | I43: 0.043877528 | K43: 59.836534
A44: 16893 | C44: 42 | D44: 48.962829 | F44: 56.422086 | K44: 59.497399
A45: 16923 | C45: 43 | D45: 48.19176 | F45: 56.130209 | K45: 59.354947
A46: 16954 | C46: 44 | D46: 47.251456 | F46: 55.607499 | K46: 59.450067
A47: 16984 | C47: 45 | D47: 45.715418 | F47: 53.695924 | K47: 59.587118
A48: 17015 | C48: 46 | D48: 44.444311 | F48: 51.551386 | K48: 59.219954
A49: 17046 | C49: 47 | D49: 45.565215 | F49: 49.040512 | K49: 58.913603
A50: 17076 | C50: 48 | D50: 45.096215 | F50: 48.145015 | K50: 58.80188
A51: 17107 | C51: 49 | D51: 44.526278 | F51: 47.536547 | K51: 59.258168
A52: 17137 | C52: 50 | D52: 44.66922 | F52: 46.504155 | K52: 59.856735
A53: 17168 | C53: 51 | D53: 38.244195 | F53: 45.614669 | K53: 60.254414
A54: 17199 | C54: 52 | D54: 37.04397 | F54: 44.891909 | K54: 60.242366
A55: 17227 | C55: 53 | D55: 35.818962 | F55: 44.150186 | K55: 60.508604
... A191: 21367 | C191: 189 | D191: 8.301152 | F191: 0.034178064 | K191: 31.212247
A192: 21398 | C192: 190 | D192: 8.2779737 | K192: 31.090992
A193: 21429 | C193: 191 | D193: 8.1180481 | K193: 31.022742
A194: 21459 | C194: 192 | D194: 7.9007768 | K194: 31.010338
A195: 21490 | C195: 193 | D195: 7.4416283 | K195: 30.95771
A196: 21520 | C196: 194 | D196: 7.4416283 | K196: 30.905171
A197: 21551 | C197: 195 | D197: 7.0496668 | K197: 30.742237
A198: 21582 | C198: 196 | D198: 6.7896242 | K198: 30.425809
A199: 21610 | C199: 197 | D199: 6.5190823 | K199: 30.208309
A200: 21641 | C200: 198 | D200: 6.4057014 | K200: 30.04606
A201: 21671 | C201: 199 | D201: 6.3504525 | K201: 29.704459
A202: 21702 | C202: 200 | D202: 6.2559871 | K202: 29.527295
A203: 21732 | C203: 201 | D203: 6.1641413 | K203: 29.42431
... A293: 24473 | C293: 291 | D293: 0.23847077 | K293: 19.96851
A294: 24504 | C294: 292 | K294: 19.87312
A295: 24532 | C295: 293 | K295: 19.843354
A296: 24563 | C296: 294 | K296: 19.825512
A297: 24593 | C297: 295 | K297: 19.711187
A298: 24624 | C298: 296 | K298: 19.605318
A299: 24654 | C299: 297 | K299: 19.505838
A300: 24685 | C300: 298 | K300: 19.449435
A301: 24716 | C301: 299 | K301: 19.453325
A302: 24746 | C302: 300 | K302: 19.424189
A303: 24777 | C303: 301 | K303: 19.397033
A304: 24807 | C304: 302 | K304: 19.333234
A305: 24838 | C305: 303 | K305: 19.333234
... A326: 25477 | C326: 324 | K326: 17.370595
A327: 25508
A328: 25538
A329: 25569
A330: 25600
A331: 25628
A332: 25659
A333: 25689
A334: 25720
A335: 25750
A336: 25781
A337: 25812
A338: 25842
... A946: 44348

Sheet Diferencial Inflação
A1: Data | B1: Inflação BR > US | C1: Inflação US > BR | D1: BTC | E1: =+'BRL IPCA'!R666/'BRL IPCA'!R654-1 -> #DIV/0! | F1: =+'FRED Graph CPI'!B569/100 -> 0.024948
A2: 34516 | E2: =+'BRL IPCA'!R667/'BRL IPCA'!R655-1 -> #DIV/0! | F2: =+'FRED Graph CPI'!B570/100 -> 0.0269896
A3: 34547 | E3: =+'BRL IPCA'!R668/'BRL IPCA'!R656-1 -> #DIV/0! | F3: =+'FRED Graph CPI'!B571/100 -> 0.0290055
A4: 34578 | E4: =+'BRL IPCA'!R669/'BRL IPCA'!R657-1 -> #DIV/0! | F4: =+'FRED Graph CPI'!B572/100 -> 0.0296552
A5: 34608 | E5: =+'BRL IPCA'!R670/'BRL IPCA'!R658-1 -> #DIV/0! | F5: =+'FRED Graph CPI'!B573/100 -> 0.0260989
A6: 34639 | E6: =+'BRL IPCA'!R671/'BRL IPCA'!R659-1 -> #DIV/0! | F6: =+'FRED Graph CPI'!B574/100 -> 0.0260274
A7: 34669 | E7: =+'BRL IPCA'!R672/'BRL IPCA'!R660-1 -> #DIV/0! | F7: =+'FRED Graph CPI'!B575/100 -> 0.025974
A8: 34700 | E8: =+'BRL IPCA'!R673/'BRL IPCA'!R661-1 -> #DIV/0! | F8: =+'FRED Graph CPI'!B576/100 -> 0.0287081
A9: 34731 | E9: =+'BRL IPCA'!R674/'BRL IPCA'!R662-1 -> #DIV/0! | F9: =+'FRED Graph CPI'!B577/100 -> 0.0286299
A10: 34759 | E10: =+'BRL IPCA'!R675/'BRL IPCA'!R663-1 -> #DIV/0! | F10: =+'FRED Graph CPI'!B578/100 -> 0.0278722
A11: 34790 | E11: =+'BRL IPCA'!R676/'BRL IPCA'!R664-1 -> #DIV/0! | F11: =+'FRED Graph CPI'!B579/100 -> 0.03125
A12: 34820 | E12: =+'BRL IPCA'!R677/'BRL IPCA'!R665-1 -> #DIV/0! | F12: =+'FRED Graph CPI'!B580/100 -> 0.0311864
A13: 34851 | E13: =+'BRL IPCA'!R678/'BRL IPCA'!R666-1 -> 0.3302943 | F13: =+'FRED Graph CPI'!B581/100 -> 0.030426
... A57: 36192 | E57: =+'BRL IPCA'!R722/'BRL IPCA'!R710-1 -> 0.02242513 | F57: =+'FRED Graph CPI'!B625/100 -> 0.0166667
A58: 36220 | B58: =IF(+E58-F58>=0,+E58-F58,"") -> 0.012885231 | C58: =IF(+E58-F58<0,+E58-F58,"") | E58: =+'BRL IPCA'!R723/'BRL IPCA'!R711-1 -> 0.030169231 | F58: =+'FRED Graph CPI'!B626/100 -> 0.017284
A59: 36251 | B59: =IF(+E59-F59>=0,+E59-F59,"") -> 0.01064658 | C59: =IF(+E59-F59<0,+E59-F59,"") | E59: =+'BRL IPCA'!R724/'BRL IPCA'!R712-1 -> 0.03345788 | F59: =+'FRED Graph CPI'!B627/100 -> 0.0228113
A60: 36281 | B60: =IF(+E60-F60>=0,+E60-F60,"") -> 0.010491047 | C60: =IF(+E60-F60<0,+E60-F60,"") | E60: =+'BRL IPCA'!R725/'BRL IPCA'!R713-1 -> 0.031401247 | F60: =+'FRED Graph CPI'!B628/100 -> 0.0209102
A61: 36312 | B61: =IF(+E61-F61>=0,+E61-F61,"") -> 0.013498279 | C61: =IF(+E61-F61<0,+E61-F61,"") | E61: =+'BRL IPCA'!R726/'BRL IPCA'!R714-1 -> 0.033154279 | F61: =+'FRED Graph CPI'!B629/100 -> 0.019656
A62: 36342 | B62: =IF(+E62-F62>=0,+E62-F62,"") -> 0.024224365 | C62: =IF(+E62-F62<0,+E62-F62,"") | E62: =+'BRL IPCA'!R727/'BRL IPCA'!R715-1 -> 0.045670465 | F62: =+'FRED Graph CPI'!B630/100 -> 0.0214461
A63: 36373 | B63: =IF(+E63-F63>=0,+E63-F63,"") -> 0.034272694 | C63: =IF(+E63-F63<0,+E63-F63,"") | E63: =+'BRL IPCA'!R728/'BRL IPCA'!R716-1 -> 0.056916494 | F63: =+'FRED Graph CPI'!B631/100 -> 0.0226438
A64: 36404 | B64: =IF(+E64-F64>=0,+E64-F64,"") -> 0.036230802 | C64: =IF(+E64-F64<0,+E64-F64,"") | E64: =+'BRL IPCA'!R729/'BRL IPCA'!R717-1 -> 0.062530502 | F64: =+'FRED Graph CPI'!B632/100 -> 0.0262997
A65: 36434 | B65: =IF(+E65-F65>=0,+E65-F65,"") -> 0.049334223 | C65: =IF(+E65-F65<0,+E65-F65,"") | E65: =+'BRL IPCA'!R730/'BRL IPCA'!R718-1 -> 0.074959623 | F65: =+'FRED Graph CPI'!B633/100 -> 0.0256254
A66: 36465 | B66: =IF(+E66-F66>=0,+E66-F66,"") -> 0.06027201 | C66: =IF(+E66-F66<0,+E66-F66,"") | E66: =+'BRL IPCA'!R731/'BRL IPCA'!R719-1 -> 0.08647551 | F66: =+'FRED Graph CPI'!B634/100 -> 0.0262035
A67: 36495 | B67: =IF(+E67-F67>=0,+E67-F67,"") -> 0.062635345 | C67: =IF(+E67-F67<0,+E67-F67,"") | E67: =+'BRL IPCA'!R732/'BRL IPCA'!R720-1 -> 0.089399345 | F67: =+'FRED Graph CPI'!B635/100 -> 0.026764
A68: 36526 | B68: =IF(+E68-F68>=0,+E68-F68,"") -> 0.060604284 | C68: =IF(+E68-F68<0,+E68-F68,"") | E68: =+'BRL IPCA'!R733/'BRL IPCA'!R721-1 -> 0.088533884 | F68: =+'FRED Graph CPI'!B636/100 -> 0.0279296
A69: 36557 | B69: =IF(+E69-F69>=0,+E69-F69,"") -> 0.046443732 | C69: =IF(+E69-F69<0,+E69-F69,"") | E69: =+'BRL IPCA'!R734/'BRL IPCA'!R722-1 -> 0.078623432 | F69: =+'FRED Graph CPI'!B637/100 -> 0.0321797
... A364: 45536 | B364: =IF(+E364-F364>=0,+E364-F364,"") -> 0.019982601 | C364: =IF(+E364-F364<0,+E364-F364,"") | E364: =+'BRL IPCA'!R1029/'BRL IPCA'!R1017-1 -> 0.044247401 | F364: =+'FRED Graph CPI'!B932/100 -> 0.0242648
A365: 45566 | B365: =IF(+E365-F365>=0,+E365-F365,"") -> 0.021792592 | E365: =+'BRL IPCA'!R1030/'BRL IPCA'!R1018-1 -> 0.047580992 | F365: =+'FRED Graph CPI'!B933/100 -> 0.0257884
A366: 45597 | B366: =IF(+E366-F366>=0,+E366-F366,"") -> 0.021535414 | E366: =+'BRL IPCA'!R1031/'BRL IPCA'!R1019-1 -> 0.048730114 | F366: =+'FRED Graph CPI'!B934/100 -> 0.0271947
A367: 45627 | B367: =IF(+E367-F367>=0,+E367-F367,"") -> 0.019606058 | E367: =+'BRL IPCA'!R1032/'BRL IPCA'!R1020-1 -> 0.048312958 | F367: =+'FRED Graph CPI'!B935/100 -> 0.0287069
A368: 45658 | B368: =IF(+E368-F368>=0,+E368-F368,"") -> 0.015688944 | E368: =+'BRL IPCA'!R1033/'BRL IPCA'!R1021-1 -> 0.045598744 | F368: =+'FRED Graph CPI'!B936/100 -> 0.0299098
A369: 45689 | B369: =IF(+E369-F369>=0,+E369-F369,"") -> 0.022560504 | E369: =+'BRL IPCA'!R1034/'BRL IPCA'!R1022-1 -> 0.050576304 | F369: =+'FRED Graph CPI'!B937/100 -> 0.0280158
A370: 45717 | B370: =IF(+E370-F370>=0,+E370-F370,"") -> 0.030952096 | E370: =+'BRL IPCA'!R1035/'BRL IPCA'!R1023-1 -> 0.054771896 | F370: =+'FRED Graph CPI'!B938/100 -> 0.0238198
A371: 45748 | B371: =IF(+E371-F371>=0,+E371-F371,"") -> 0.032043386 | E371: =+'BRL IPCA'!R1036/'BRL IPCA'!R1024-1 -> 0.055297286 | F371: =+'FRED Graph CPI'!B939/100 -> 0.0232539
A372: 45778 | B372: =IF(+E372-F372>=0,+E372-F372,"") -> 0.029423656 | E372: =+'BRL IPCA'!R1037/'BRL IPCA'!R1025-1 -> 0.053196356 | F372: =+'FRED Graph CPI'!B940/100 -> 0.0237727
A373: 45809 | B373: =IF(+E373-F373>=0,+E373-F373,"") -> 0.026707152 | E373: =+'BRL IPCA'!R1038/'BRL IPCA'!R1026-1 -> 0.053511652 | F373: =+'FRED Graph CPI'!B941/100 -> 0.0268045
A374: 45839 | B374: =IF(+E374-F374>=0,+E374-F374,"") -> 0.024826024 | E374: =+'BRL IPCA'!R1039/'BRL IPCA'!R1027-1 -> 0.052252224 | F374: =+'FRED Graph CPI'!B942/100 -> 0.0274262
A375: 45870 | B375: =IF(+E375-F375>=0,+E375-F375,"") -> 0.021919108 | E375: =+'BRL IPCA'!R1040/'BRL IPCA'!R1028-1 -> 0.051305008 | F375: =+'FRED Graph CPI'!B943/100 -> 0.0293859
A376: 45901 | B376: =IF(+E376-F376>=0,+E376-F376,"") -> 0.021497988 | E376: =+'BRL IPCA'!R1041/'BRL IPCA'!R1029-1 -> 0.051723688 | F376: =+'FRED Graph CPI'!B944/100 -> 0.0302257
A377: 45962 | B377: =IF(+E377-F377>=0,+E377-F377,"") -> 0.017653956 | E377: =+'BRL IPCA'!R1043/'BRL IPCA'!R1031-1 -> 0.044618356 | F377: =+'FRED Graph CPI'!B946/100 -> 0.0269644
A378: 45992 | B378: =IF(+E378-F378>=0,+E378-F378,"") -> 0.016110849 | E378: =+'BRL IPCA'!R1044/'BRL IPCA'!R1032-1 -> 0.042643849 | F378: =+'FRED Graph CPI'!B947/100 -> 0.026533
A379: 46023 | B379: =IF(+E379-F379>=0,+E379-F379,"") -> 0.020501512 | E379: =+'BRL IPCA'!R1045/'BRL IPCA'!R1033-1 -> 0.044413512 | F379: =+'FRED Graph CPI'!B948/100 -> 0.023912
A380: 46054 | B380: =IF(+E380-F380>=0,+E380-F380,"") -> 0.01378497 | E380: =+'BRL IPCA'!R1046/'BRL IPCA'!R1034-1 -> 0.03812497 | F380: =+'FRED Graph CPI'!B949/100 -> 0.02434
A381: 46082 | B381: =IF(+E381-F381>=0,+E381-F381,"") -> 0.0085688699 | E381: =+'BRL IPCA'!R1047/'BRL IPCA'!R1035-1 -> 0.04142847 | F381: =+'FRED Graph CPI'!B950/100 -> 0.0328596
E977: 1

Sheet FRED Graph CPI
A1: FRED Graph Observations
A2: Federal Reserve Economic Data
A3: Link: https://fred.stlouisfed.org
A4: Help: https://fredhelp.stlouisfed.org
A5: Economic Research Division
A6: Federal Reserve Bank of St. Louis
A8: CPIAUCSL_PC1 | B8: Consumer Price Index for All Urban Consumers: All Items in U.S. City Average, Percent Change from Year Ago, Monthly, Seasonally Adjusted
A10: Frequency: Monthly
A11: observation_date | B11: CPIAUCSL_PC1
A12: 17533 | B12: 10.24209
A13: 17564 | B13: 9.48196
A14: 17593 | B14: 6.81818
A15: 17624 | B15: 8.27273
A16: 17654 | B16: 9.38497
A17: 17685 | B17: 9.375
A18: 17715 | B18: 9.76158
A19: 17746 | B19: 9.0625
A20: 17777 | B20: 6.65499
A21: 17807 | B21: 6.11087
A22: 17838 | B22: 4.77016
A23: 17868 | B23: 2.73387
... A944: 45901 | B944: 3.02257
A945: 45931
A946: 45962 | B946: 2.69644
A947: 45992 | B947: 2.6533
A948: 46023 | B948: 2.3912
A949: 46054 | B949: 2.434
A950: 46082 | B950: 3.28596

Sheet 1_FX_IDC_USDBRL, M
A1: time | B1: close | C1: BRTOT · FUNCEX: Close
A2: 1990-12-31T20:00:00-02:00 | B2: 10000 | C2: 66.38
A3: 1991-01-31T20:00:00-02:00 | B3: 10000 | C3: 65.75
A4: 1991-02-28T19:00:00-03:00 | B4: 10000 | C4: 71.86
A5: 1991-03-31T19:00:00-03:00 | B5: 10000 | C5: 73.15
A6: 1991-04-30T19:00:00-03:00 | B6: 10000 | C6: 73.19
A7: 1991-06-02T19:00:00-03:00 | B7: 10000 | C7: 72.46
A8: 1991-06-30T19:00:00-03:00 | B8: 10000 | C8: 75.9
A9: 1991-07-31T19:00:00-03:00 | B9: 5000 | C9: 77.43
A10: 1991-09-01T19:00:00-03:00 | B10: 5000 | C10: 75.36
A11: 1991-09-30T19:00:00-03:00 | B11: 3333.3333 | C11: 74.38
A12: 1991-10-31T20:00:00-02:00 | B12: 3333.3333 | C12: 71.17
A13: 1991-12-01T20:00:00-02:00 | B13: 2500 | C13: 69.08
... A392: 2023-07-02T19:00:00-03:00 | B392: 0.21168949 | C392: 107.77
A393: 2023-07-31T19:00:00-03:00 | B393: 0.20187339 | C393: NaN
A394: 2023-08-31T19:00:00-03:00 | B394: 0.19872814 | C394: NaN
A395: 2023-10-01T19:00:00-03:00 | B395: 0.19846783 | C395: NaN

Sheet Termos de Troca
A1: Data | C1: Mês | D1: BRLUSD (esq.) | E1: Termos de Troca | F1: Termos de Troca (FUNCEX, dir.) | G1: Cruzado (fev-86 a jan-89) | H1: Cruzado Novo (jan-89 a mar-90) | I1: Cruzeiro (mar-90 a ago/93) | J1: Cruzeiro real (ago/93 a jun-94) | K1: Real (jul/94 a jun-21)
A2: 15615 | C2: 34486 | D2: ='ECONOMICS_BRTOT, 1D'!C195 -> 0 | E2: =+'ECONOMICS_BRTOT, 1D'!B195 -> 83.92 | F2: =+E2 -> 83.92 | G2: 100 | H2: 100 | I2: 100 | J2: 100 | K2: 100
A3: 15646 | C3: 34516 | D3: ='ECONOMICS_BRTOT, 1D'!C196 -> 0 | E3: =+'ECONOMICS_BRTOT, 1D'!B196 -> 81.75 | F3: =+E3 -> 81.75 | G3: 98.202887 | H3: 87.711604 | I3: 83.201597 | J3: 74.560095 | K3: 93.501636 | P3: =5.2/4.9-1 -> 0.06122449
A4: 15676 | C4: 34547 | D4: ='ECONOMICS_BRTOT, 1D'!C197 -> 0 | E4: =+'ECONOMICS_BRTOT, 1D'!B197 -> 81.8 | F4: =+E4 -> 81.8 | G4: 95.985619 | H4: 82.389258 | I4: 76.662303 | J4: 55.135765 | K4: 91.713228
A5: 15707 | C5: 34578 | D5: ='ECONOMICS_BRTOT, 1D'!C198 -> 0 | E5: =+'ECONOMICS_BRTOT, 1D'!B198 -> 80.74 | F5: =+E5 -> 80.74 | G5: 94.177413 | H5: 74.88571 | I5: 68.632321 | J5: 40.588755 | K5: 90.967296
A6: 15738 | C6: 34608 | D6: ='ECONOMICS_BRTOT, 1D'!C199 -> 0 | E6: =+'ECONOMICS_BRTOT, 1D'!B199 -> 83.4 | F6: =+E6 -> 83.4 | G6: 93.281907 | H6: 64.22996 | I6: 61.65872 | J6: 29.301729 | K6: 88.172237
A7: 15766 | C7: 34639 | D7: ='ECONOMICS_BRTOT, 1D'!C200 -> 0 | E7: =+'ECONOMICS_BRTOT, 1D'!B200 -> 81.47 | F7: =+E7 -> 81.47 | G7: 92.294357 | H7: 51.265033 | I7: 55.136117 | J7: 20.885053 | K7: 85.587494
A8: 15797 | C8: 34669 | D8: ='ECONOMICS_BRTOT, 1D'!C201 -> 0 | E8: =+'ECONOMICS_BRTOT, 1D'!B201 -> 83.31 | F8: =+E8 -> 83.31 | G8: 90.591242 | H8: 40.032042 | I8: 48.736955 | J8: 15.113288 | K8: 84.530859
A9: 15827 | C9: 34700 | D9: ='ECONOMICS_BRTOT, 1D'!C202 -> 0 | E9: =+'ECONOMICS_BRTOT, 1D'!B202 -> 86.27 | F9: =+E9 -> 86.27 | G9: 89.314051 | H9: 30.570479 | I9: 42.07628 | J9: 10.64766 | K9: 83.859979
A10: 15858 | C10: 34731 | D10: ='ECONOMICS_BRTOT, 1D'!C203 -> 0 | E10: =+'ECONOMICS_BRTOT, 1D'!B203 -> 90.75 | F10: =+E10 -> 90.75 | G10: 86.645373 | H10: 22.506426 | I10: 35.48944 | J10: 7.2819448 | K10: 82.767448
A11: 15888 | C11: 34759 | D11: ='ECONOMICS_BRTOT, 1D'!C204 -> 0 | E11: =+'ECONOMICS_BRTOT, 1D'!B204 -> 93.5 | F11: =+E11 -> 93.5 | G11: 82.969811 | H11: 16.393347 | I11: 30.586435 | J11: 5.0185698 | K11: 81.20825
A12: 15919 | C12: 34790 | D12: ='ECONOMICS_BRTOT, 1D'!C205 -> 0 | E12: =+'ECONOMICS_BRTOT, 1D'!B205 -> 91.53 | F12: =+E12 -> 91.53 | G12: 75.22195 | H12: 11.467087 | I12: 25.273868 | J12: 3.3290679 | K12: 79.119495
A13: 15950 | C13: 34820 | D13: ='ECONOMICS_BRTOT, 1D'!C206 -> 0 | E13: =+'ECONOMICS_BRTOT, 1D'!B206 -> 92.37 | F13: =+E13 -> 92.37 | G13: 66.129187 | H13: 7.5530804 | I13: 20.967204 | K13: 77.590954
A14: 15980 | C14: 34851 | D14: ='ECONOMICS_BRTOT, 1D'!C207 -> 0 | E14: =+'ECONOMICS_BRTOT, 1D'!B207 -> 97.4 | F14: =+E14 -> 97.4 | G14: 59.425941 | H14: 4.3276688 | I14: 19.508005 | K14: 75.580512
A15: 16011 | C15: 34881 | D15: ='ECONOMICS_BRTOT, 1D'!C208 -> 0 | E15: =+'ECONOMICS_BRTOT, 1D'!B208 -> 94.19 | F15: =+E15 -> 94.19 | G15: 53.073092 | H15: 2.5432939 | I15: 18.199464 | K15: 72.869757
A16: 16041 | C16: 34912 | D16: ='ECONOMICS_BRTOT, 1D'!C209 -> 0 | E16: =+'ECONOMICS_BRTOT, 1D'!B209 -> 91.84 | F16: =+E16 -> 91.84 | G16: 45.536758 | H16: 1.419962 | I16: 17.208267 | K16: 71.84241
A17: 16072 | C17: 34943 | D17: ='ECONOMICS_BRTOT, 1D'!C210 -> 0 | E17: =+'ECONOMICS_BRTOT, 1D'!B210 -> 91.52 | F17: =+E17 -> 91.52 | G17: 36.000283 | I17: 15.67523 | K17: 71.314682
A18: 16103 | C18: 34973 | D18: ='ECONOMICS_BRTOT, 1D'!C211 -> 0 | E18: =+'ECONOMICS_BRTOT, 1D'!B211 -> 95.81 | F18: =+E18 -> 95.81 | G18: 28.40035 | I18: 14.083765 | K18: 70.274617
A19: 16132 | C19: 35004 | D19: ='ECONOMICS_BRTOT, 1D'!C212 -> 0 | E19: =+'ECONOMICS_BRTOT, 1D'!B212 -> 93.98 | F19: =+E19 -> 93.98 | G19: 25.998123 | I19: 12.308831 | K19: 69.461913
A20: 16163 | C20: 35034 | D20: ='ECONOMICS_BRTOT, 1D'!C213 -> 0 | E20: =+'ECONOMICS_BRTOT, 1D'!B213 -> 95.88 | F20: =+E20 -> 95.88 | G20: 24.890496 | I20: 10.591886 | K20: 68.631472
A21: 16193 | C21: 35065 | D21: ='ECONOMICS_BRTOT, 1D'!C214 -> 0 | E21: =+'ECONOMICS_BRTOT, 1D'!B214 -> 95.71 | F21: =+E21 -> 95.71 | G21: 23.320993 | I21: 8.4620008 | K21: 67.404707
A22: 16224 | C22: 35096 | D22: ='ECONOMICS_BRTOT, 1D'!C215 -> 0 | E22: =+'ECONOMICS_BRTOT, 1D'!B215 -> 95.12 | F22: =+E22 -> 95.12 | G22: 21.168188 | I22: 6.7485452 | K22: 67.136162
A23: 16254 | C23: 35125 | D23: ='ECONOMICS_BRTOT, 1D'!C216 -> 0 | E23: =+'ECONOMICS_BRTOT, 1D'!B216 -> 95.79 | F23: =+E23 -> 95.79 | G23: 18.666833 | I23: 5.475493 | K23: 66.982103
A24: 16285 | C24: 35156 | D24: ='ECONOMICS_BRTOT, 1D'!C217 -> 0 | E24: =+'ECONOMICS_BRTOT, 1D'!B217 -> 93.64 | F24: =+E24 -> 93.64 | G24: 16.103203 | I24: 4.3494265 | K24: 65.914292
A25: 16316 | C25: 35186 | D25: ='ECONOMICS_BRTOT, 1D'!C218 -> 0 | E25: =+'ECONOMICS_BRTOT, 1D'!B218 -> 91.54 | F25: =+E25 -> 91.54 | G25: 14.03941 | I25: 3.5777137 | K25: 65.042719
A26: 16346 | C26: 35217 | D26: ='ECONOMICS_BRTOT, 1D'!C219 -> 0 | E26: =+'ECONOMICS_BRTOT, 1D'!B219 -> 89.84 | F26: =+E26 -> 89.84 | G26: 12.382616 | I26: 2.9388152 | K26: 64.138368
A27: 16377 | C27: 35247 | D27: ='ECONOMICS_BRTOT, 1D'!C220 -> 0 | E27: =+'ECONOMICS_BRTOT, 1D'!B220 -> 91.45 | F27: =+E27 -> 91.45 | G27: 10.436254 | I27: 2.394537 | K27: 63.30902
A28: 16407 | C28: 35278 | D28: ='ECONOMICS_BRTOT, 1D'!C221 -> 0 | E28: =+'ECONOMICS_BRTOT, 1D'!B221 -> 92.27 | F28: =+E28 -> 92.27 | G28: 8.6129027 | I28: 1.9542455 | K28: 63.094499
... A37: 16681 | C37: 35551 | D37: ='ECONOMICS_BRTOT, 1D'!C230 -> 0 | E37: =+'ECONOMICS_BRTOT, 1D'!B230 -> 93.66 | F37: =+E37 -> 93.66 | G37: 1.238539 | I37: 0.27939501 | K37: 60.750207
A38: 16711 | C38: 35582 | D38: ='ECONOMICS_BRTOT, 1D'!C231 -> 0 | E38: =+'ECONOMICS_BRTOT, 1D'!B231 -> 94.96 | F38: =+E38 -> 94.96 | I38: 0.22323027 | K38: 59.899632
A39: 16742 | C39: 35612 | D39: ='ECONOMICS_BRTOT, 1D'!C232 -> 0 | E39: =+'ECONOMICS_BRTOT, 1D'!B232 -> 96.77 | F39: =+E39 -> 96.77 | I39: 0.1733962 | K39: 59.833815
A40: 16772 | C40: 35643 | D40: ='ECONOMICS_BRTOT, 1D'!C233 -> 0 | E40: =+'ECONOMICS_BRTOT, 1D'!B233 -> 96.37 | F40: =+E40 -> 96.37 | I40: 0.13426994 | K40: 60.292035
A41: 16803 | C41: 35674 | D41: ='ECONOMICS_BRTOT, 1D'!C234 -> 0 | E41: =+'ECONOMICS_BRTOT, 1D'!B234 -> 101.43 | F41: =+E41 -> 101.43 | I41: 0.1028652 | K41: 60.286006
A42: 16834 | C42: 35704 | D42: ='ECONOMICS_BRTOT, 1D'!C235 -> 0 | E42: =+'ECONOMICS_BRTOT, 1D'!B235 -> 99.23 | F42: =+E42 -> 99.23 | I42: 0.078589041 | K42: 60.153668
A43: 16862 | C43: 35735 | D43: ='ECONOMICS_BRTOT, 1D'!C236 -> 0 | E43: =+'ECONOMICS_BRTOT, 1D'!B236 -> 100.11 | F43: =+E43 -> 100.11 | I43: 0.058661671 | K43: 59.836534
A44: 16893 | C44: 35765 | D44: ='ECONOMICS_BRTOT, 1D'!C237 -> 0 | E44: =+'ECONOMICS_BRTOT, 1D'!B237 -> 100.35 | F44: =+E44 -> 100.35 | K44: 59.497399
A45: 16923 | C45: 35796 | D45: ='ECONOMICS_BRTOT, 1D'!C238 -> 0 | E45: =+'ECONOMICS_BRTOT, 1D'!B238 -> 100.75 | F45: =+E45 -> 100.75 | K45: 59.354947
A46: 16954 | C46: 35827 | D46: ='ECONOMICS_BRTOT, 1D'!C239 -> 0 | E46: =+'ECONOMICS_BRTOT, 1D'!B239 -> 97.91 | F46: =+E46 -> 97.91 | K46: 59.450067
A47: 16984 | C47: 35855 | D47: ='ECONOMICS_BRTOT, 1D'!C240 -> 0 | E47: =+'ECONOMICS_BRTOT, 1D'!B240 -> 98.93 | F47: =+E47 -> 98.93 | K47: 59.587118
A48: 17015 | C48: 35886 | D48: ='ECONOMICS_BRTOT, 1D'!C241 -> 0 | E48: =+'ECONOMICS_BRTOT, 1D'!B241 -> 97.03 | F48: =+E48 -> 97.03 | K48: 59.219954
A49: 17046 | C49: 35916 | D49: ='ECONOMICS_BRTOT, 1D'!C242 -> 0 | E49: =+'ECONOMICS_BRTOT, 1D'!B242 -> 100.23 | F49: =+E49 -> 100.23 | K49: 58.913603
A50: 17076 | C50: 35947 | D50: ='ECONOMICS_BRTOT, 1D'!C243 -> 0 | E50: =+'ECONOMICS_BRTOT, 1D'!B243 -> 99.26 | F50: =+E50 -> 99.26 | K50: 58.80188
A51: 17107 | C51: 35977 | D51: ='ECONOMICS_BRTOT, 1D'!C244 -> 0 | E51: =+'ECONOMICS_BRTOT, 1D'!B244 -> 99.78 | F51: =+E51 -> 99.78 | K51: 59.258168
A52: 17137 | C52: 36008 | D52: ='ECONOMICS_BRTOT, 1D'!C245 -> 0 | E52: =+'ECONOMICS_BRTOT, 1D'!B245 -> 98.82 | F52: =+E52 -> 98.82 | K52: 59.856735
A53: 17168 | C53: 36039 | D53: ='ECONOMICS_BRTOT, 1D'!C246 -> 0 | E53: =+'ECONOMICS_BRTOT, 1D'!B246 -> 96.94 | F53: =+E53 -> 96.94 | K53: 60.254414
A54: 17199 | C54: 36069 | D54: ='ECONOMICS_BRTOT, 1D'!C247 -> 0 | E54: =+'ECONOMICS_BRTOT, 1D'!B247 -> 98.24 | F54: =+E54 -> 98.24 | K54: 60.242366
A55: 17227 | C55: 36100 | D55: ='ECONOMICS_BRTOT, 1D'!C248 -> 0 | E55: =+'ECONOMICS_BRTOT, 1D'!B248 -> 97.04 | F55: =+E55 -> 97.04 | K55: 60.508604
... A326: 25477 | C326: 44348 | D326: ='ECONOMICS_BRTOT, 1D'!C519 -> 0.1782 | E326: =+'ECONOMICS_BRTOT, 1D'!B519 -> 120.33 | F326: =+E326 -> 120.33 | K326: 17.370595
A327: 25508 | C327: 44378 | D327: ='ECONOMICS_BRTOT, 1D'!C520 -> 0.1772 | E327: =+'ECONOMICS_BRTOT, 1D'!B520 -> 118.89 | F327: =+E327 -> 118.89
A328: 25538 | C328: 44409 | D328: ='ECONOMICS_BRTOT, 1D'!C521 -> 0.1835 | E328: =+'ECONOMICS_BRTOT, 1D'!B521 -> 116.07 | F328: =+E328 -> 116.07 | S328: 4.93
A329: 25569 | C329: 44440 | D329: ='ECONOMICS_BRTOT, 1D'!C522 -> 0.1912 | E329: =+'ECONOMICS_BRTOT, 1D'!B522 -> 117.42 | F329: =+E329 -> 117.42 | H329: 7.6 | I329: =+H329/F329*100 -> 6.4724919 | S329: =+F334/S328-1 -> 21.572008
A330: 25600 | C330: 44470 | D330: ='ECONOMICS_BRTOT, 1D'!C523 -> 0.2008 | E330: =+'ECONOMICS_BRTOT, 1D'!B523 -> 122.43 | F330: =+E330 -> 122.43
A331: 25628 | C331: 44501 | D331: ='ECONOMICS_BRTOT, 1D'!C524 -> 0.1916 | E331: =+'ECONOMICS_BRTOT, 1D'!B524 -> 121.43 | F331: =+E331 -> 121.43 | N331: 5.15
A332: 25659 | C332: 44531 | D332: ='ECONOMICS_BRTOT, 1D'!C525 -> 0.1938 | E332: =+'ECONOMICS_BRTOT, 1D'!B525 -> 117.69 | F332: =+E332 -> 117.69 | N332: =+F334/N331-1 -> 20.607767
A333: 25689 | C333: 44562 | D333: ='ECONOMICS_BRTOT, 1D'!C526 -> 0.1833 | E333: =+'ECONOMICS_BRTOT, 1D'!B526 -> 114.22 | F333: =+E333 -> 114.22
A334: 25720 | C334: 44593 | D334: ='ECONOMICS_BRTOT, 1D'!C527 -> 0.177 | E334: =+'ECONOMICS_BRTOT, 1D'!B527 -> 111.28 | F334: =+E334 -> 111.28 | H334: 11
A335: 25750 | C335: 44621 | D335: ='ECONOMICS_BRTOT, 1D'!C528 -> 0.1774 | E335: =+'ECONOMICS_BRTOT, 1D'!B528 -> 104.54 | F335: =+E335 -> 104.54
A336: 25781 | C336: 44652 | D336: ='ECONOMICS_BRTOT, 1D'!C529 -> 0.1791 | E336: =+'ECONOMICS_BRTOT, 1D'!B529 -> 104.23 | F336: =+E336 -> 104.23
A337: 25812 | C337: 44682 | D337: ='ECONOMICS_BRTOT, 1D'!C530 -> 0.1881 | E337: =+'ECONOMICS_BRTOT, 1D'!B530 -> 104.98 | F337: =+E337 -> 104.98
A338: 25842 | C338: 44713 | D338: ='ECONOMICS_BRTOT, 1D'!C531 -> 0.1934 | E338: =+'ECONOMICS_BRTOT, 1D'!B531 -> 106.53 | F338: =+E338 -> 106.53
A339: 25873 | C339: 44743 | D339: ='ECONOMICS_BRTOT, 1D'!C532 -> 0.2106 | E339: =+'ECONOMICS_BRTOT, 1D'!B532 -> 109.76 | F339: =+E339 -> 109.76
A340: 25903 | C340: 44774 | D340: ='ECONOMICS_BRTOT, 1D'!C533 -> 0.2007 | E340: =+'ECONOMICS_BRTOT, 1D'!B533 -> 106.49 | F340: =+E340 -> 106.49
A341: 25934 | C341: 44805 | D341: ='ECONOMICS_BRTOT, 1D'!C534 -> 0.2109 | E341: =+'ECONOMICS_BRTOT, 1D'!B534 -> 106.62 | F341: =+E341 -> 106.62
A342: 25965 | C342: 44835 | D342: ='ECONOMICS_BRTOT, 1D'!C535 -> 0.1899 | E342: =+'ECONOMICS_BRTOT, 1D'!B535 -> 106.71 | F342: =+E342 -> 106.71
A343: 25993 | C343: 44866 | D343: ='ECONOMICS_BRTOT, 1D'!C536 -> 0.1929 | E343: =+'ECONOMICS_BRTOT, 1D'!B536 -> 109.94 | F343: =+E343 -> 109.94
A344: 26024 | C344: 44896 | D344: ='ECONOMICS_BRTOT, 1D'!C537 -> 0.1925 | E344: =+'ECONOMICS_BRTOT, 1D'!B537 -> 106.85 | F344: =+E344 -> 106.85
A345: 26054 | C345: 44927 | D345: ='ECONOMICS_BRTOT, 1D'!C538 -> 0.1844 | E345: =+'ECONOMICS_BRTOT, 1D'!B538 -> 107.6 | F345: =+E345 -> 107.6
A346: 26085 | C346: 44958 | D346: ='ECONOMICS_BRTOT, 1D'!C539 -> 0.1927 | E346: =+'ECONOMICS_BRTOT, 1D'!B539 -> 107.69 | F346: =+E346 -> 107.69
... A383: 27211 | C383: 46082 | D383: ='ECONOMICS_BRTOT, 1D'!C576 -> 0.1922 | E383: =+'ECONOMICS_BRTOT, 1D'!B576 -> 125 | F383: =+E383 -> 125
A384: 27242
A385: 27273
A386: 27303
A387: 27334
A388: 27364
A389: 27395
A390: 27426
A391: 27454
A392: 27485
A393: 27515
A394: 27546
A395: 27576
... A946: 44348

Sheet ECONOMICS_BRTOT, 1D
A1: time | B1: close | C1: BRLUSD · ICE: close
A2: 28491 | B2: 110.82
A3: 28522 | B3: 106.1
A4: 28550 | B4: 105.06
A5: 28581 | B5: 103.59
A6: 28611 | B6: 101.19
A7: 28642 | B7: 91.95
A8: 28672 | B8: 100.18
A9: 28703 | B9: 101.78
A10: 28734 | B10: 98.86
A11: 28764 | B11: 98.51
A12: 28795 | B12: 98.49
A13: 28825 | B13: 96.35
... A304: 37681 | B304: 83.66
A305: 37712 | B305: 83.82 | C305: 0.3436
A306: 37742 | B306: 84.72 | C306: 0.3379
A307: 37773 | B307: 85.79 | C307: 0.3518
A308: 37803 | B308: 86.12 | C308: 0.3372
A309: 37834 | B309: 84.57 | C309: 0.3357
A310: 37865 | B310: 84.9 | C310: 0.3454
A311: 37895 | B311: 86.73 | C311: 0.3488
A312: 37926 | B312: 85.56 | C312: 0.3394
A313: 37956 | B313: 85.72 | C313: 0.3463
A314: 37987 | B314: 87.28 | C314: 0.3412
A315: 38018 | B315: 85.21 | C315: 0.3445
A316: 38047 | B316: 86.13 | C316: 0.3453
... A576: 46082 | B576: 125 | C576: 0.1922

Sheet BRL PP Chart desde 2019
A1: Data | C1: Mês | D1: Real (jan/19 a dez/24) | E1: Real (jan/19 a dez/24) | F1: Taxa de Inflação Mensal | G1: Taxa de Inflação Mensal | H1: Taxa de Inflação Anual | I1: Taxa de Inflação Anual
A2: 15615 | C2: 34486 | D2: =+'BRL e USD Chart'!$D2 -> 100 | E2: =+'BRL e USD Chart'!$D2 -> 100
A3: 15646 | C3: 34516 | D3: =+'BRL e USD Chart'!$D3 -> 93.597903 | E3: =+'BRL e USD Chart'!$D3 -> 93.597903 | F3: =+E3/E2-1 -> -0.064020966 | G3: =+F3 -> -0.064020966
A4: 15676 | C4: 34547 | D4: =+'BRL e USD Chart'!$D4 -> 91.888772 | E4: =+'BRL e USD Chart'!$D4 -> 91.888772 | F4: =+E4/E3-1 -> -0.018260357 | G4: =+F4 -> -0.018260357
A5: 15707 | C5: 34578 | D5: =+'BRL e USD Chart'!$D5 -> 90.50406 | E5: =+'BRL e USD Chart'!$D5 -> 90.50406 | F5: =+E5/E4-1 -> -0.015069438 | G5: =+F5 -> -0.015069438
A6: 15738 | C6: 34608 | D6: =+'BRL e USD Chart'!$D6 -> 88.193393 | E6: =+'BRL e USD Chart'!$D6 -> 88.193393 | F6: =+E6/E5-1 -> -0.025531086 | G6: =+F6 -> -0.025531086
A7: 15766 | C7: 34639 | D7: =+'BRL e USD Chart'!$D7 -> 85.782894 | E7: =+'BRL e USD Chart'!$D7 -> 85.782894 | F7: =+E7/E6-1 -> -0.027331972 | G7: =+F7 -> -0.027331972
A8: 15797 | C8: 34669 | D8: =+'BRL e USD Chart'!$D8 -> 84.340668 | E8: =+'BRL e USD Chart'!$D8 -> 84.340668 | F8: =+E8/E7-1 -> -0.016812506 | G8: =+F8 -> -0.016812506
A9: 15827 | C9: 34700 | D9: =+'BRL e USD Chart'!$D9 -> 82.930844 | E9: =+'BRL e USD Chart'!$D9 -> 82.930844 | F9: =+E9/E8-1 -> -0.016715831 | G9: =+F9 -> -0.016715831
A10: 15858 | C10: 34731 | D10: =+'BRL e USD Chart'!$D10 -> 82.093491 | E10: =+'BRL e USD Chart'!$D10 -> 82.093491 | F10: =+E10/E9-1 -> -0.01009701 | G10: =+F10 -> -0.01009701
A11: 15888 | C11: 34759 | D11: =+'BRL e USD Chart'!$D11 -> 80.840463 | E11: =+'BRL e USD Chart'!$D11 -> 80.840463 | F11: =+E11/E10-1 -> -0.015263417 | G11: =+F11 -> -0.015263417
A12: 15919 | C12: 34790 | D12: =+'BRL e USD Chart'!$D12 -> 78.922643 | E12: =+'BRL e USD Chart'!$D12 -> 78.922643 | F12: =+E12/E11-1 -> -0.023723519 | G12: =+F12 -> -0.023723519
A13: 15950 | C13: 34820 | D13: =+'BRL e USD Chart'!$D13 -> 76.870209 | E13: =+'BRL e USD Chart'!$D13 -> 76.870209 | F13: =+E13/E12-1 -> -0.026005649 | G13: =+F13 -> -0.026005649
A14: 15980 | C14: 34851 | D14: =+'BRL e USD Chart'!$D14 -> 75.171336 | E14: =+'BRL e USD Chart'!$D14 -> 75.171336 | F14: =+E14/E13-1 -> -0.022100528 | G14: =+F14 -> -0.022100528 | H14: =+E14/E2-1 -> -0.24828664 | I14: =+H14 -> -0.24828664
A15: 16011 | C15: 34881 | D15: =+'BRL e USD Chart'!$D15 -> 73.438195 | E15: =+'BRL e USD Chart'!$D15 -> 73.438195 | F15: =+E15/E14-1 -> -0.023055881 | G15: =+F15 -> -0.023055881 | H15: =+E15/E3-1 -> -0.21538633 | I15: =+H15 -> -0.21538633
A16: 16041 | C16: 34912 | D16: =+'BRL e USD Chart'!$D16 -> 72.718284 | E16: =+'BRL e USD Chart'!$D16 -> 72.718284 | F16: =+E16/E15-1 -> -0.0098029508 | G16: =+F16 -> -0.0098029508 | H16: =+E16/E4-1 -> -0.2086271 | I16: =+H16 -> -0.2086271
A17: 16072 | C17: 34943 | D17: =+'BRL e USD Chart'!$D17 -> 72.00543 | E17: =+'BRL e USD Chart'!$D17 -> 72.00543 | F17: =+E17/E16-1 -> -0.0098029508 | G17: =+F17 -> -0.0098029508 | H17: =+E17/E5-1 -> -0.20439558 | I17: =+H17 -> -0.20439558
A18: 16103 | C18: 34973 | D18: =+'BRL e USD Chart'!$D18 -> 71.00427 | E18: =+'BRL e USD Chart'!$D18 -> 71.00427 | F18: =+E18/E17-1 -> -0.013903954 | G18: =+F18 -> -0.013903954 | H18: =+E18/E6-1 -> -0.19490262 | I18: =+H18 -> -0.19490262
A19: 16132 | C19: 35004 | D19: =+'BRL e USD Chart'!$D19 -> 69.975628 | E19: =+'BRL e USD Chart'!$D19 -> 69.975628 | F19: =+E19/E18-1 -> -0.014487041 | G19: =+F19 -> -0.014487041 | H19: =+E19/E7-1 -> -0.1842706 | I19: =+H19 -> -0.1842706
A20: 16163 | C20: 35034 | D20: =+'BRL e USD Chart'!$D20 -> 68.900776 | E20: =+'BRL e USD Chart'!$D20 -> 68.900776 | F20: =+E20/E19-1 -> -0.015360378 | G20: =+F20 -> -0.015360378 | H20: =+E20/E8-1 -> -0.1830658 | I20: =+H20 -> -0.1830658
A21: 16193 | C21: 35065 | D21: =+'BRL e USD Chart'!$D21 -> 67.989714 | E21: =+'BRL e USD Chart'!$D21 -> 67.989714 | F21: =+E21/E20-1 -> -0.013222814 | G21: =+F21 -> -0.013222814 | H21: =+E21/E9-1 -> -0.18016373 | I21: =+H21 -> -0.18016373
A22: 16224 | C22: 35096 | D22: =+'BRL e USD Chart'!$D22 -> 67.296559 | E22: =+'BRL e USD Chart'!$D22 -> 67.296559 | F22: =+E22/E21-1 -> -0.010194992 | G22: =+F22 -> -0.010194992 | H22: =+E22/E10-1 -> -0.18024488 | I22: =+H22 -> -0.18024488
A23: 16254 | C23: 35125 | D23: =+'BRL e USD Chart'!$D23 -> 67.061843 | E23: =+'BRL e USD Chart'!$D23 -> 67.061843 | F23: =+E23/E22-1 -> -0.0034877927 | G23: =+F23 -> -0.0034877927 | H23: =+E23/E11-1 -> -0.17044213 | I23: =+H23 -> -0.17044213
A24: 16285 | C24: 35156 | D24: =+'BRL e USD Chart'!$D24 -> 66.227378 | E24: =+'BRL e USD Chart'!$D24 -> 66.227378 | F24: =+E24/E23-1 -> -0.012443215 | G24: =+F24 -> -0.012443215 | H24: =+E24/E12-1 -> -0.16085707 | I24: =+H24 -> -0.16085707
A25: 16316 | C25: 35186 | D25: =+'BRL e USD Chart'!$D25 -> 65.429142 | E25: =+'BRL e USD Chart'!$D25 -> 65.429142 | F25: =+E25/E24-1 -> -0.012052954 | G25: =+F25 -> -0.012052954 | H25: =+E25/E13-1 -> -0.14883615 | I25: =+H25 -> -0.14883615
... A295: 24532 | C295: 43405 | D295: =+'BRL e USD Chart'!$D295 -> 16.832454 | E295: =+'BRL e USD Chart'!$D295 -> 16.832454 | F295: =+E295/E294-1 -> 0.0021044193 | G295: =+F295 -> 0.0021044193 | H295: =+E295/E283-1 -> -0.038885662 | I295: =+H295 -> -0.038885662
A296: 24563 | C296: 43435 | D296: ='BRL IPCA'!$K960 -> 100 | E296: ='BRL IPCA'!$K960 -> 100 | F296: =+E296/E295-1 -> 4.9409046 | G296: =+F296 -> 4.9409046 | H296: =+E296/E284-1 -> 4.7350121 | I296: =+H296 -> 4.7350121
A297: 24593 | C297: 43466 | D297: ='BRL IPCA'!$K961 -> 99.681021 | E297: ='BRL IPCA'!$K961 -> 99.681021 | F297: =+E297/E296-1 -> -0.0031897927 | G297: =+F297 -> -0.0031897927 | H297: =+E297/E285-1 -> 4.733297 | I297: =+H297 -> 4.733297
A298: 24624 | C298: 43497 | D298: ='BRL IPCA'!$K962 -> 99.254228 | E298: ='BRL IPCA'!$K962 -> 99.254228 | F298: =+E298/E297-1 -> -0.0042815892 | G298: =+F298 -> -0.0042815892 | H298: =+E298/E286-1 -> 4.7270174 | I298: =+H298 -> 4.7270174
A299: 24654 | C299: 43525 | D299: ='BRL IPCA'!$K963 -> 98.515362 | E299: ='BRL IPCA'!$K963 -> 98.515362 | F299: =+E299/E298-1 -> -0.0074441687 | G299: =+F299 -> -0.0074441687 | H299: =+E299/E287-1 -> 4.6895005 | I299: =+H299 -> 4.6895005
A300: 24685 | C300: 43556 | D300: ='BRL IPCA'!$K964 -> 97.957007 | E300: ='BRL IPCA'!$K964 -> 97.957007 | F300: =+E300/E299-1 -> -0.0056676941 | G300: =+F300 -> -0.0056676941 | H300: =+E300/E288-1 -> 4.6697001 | I300: =+H300 -> 4.6697001
A301: 24716 | C301: 43586 | D301: ='BRL IPCA'!$K965 -> 97.829829 | E301: ='BRL IPCA'!$K965 -> 97.829829 | F301: =+E301/E300-1 -> -0.0012983122 | G301: =+F301 -> -0.0012983122 | H301: =+E301/E289-1 -> 4.6849884 | I301: =+H301 -> 4.6849884
A302: 24746 | C302: 43617 | D302: ='BRL IPCA'!$K966 -> 97.820047 | E302: ='BRL IPCA'!$K966 -> 97.820047 | F302: =+E302/E301-1 -> -9.9990001e-05 | G302: =+F302 -> -9.9990001e-05 | H302: =+E302/E290-1 -> 4.7560437 | I302: =+H302 -> 4.7560437
A303: 24777 | C303: 43647 | D303: ='BRL IPCA'!$K967 -> 97.634541 | E303: ='BRL IPCA'!$K967 -> 97.634541 | F303: =+E303/E302-1 -> -0.0018963968 | G303: =+F303 -> -0.0018963968 | H303: =+E303/E291-1 -> 4.7640868 | I303: =+H303 -> 4.7640868
A304: 24807 | C304: 43678 | D304: ='BRL IPCA'!$K968 -> 97.527261 | E304: ='BRL IPCA'!$K968 -> 97.527261 | F304: =+E304/E303-1 -> -0.0010987913 | G304: =+F304 -> -0.0010987913 | H304: =+E304/E292-1 -> 4.7525713 | I304: =+H304 -> 4.7525713
A305: 24838 | C305: 43709 | D305: ='BRL IPCA'!$K969 -> 97.566288 | E305: ='BRL IPCA'!$K969 -> 97.566288 | F305: =+E305/E304-1 -> 0.00040016006 | G305: =+F305 -> 0.00040016006 | H305: =+E305/E293-1 -> 4.7824967 | I305: =+H305 -> 4.7824967
A306: 24869 | C306: 43739 | D306: ='BRL IPCA'!$K970 -> 97.468819 | E306: ='BRL IPCA'!$K970 -> 97.468819 | F306: =+E306/E305-1 -> -0.000999001 | G306: =+F306 -> -0.000999001 | H306: =+E306/E294-1 -> 4.8027152 | I306: =+H306 -> 4.8027152
A307: 24898 | C307: 43770 | D307: ='BRL IPCA'!$K971 -> 96.97425 | E307: ='BRL IPCA'!$K971 -> 96.97425 | F307: =+E307/E306-1 -> -0.005074122 | G307: =+F307 -> -0.005074122 | H307: =+E307/E295-1 -> 4.7611476 | I307: =+H307 -> 4.7611476
... A368: 26755 | C368: 45627 | D368: ='BRL IPCA'!$K1032 -> 71.834783 | E368: ='BRL IPCA'!$K1032 -> 71.834783 | F368: =+E368/E367-1 -> -0.0051730999 | G368: =+F368 -> -0.0051730999 | H368: =+E368/E356-1 -> -0.046086388 | I368: =+H368 -> -0.046086388
A369: 26785
A370: 26816
A371: 26846
A372: 26877
A373: 26908
A374: 26938
A375: 26969
A376: 26999
A377: 27030
A378: 27061
A379: 27089
A380: 27120
... A405: 27881
A406: 27912 | I406: -0.1 | J406: =((1+J407)^(12))-1 -> -0.058377193 | K406: =+D359/D239-1 -> 2.3766453 | L406: meses | M406: =+'USD PP Chart'!B1347/'USD PP Chart'!B1227-1 -> -0.24349882
A407: 27942 | I407: =((1+I406)^(0.0833333333333333))-1 -> -0.008741611 | J407: -0.005 | K407: =((1+K406)^(1/L407))-1 -> 0.01019228 | L407: 120 | M407: =((1+M406)^(1/L407))-1 -> -0.0023227248
A408: 27973
A409: 28004
A410: 28034 | L410: =10*12 -> 120
A411: 28065
A412: 28095
A413: 28126
A414: 28157
A415: 28185
A416: 28216
A417: 28246
A418: 28277
A419: 28307
A420: 28338
A421: 28369
A422: 28399
... A946: 44348

Sheet USD PP Chart
A1: FRED Graph Observations
A2: Federal Reserve Economic Data
A3: Link: https://fred.stlouisfed.org
A4: Help: https://fredhelp.stlouisfed.org
A5: Economic Research Division
A6: Federal Reserve Bank of St. Louis
A8: CUUR0000SA0R | D8: Consumer Price Index for All Urban Consumers: Purchasing Power of the Consumer Dollar in U.S. City Average, Index 1982-1984=100, Monthly, Not Seasonally Adjusted
A10: Frequency: Monthly | B10: 100 | C10: 100
A11: Date | B11: Dólar (dez/12 a mar/26) | C11: Dólar (dez/12 a mar/26) | D11: CUUR0000SA0R
A12: 4719 | B12: 100 | C12: =+B12 -> 100
A13: 4750 | B13: =D13/$D$13*$B$12 -> 100 | C13: =+B13 -> 100 | D13: 1017.8
A14: 4781 | B14: =D14/$D$13*$B$12 -> 100.3537 | C14: =+B14 -> 100.3537 | D14: 1021.4
A15: 4809 | B15: =D15/$D$13*$B$12 -> 100.3537 | C15: =+B15 -> 100.3537 | D15: 1021.4
A16: 4840 | B16: =D16/$D$13*$B$12 -> 100 | C16: =+B16 -> 100 | D16: 1017.8
A17: 4870 | B17: =D17/$D$13*$B$12 -> 100.70741 | C17: =+B17 -> 100.70741 | D17: 1025
A18: 4901 | B18: =D18/$D$13*$B$12 -> 100.3537 | C18: =+B18 -> 100.3537 | D18: 1021.4
A19: 4931 | B19: =D19/$D$13*$B$12 -> 99.331892 | C19: =+B19 -> 99.331892 | D19: 1011
A20: 4962 | B20: =D20/$D$13*$B$12 -> 98.683435 | C20: =+B20 -> 98.683435 | D20: 1004.4
A21: 4993 | B21: =D21/$D$13*$B$12 -> 98.329731 | C21: =+B21 -> 98.329731 | D21: 1000.8
A22: 5023 | B22: =D22/$D$13*$B$12 -> 97.681273 | C22: =+B22 -> 97.681273 | D22: 994.2
A23: 5054 | B23: =D23/$D$13*$B$12 -> 97.357045 | C23: =+B23 -> 97.357045 | D23: 990.9
A24: 5084 | B24: =D24/$D$13*$B$12 -> 97.681273 | C24: =+B24 -> 97.681273 | D24: 994.2
... A1317: 44440 | B1317: =D1317/$D$13*$B$12 -> 3.5861662 | C1317: =+B1317 -> 3.5861662 | D1317: 36.5
A1318: 44470 | B1318: =D1318/$D$13*$B$12 -> 3.5566909 | C1318: =+B1318 -> 3.5566909 | D1318: 36.2 | F1318: =100-C1325 -> 96.639811
A1319: 44501 | B1319: =D1319/$D$13*$B$12 -> 3.5370407 | C1319: =+B1319 -> 3.5370407 | D1319: 36 | F1319: =+B1325 -> 3.3601886
A1320: 44531 | B1320: =D1320/$D$13*$B$12 -> 3.5272156 | C1320: =+B1320 -> 3.5272156 | D1320: 35.9
A1321: 44562 | B1321: =D1321/$D$13*$B$12 -> 3.4977402 | C1321: =+B1321 -> 3.4977402 | D1321: 35.6
A1322: 44593 | B1322: =D1322/$D$13*$B$12 -> 3.4584398 | C1322: =+B1322 -> 3.4584398 | D1322: 35.2
A1323: 44621 | B1323: =D1323/$D$13*$B$12 -> 3.4191393 | C1323: =+B1323 -> 3.4191393 | D1323: 34.8
A1324: 44652 | B1324: =D1324/$D$13*$B$12 -> 3.3994891 | C1324: =+B1324 -> 3.3994891 | D1324: 34.6
A1325: 44682 | B1325: =D1325/$D$13*$B$12 -> 3.3601886 | C1325: =+B1325 -> 3.3601886 | D1325: 34.2
A1326: 44713 | B1326: =D1326/$D$13*$B$12 -> 3.3110631 | C1326: =+B1326 -> 3.3110631 | D1326: 33.7
A1327: 44743 | B1327: =D1327/$D$13*$B$12 -> 3.3208882 | C1327: =+B1327 -> 3.3208882 | D1327: 33.8
A1328: 44774 | B1328: =D1328/$D$13*$B$12 -> 3.3208882 | C1328: =+B1328 -> 3.3208882 | D1328: 33.8
A1329: 44805 | B1329: =D1329/$D$13*$B$12 -> 3.3110631 | C1329: =+B1329 -> 3.3110631 | D1329: 33.7
A1330: 44835 | B1330: =D1330/$D$13*$B$12 -> 3.301238 | C1330: =+B1330 -> 3.301238 | D1330: 33.6
A1331: 44866 | B1331: =D1331/$D$13*$B$12 -> 3.301238 | C1331: =+B1331 -> 3.301238 | D1331: 33.6
... A1365: 45901 | B1365: =D1365/$D$13*$B$12 -> 3.0261348 | C1365: =+B1365 -> 3.0261348 | D1365: 30.8
A1366: 45931
A1367: 45962 | B1367: =D1367/$D$13*$B$12 -> 3.0359599 | C1367: =+B1367 -> 3.0359599 | D1367: 30.9
A1368: 45992 | B1368: =D1368/$D$13*$B$12 -> 3.0359599 | C1368: =+B1368 -> 3.0359599 | D1368: 30.9
A1369: 46023 | B1369: =D1369/$D$13*$B$12 -> 3.0163097 | C1369: =+B1369 -> 3.0163097 | D1369: 30.7
A1370: 46054 | B1370: =D1370/$D$13*$B$12 -> 3.0064846 | C1370: =+B1370 -> 3.0064846 | D1370: 30.6
A1371: 46082 | B1371: =D1371/$D$13*$B$12 -> 2.9770092 | C1371: =+B1371 -> 2.9770092 | D1371: 30.3

Sheet FRED Graph Chart (2)
A1: FRED Graph Observations
A2: Federal Reserve Economic Data
A3: Link: https://fred.stlouisfed.org
A4: Help: https://fredhelp.stlouisfed.org
A5: Economic Research Division
A6: Federal Reserve Bank of St. Louis
A8: CUUR0000SA0R | D8: Consumer Price Index for All Urban Consumers: Purchasing Power of the Consumer Dollar in U.S. City Average, Index 1982-1984=100, Monthly, Not Seasonally Adjusted
A10: Frequency: Monthly | B10: 100 | C10: 100
A11: Date | B11: Dollar PP (Dec. '12 to Oct. '21) | C11: Dollar PP (Dec. '12 to Oct. '21) | D11: CUUR0000SA0R
A12: 4719 | B12: 100 | C12: =+B12 -> 100
A13: 4750 | B13: =D13/$D$13*$B$12 -> 100 | C13: =+B13 -> 100 | D13: =+'USD PP Chart'!D13 -> 1017.8
A14: 4781 | B14: =D14/$D$13*$B$12 -> 100.3537 | C14: =+B14 -> 100.3537 | D14: =+'USD PP Chart'!D14 -> 1021.4
A15: 4809 | B15: =D15/$D$13*$B$12 -> 100.3537 | C15: =+B15 -> 100.3537 | D15: =+'USD PP Chart'!D15 -> 1021.4
A16: 4840 | B16: =D16/$D$13*$B$12 -> 100 | C16: =+B16 -> 100 | D16: =+'USD PP Chart'!D16 -> 1017.8
A17: 4870 | B17: =D17/$D$13*$B$12 -> 100.70741 | C17: =+B17 -> 100.70741 | D17: =+'USD PP Chart'!D17 -> 1025
A18: 4901 | B18: =D18/$D$13*$B$12 -> 100.3537 | C18: =+B18 -> 100.3537 | D18: =+'USD PP Chart'!D18 -> 1021.4
A19: 4931 | B19: =D19/$D$13*$B$12 -> 99.331892 | C19: =+B19 -> 99.331892 | D19: =+'USD PP Chart'!D19 -> 1011
A20: 4962 | B20: =D20/$D$13*$B$12 -> 98.683435 | C20: =+B20 -> 98.683435 | D20: =+'USD PP Chart'!D20 -> 1004.4
A21: 4993 | B21: =D21/$D$13*$B$12 -> 98.329731 | C21: =+B21 -> 98.329731 | D21: =+'USD PP Chart'!D21 -> 1000.8
A22: 5023 | B22: =D22/$D$13*$B$12 -> 97.681273 | C22: =+B22 -> 97.681273 | D22: =+'USD PP Chart'!D22 -> 994.2
A23: 5054 | B23: =D23/$D$13*$B$12 -> 97.357045 | C23: =+B23 -> 97.357045 | D23: =+'USD PP Chart'!D23 -> 990.9
A24: 5084 | B24: =D24/$D$13*$B$12 -> 97.681273 | C24: =+B24 -> 97.681273 | D24: =+'USD PP Chart'!D24 -> 994.2
... A1317: 44440 | B1317: =D1317/$D$13*$B$12 -> 3.5861662 | C1317: =+B1317 -> 3.5861662 | D1317: =+'USD PP Chart'!D1317 -> 36.5
A1318: 44470 | B1318: =D1318/$D$13*$B$12 -> 3.5566909 | C1318: =+B1318 -> 3.5566909 | D1318: =+'USD PP Chart'!D1318 -> 36.2 | F1318: =100-C1317 -> 96.413834
A1319: 44501 | B1319: =D1319/$D$13*$B$12 -> 3.5370407 | C1319: =+B1319 -> 3.5370407 | D1319: =+'USD PP Chart'!D1319 -> 36
A1320: 44531 | B1320: =D1320/$D$13*$B$12 -> 3.5272156 | C1320: =+B1320 -> 3.5272156 | D1320: =+'USD PP Chart'!D1320 -> 35.9
A1321: 44562 | B1321: =D1321/$D$13*$B$12 -> 3.4977402 | C1321: =+B1321 -> 3.4977402 | D1321: =+'USD PP Chart'!D1321 -> 35.6
A1322: 44593 | B1322: =D1322/$D$13*$B$12 -> 3.4584398 | C1322: =+B1322 -> 3.4584398 | D1322: =+'USD PP Chart'!D1322 -> 35.2
A1323: 44621 | B1323: =D1323/$D$13*$B$12 -> 3.4191393 | C1323: =+B1323 -> 3.4191393 | D1323: =+'USD PP Chart'!D1323 -> 34.8
A1324: 44652 | B1324: =D1324/$D$13*$B$12 -> 3.3994891 | C1324: =+B1324 -> 3.3994891 | D1324: =+'USD PP Chart'!D1324 -> 34.6
A1325: 44682 | B1325: =D1325/$D$13*$B$12 -> 3.3601886 | C1325: =+B1325 -> 3.3601886 | D1325: =+'USD PP Chart'!D1325 -> 34.2
A1326: 44713 | B1326: =D1326/$D$13*$B$12 -> 3.3110631 | C1326: =+B1326 -> 3.3110631 | D1326: =+'USD PP Chart'!D1326 -> 33.7
A1327: 44743 | B1327: =D1327/$D$13*$B$12 -> 3.3208882 | C1327: =+B1327 -> 3.3208882 | D1327: =+'USD PP Chart'!D1327 -> 33.8
A1328: 44774 | B1328: =D1328/$D$13*$B$12 -> 3.3208882 | C1328: =+B1328 -> 3.3208882 | D1328: =+'USD PP Chart'!D1328 -> 33.8
A1329: 44805 | B1329: =D1329/$D$13*$B$12 -> 3.3110631 | C1329: =+B1329 -> 3.3110631 | D1329: =+'USD PP Chart'!D1329 -> 33.7
A1330: 44835 | B1330: =D1330/$D$13*$B$12 -> 3.301238 | C1330: =+B1330 -> 3.301238 | D1330: =+'USD PP Chart'!D1330 -> 33.6
... A1344: 45261 | B1344: =D1344/$D$13*$B$12 -> 3.2029868 | C1344: =+B1344 -> 3.2029868 | D1344: =+'USD PP Chart'!D1344 -> 32.6

Sheet USD PP 1994
A1: FRED Graph Observations
A2: Federal Reserve Economic Data
